[
  {
    "start": 360,
    "end": 2513,
    "text": "こんにちは、Skedeval チャンネルへようこそ。"
  },
  {
    "start": 2569,
    "end": 14545,
    "text": "今日は、市場に出回っているほぼすべての B650 マザーボードをランキングして、次回または最初の AMD ゲーミング PC に最適なものを確認します。"
  },
  {
    "start": 14665,
    "end": 19017,
    "text": "B650 マザーボードはたくさんあります。"
  },
  {
    "start": 19121,
    "end": 23713,
    "text": "おそらく、オプションの多さに圧倒されてしまうかもしれません。"
  },
  {
    "start": 23849,
    "end": 31557,
    "text": "だからこそ、ビデオスケジュールを 4 日遅らせてでも、この Tier リストを丹念に作成しています。"
  },
  {
    "start": 31621,
    "end": 39645,
    "text": "これらの B650 マザーボードのうち 49 個を、誰でも理解できるわかりやすい階層リストに分類します。"
  },
  {
    "start": 39725,
    "end": 47795,
    "text": "これにより、次回または最初の AMD ベースのゲーム PC にどの B650 マザーボードを再度選択する必要があるかが明確になるはずです。"
  },
  {
    "start": 47868,
    "end": 51444,
    "text": "それに対して私は一つ言いたいのですが、どういたしまして。"
  },
  {
    "start": 51517,
    "end": 63969,
    "text": "2 つ目は、この層全体で私が推奨する B650 マザーボードのいずれかをチェックしてみたい場合は、以下の説明にすべてのリンクと、私の Web サイト PCBuilds GG を掲載しています。"
  },
  {
    "start": 64057,
    "end": 78441,
    "text": "ゲーム用 PC を構築したい場合、またはその Web サイトにある高評価のマザーボードを中心とした特定の予算で最適な構築リストを知りたい場合は、PCbuilds GG がさまざまな予算とさまざまな用途に対応しています。"
  },
  {
    "start": 78553,
    "end": 85777,
    "text": "これは、初めて PC を構築したいが、特定の予算で最適な構築リストがわからない場合に再度使用できる非常に優れたツールです。"
  },
  {
    "start": 85841,
    "end": 87361,
    "text": "それがそのウェブサイトが存在する理由です。"
  },
  {
    "start": 87473,
    "end": 92337,
    "text": "これで十分なので、階層リストに進みますが、その前にいくつかのコンテキストを提供する必要があります。"
  },
  {
    "start": 92441,
    "end": 95009,
    "text": "さあ、今すぐこれを正しましょう。"
  },
  {
    "start": 95097,
    "end": 101697,
    "text": "正直なところ、ゲーミング PC にどの B650 マザーボードを選択しても、それほど大きな違いはありません。"
  },
  {
    "start": 101801,
    "end": 102793,
    "text": "本当にそうではありません。"
  },
  {
    "start": 102929,
    "end": 103817,
    "text": "その理由をお話ししましょう。"
  },
  {
    "start": 103881,
    "end": 114483,
    "text": "これらの B650 マザーボードを中心としたゲーミング PC の構築を計画している人の大多数は、おそらく 6 コアまたは 8 コアの Ryzen CPU を選択するでしょう。"
  },
  {
    "start": 114567,
    "end": 127129,
    "text": "Ryzen 5 9600X や Ryzen 7 7800X 3D のようなものです。公平を期すために言うと、2024 年以降でも、ゲーム PC に実際には 8 コア以上は必要ありません。"
  },
  {
    "start": 127217,
    "end": 134129,
    "text": "12 コアまたは 16 コアの CPU を使用している場合、ほとんどの場合、1 秒あたりのフレーム数は向上しません。"
  },
  {
    "start": 134202,
    "end": 135963,
    "text": "8コアCPU以上。"
  },
  {
    "start": 136036,
    "end": 152887,
    "text": "私がこれについて言及する理由は、6 コアと 8 コアの CPU は、非常に電力を消費する 12 コアと 16 コアの CPU に比べて消費電力がはるかに少ないためです。これらの CPU は、実を言うとマーケティングのせいで常に押しつけられ、常に売り込まれています。最高の中の最高として。"
  },
  {
    "start": 152951,
    "end": 162927,
    "text": "ゲーム用の実際のベンチマークを見ると、先ほども言いましたが、16 コアや 12 コアの CPU は、8 コアや 6 コアの CPU に比べてそれほど意味のあるパフォーマンスを達成しません。"
  },
  {
    "start": 162991,
    "end": 164201,
    "text": "なぜ私がこれを言うのですか？"
  },
  {
    "start": 164343,
    "end": 170373,
    "text": "それは、ゲームではほとんどの場合、CPU に大きなストレスを与えることは決してないからです。"
  },
  {
    "start": 170469,
    "end": 180573,
    "text": "PC でゲームをプレイする場合、ほとんどの場合、PC ゲームのグラフィックを計算するグラフィック カードに負荷がかかることになるからです。"
  },
  {
    "start": 180669,
    "end": 187053,
    "text": "CPU は、グラフィックス カードと比べて、ゲームにおいて思っているほど大きな役割を果たしません。"
  },
  {
    "start": 187109,
    "end": 190057,
    "text": "Tier リストの前に、なぜこのようなことについてすぐに話したいのでしょうか?"
  },
  {
    "start": 190141,
    "end": 196993,
    "text": "なぜなら、この階層リストにある C 階層以上のマザーボードのほとんどは、非常に優れた性能を発揮するからです。"
  },
  {
    "start": 197129,
    "end": 204145,
    "text": "だって、先ほども言いましたが、皆さんがゲーム用のこれらのマザーボードに 16 コアや 12 コアの非常に大きな CPU を搭載するとは期待していません。"
  },
  {
    "start": 204225,
    "end": 206441,
    "text": "6コアか8コアのCPUを期待しています。"
  },
  {
    "start": 206513,
    "end": 214433,
    "text": "たとえこれらのマルチコア 12 または 16 コア CPU のいずれかを投入したい場合でも、ゲームには B 層以上でも問題ありません。"
  },
  {
    "start": 214489,
    "end": 228807,
    "text": "ここで少し曖昧になりますが、レンダリングを必要とするゲームや CPU ベースのワークロードを実行し、ストレスのかかるものに CPU を利用したい場合は、どのマザーボードを選択するかに注意してください。"
  },
  {
    "start": 228871,
    "end": 236559,
    "text": "これはシミュレーションかもしれないし、計算作業かもしれません。あるいは、GPU の代わりに CPU を使ってビデオをレンダリングするかどうかを決定することかもしれません。"
  },
  {
    "start": 236687,
    "end": 240559,
    "text": "つまり、CPU にほぼ 100% の負荷がかかることになります。"
  },
  {
    "start": 240687,
    "end": 245623,
    "text": "ここで、どのマザーボードが他のマザーボードと比べて違いを生むかがわかります。"
  },
  {
    "start": 245759,
    "end": 255599,
    "text": "特定のマザーボードは、特に CPU ベースのワークロード アプリケーションの場合、他のマザーボードよりも多くの電力を消費するコア数の高い CPU を処理できます。"
  },
  {
    "start": 255767,
    "end": 259343,
    "text": "マザーボードの選択によって多少の違いが生じるのはこの点です。"
  },
  {
    "start": 259399,
    "end": 268375,
    "text": "ゲーマーだけでなく、CPU を使用するワークステーション アプリケーションを日常的に使用する人を対象とします。"
  },
  {
    "start": 268495,
    "end": 276277,
    "text": "要約すると、あなたが PC ゲーマーで、ゲーミング PC C 層以上の 6 コアまたは 8 コア CPU を使用している場合は、問題ありません。"
  },
  {
    "start": 276334,
    "end": 284389,
    "text": "あなたが PC ゲーマーで、ゲーミング PC に 12 コアまたは 16 コアの CPU を使用したい場合は、B 層以上で問題ありません。"
  },
  {
    "start": 284437,
    "end": 296277,
    "text": "さて、あなたがゲーマーであり、たとえば 12 または 16 コア CPU を搭載した PC で CPU ワークロード アプリケーションを実行したいと考えている愛好家であれば、1 層以上に注目する必要があります。"
  },
  {
    "start": 296341,
    "end": 308161,
    "text": "さらに言えば、マザーボードに少なくとも 150 ドルを費やした場合、Asus B650 Prime でない限り、悪い B650 マザーボードを手に入れることはできません。"
  },
  {
    "start": 308273,
    "end": 312497,
    "text": "さらに、それはマザーボードが悪いので、その理由についてはビデオの後半で説明します。"
  },
  {
    "start": 312561,
    "end": 314457,
    "text": "はい、はい、心配しないでください。ティアリストに進みます。"
  },
  {
    "start": 314481,
    "end": 315409,
    "text": "すぐに取り掛かります。"
  },
  {
    "start": 315457,
    "end": 319273,
    "text": "これらのマザーボードの選択を 3 つの主な要素から等級付けしていきます。"
  },
  {
    "start": 319369,
    "end": 324161,
    "text": "まず、マザーボード上の VRM とヒートシンクがどれほど優れているかです。"
  },
  {
    "start": 324233,
    "end": 331463,
    "text": "これは基本的に、このマザーボードが CPU から電力をどの程度効率的に取り込み、その熱をマザーボードから放散できるかを示しています。"
  },
  {
    "start": 331569,
    "end": 341462,
    "text": "第二に、マザーボードが将来性を考慮して PCIe Gen 5.0 をサポートしているのであれば、PCIe Gen 5.0 をサポートする次世代のグラフィックス カードがすぐに入手できることになります。"
  },
  {
    "start": 341545,
    "end": 361139,
    "text": "また、マザーボードが M2 SSD で PCIe Gen 5.0 をサポートしている場合、それはかなりやりすぎであることは承知していますが、繰り返しになりますが、将来のアップグレードに備えて将来性のあるマザーボードを用意するという精神から、PCI Gen を備えたマザーボードが必要になる可能性があります。非常に高速な M2 SSD 用の 5.0 M2 コネクタ。"
  },
  {
    "start": 361187,
    "end": 364771,
    "text": "書き込むもの、またはブートドライブとして機能するものが必要な場合。"
  },
  {
    "start": 364843,
    "end": 370523,
    "text": "それ以外には、マザーボードに搭載されている IO の量など、非常に小さな違いがあります。"
  },
  {
    "start": 370579,
    "end": 373963,
    "text": "先ほども言いましたが、どの B650 マザーボードでも間違いはありません。"
  },
  {
    "start": 374019,
    "end": 378763,
    "text": "いくつかは絶対に避けたいものですが、それについては Tier リストで説明します。"
  },
  {
    "start": 378859,
    "end": 381035,
    "text": "さて、Tierリストがここにあります。"
  },
  {
    "start": 381075,
    "end": 383587,
    "text": "これから取り上げていきますが、最終的にはビデオになります。"
  },
  {
    "start": 383651,
    "end": 386727,
    "text": "まず最初に 2 つの大きな声を上げたいと思います。"
  },
  {
    "start": 386811,
    "end": 392706,
    "text": "必ずしも MSI、Gigabyte、Asus、ASRock の 4 大メーカーからマザーボードを入手する必要はありません。"
  },
  {
    "start": 392767,
    "end": 397215,
    "text": "たとえば、AliExpress 上の Colorful などのブランドのベンダーから入手できます。"
  },
  {
    "start": 397295,
    "end": 402007,
    "text": "ビッグ 4 以外に存在する可能性のある他のマザーボード ブランドについて詳しく知りたい場合は、"
  },
  {
    "start": 402071,
    "end": 419219,
    "text": "それから、AliExpress で見つけた 2 つのマザーボードについて詳しく説明している Tech Yes City のビデオをチェックすることをお勧めします。このビデオでは、世界の地域によっては、いくつかの価値あるオプションよりも低価格の B650 マザーボードを購入する方が良い可能性があります。この Tier リストで取り上げます。"
  },
  {
    "start": 419267,
    "end": 423675,
    "text": "それに関するブライアンのビデオをチェックしたい場合は、以下の説明にリンクを貼っておきます。"
  },
  {
    "start": 423755,
    "end": 430203,
    "text": "また、特にこれに関しては、さらに上を行く人たちに大きなエールを送りたいと思います。"
  },
  {
    "start": 430259,
    "end": 453543,
    "text": "これはマザーボードのテストであり、ハードウェアが箱から出されていない状態であり、さまざまなマザーボードのベンチマークを紹介する優れた一連の AMD マザーボード ガイド ビデオがあり、この Tier リスト ビデオで説明する内容以上のものをカバーしており、これらのマザーボードがどの程度優れているかについて詳しく説明しています。マザーボードは特定の CPU を 100% の負荷で動作させ、どのマザーボードが特定のテストに合格するかを確認または拒否することもできます。"
  },
  {
    "start": 453599,
    "end": 465911,
    "text": "このビデオで気に入った特定のマザーボードがあり、それに関する技術情報やパフォーマンスの数値をさらに知りたい場合は、お気軽にそのマザーボードを手に取り、ビデオをチェックして、さらに詳しく学びましょう。"
  },
  {
    "start": 465943,
    "end": 471103,
    "text": "作品もチェックしてみたい場合は、以下の説明にそれらのビデオのリンクも載せておきます。"
  },
  {
    "start": 471199,
    "end": 480431,
    "text": "さて、まずは安いものから順に価格を上げていくと、ASRock B650M H M2 Plus があります。"
  },
  {
    "start": 480503,
    "end": 481831,
    "text": "これをどこに置きますか？"
  },
  {
    "start": 481903,
    "end": 485639,
    "text": "さて、Tier リストでは少し早いですが、F Tier です。"
  },
  {
    "start": 485727,
    "end": 488263,
    "text": "これがこのビデオの残りの部分の合言葉になります。"
  },
  {
    "start": 488359,
    "end": 493655,
    "text": "B650 マザーボードに関しては 100 ドルで、支払った金額に見合ったものを手に入れることができます。"
  },
  {
    "start": 493815,
    "end": 498407,
    "text": "たとえそれがそれほど安いものであっても、なぜそれが最適な選択ではないのかを見てみましょう。"
  },
  {
    "start": 498471,
    "end": 505047,
    "text": "これは 6 プラス 1 プラス 1 のパワーフェイスのデザインで、実際には 100 ドルとしてはそれほど粗末なものではありません。"
  },
  {
    "start": 505111,
    "end": 511293,
    "text": "見てください、VRM ヒートスーツのシンクはかなり小さくて、もしあったとしても哀れなものです。"
  },
  {
    "start": 511389,
    "end": 527997,
    "text": "ベンチマークによると、このマザーボードは確実に発熱し、特にコア数が 12 および 16 の領域に入ると、CPU のパフォーマンスが確実に低下します。率直に言って、これは 1000 億 650 ドルのマザーボードとしてはまったく非現実的です。"
  },
  {
    "start": 528061,
    "end": 532637,
    "text": "つまり、ゲーミング PC よりも多くの IO が必要だということを見てください。"
  },
  {
    "start": 532701,
    "end": 537397,
    "text": "すべての USB 周辺機器とワイヤレス デバイスには、これ以上のものが必要になります。"
  },
  {
    "start": 537501,
    "end": 541597,
    "text": "先ほども言いましたが、支払ったものは得られます。それが F 層の最下位にある理由です。"
  },
  {
    "start": 541661,
    "end": 544797,
    "text": "さて、ギガバイトのB650MKはどうでしょうか？"
  },
  {
    "start": 544901,
    "end": 549405,
    "text": "さて、これは少し興味深いので、このスペックシートを調べてみましょう。"
  },
  {
    "start": 549485,
    "end": 556269,
    "text": "理論上、これは 8 プラス 2 プラス 1 の電源フェーズ設計になっており、素晴らしいサウンドです。"
  },
  {
    "start": 556357,
    "end": 562101,
    "text": "マザーボード自体を見ても、VRM の大部分の上にきちんとしたヒートシンクが付いています。"
  },
  {
    "start": 562173,
    "end": 576329,
    "text": "残念ながら、マルチコア数の CPU を搭載したこのマザーボードのベンチマークを見ると、発熱が多すぎて CPU に十分な電力が供給されていないため、CPU のパフォーマンスが低下することはありません。"
  },
  {
    "start": 576417,
    "end": 587177,
    "text": "このマザーボードは、8 プラス 2 プラス 1 のパワー フェイス デザインで紙の上ではクールに見えますが、これも F 層の最下位で ASRock B650M に加わる必要があります。"
  },
  {
    "start": 587321,
    "end": 592049,
    "text": "さて、ギガバイトの B650M D3HP AX はどうでしょうか?"
  },
  {
    "start": 592137,
    "end": 593649,
    "text": "うわー、文字がたくさん。"
  },
  {
    "start": 593817,
    "end": 595625,
    "text": "こちらもアタリになります。"
  },
  {
    "start": 595665,
    "end": 596481,
    "text": "いいえ。"
  },
  {
    "start": 596673,
    "end": 600049,
    "text": "B650MKと同様の状況です。"
  },
  {
    "start": 600137,
    "end": 605689,
    "text": "ただし、もう一度このマザーボードのスペックシートを見ると、これは約 130 ドル程度です。"
  },
  {
    "start": 605776,
    "end": 608713,
    "text": "VRM レイアウトを見てみましょう。"
  },
  {
    "start": 608800,
    "end": 610485,
    "text": "52 2です。"
  },
  {
    "start": 610565,
    "end": 624709,
    "text": "つまり、ゲーム用の 6 コアまたは 8 コアの CPU には問題ありませんが、この階層リストから外れて最終的にどこに行き着くかは、今後登場する他の多くの B650 マザーボードと比較するとかなり残念です。この Tier リストで話しています。"
  },
  {
    "start": 624797,
    "end": 629477,
    "text": "先ほども言いましたが、6 コア CPU を搭載した低価格のゲーム PC としてはまったく問題ありません。"
  },
  {
    "start": 629541,
    "end": 634193,
    "text": "20 ドル高くても、これより優れたマザーボードを入手できます。"
  },
  {
    "start": 634249,
    "end": 639473,
    "text": "これも、F 層の 3 つのマザーボードに再び加わることになります。"
  },
  {
    "start": 639569,
    "end": 641113,
    "text": "素晴らしいスタートを切りました。"
  },
  {
    "start": 641209,
    "end": 642825,
    "text": "MSIはどうですか？"
  },
  {
    "start": 642905,
    "end": 649121,
    "text": "最も安価な B650 マザーボードの 1 つである B650MP でさらに改善できるでしょうか?"
  },
  {
    "start": 649273,
    "end": 651305,
    "text": "そうですね。"
  },
  {
    "start": 651385,
    "end": 653001,
    "text": "よし、それでは。"
  },
  {
    "start": 653033,
    "end": 654953,
    "text": "またしてもF層。"
  },
  {
    "start": 655049,
    "end": 655833,
    "text": "なぜF層なのか？"
  },
  {
    "start": 655889,
    "end": 657753,
    "text": "さて、このマザーボードのスペックを見てみましょう。"
  },
  {
    "start": 657809,
    "end": 658759,
    "text": "その理由を説明しましょう。"
  },
  {
    "start": 658857,
    "end": 662531,
    "text": "このマザーボードには、VRM レイアウトがまったく記載されていません。"
  },
  {
    "start": 662723,
    "end": 665011,
    "text": "実際のところ、何が入っているのか思い出せません。"
  },
  {
    "start": 665043,
    "end": 667499,
    "text": "おそらく仕様書にも記載されていないと思います。"
  },
  {
    "start": 667667,
    "end": 668539,
    "text": "いいえ、そうではありません。"
  },
  {
    "start": 668587,
    "end": 675067,
    "text": "私の知る限り、それは 6 フェーズ VRM レイアウトまたは 5 フェーズ VRM レイアウトのいずれかでした。"
  },
  {
    "start": 675131,
    "end": 677987,
    "text": "何はともあれ、ベンチマークは良くありませんでした。"
  },
  {
    "start": 678051,
    "end": 680851,
    "text": "マルチコアCPUだと確実にオーバーヒートしてしまいます。"
  },
  {
    "start": 680923,
    "end": 686027,
    "text": "これにより、100% の負荷がかかると、12 コアや 16 コアの CPU などのパフォーマンスが制限されます。"
  },
  {
    "start": 686091,
    "end": 690631,
    "text": "先ほども言いましたが、ほんの数ドル追加すれば、これよりもはるかに優れたマザーボードを入手できます。"
  },
  {
    "start": 690723,
    "end": 693655,
    "text": "ASRock を使えばすぐに考えが変わるでしょうか?"
  },
  {
    "start": 693735,
    "end": 701679,
    "text": "ここには ASRock B650M PG Lightning WI FI があり、これは D 層に入る予定です。"
  },
  {
    "start": 701767,
    "end": 703231,
    "text": "このマザーボードを簡単に見てみましょう。"
  },
  {
    "start": 703303,
    "end": 707263,
    "text": "こちらは6プラス2プラス1のパワーフェイスデザイン。"
  },
  {
    "start": 707359,
    "end": 708535,
    "text": "それで大丈夫です。"
  },
  {
    "start": 708615,
    "end": 715135,
    "text": "Wi Fi が付属する 120 ドルのマザーボードとしては、背面 IO はそれほど優れたものではないと思います。"
  },
  {
    "start": 715215,
    "end": 726277,
    "text": "6 プラス 2 プラス 1 の優れた電源フェーズ設計により、少なくとも、先ほど取り上げた他の低価格マザーボードよりもわずかに優れたマルチコア CPU の搭載が可能です。"
  },
  {
    "start": 726381,
    "end": 732589,
    "text": "これは熱くなりますが、ベンチマークによると、CPU のパフォーマンスをそれほど制限しません。"
  },
  {
    "start": 732717,
    "end": 736197,
    "text": "まだ素晴らしいというわけではありませんが、最悪というわけでもありません。"
  },
  {
    "start": 736261,
    "end": 739045,
    "text": "今のところD層に位置する予定です。"
  },
  {
    "start": 739125,
    "end": 739645,
    "text": "ああ、ああ。"
  },
  {
    "start": 739685,
    "end": 752185,
    "text": "そうですね、ギガバイトの B650MC V2 は販売されるべきではありません。なぜなら、私の知る限りでは、それは既製のシステムと同じようにそのまま取り出されるマザーボードだからです。"
  },
  {
    "start": 752305,
    "end": 760121,
    "text": "Reddit で見たところによると、マザーボードの BIOS を更新する際に実際に問題が発生していることがわかりました。なぜなら、これも既製のマザーボードで使用することを目的としているからです。"
  },
  {
    "start": 760193,
    "end": 763441,
    "text": "既製の PC で BIOS を更新したくない理由がわかりません。"
  },
  {
    "start": 763553,
    "end": 764633,
    "text": "それは本当に奇妙なことです。"
  },
  {
    "start": 764689,
    "end": 766409,
    "text": "また、マザーボードにもさまざまなバージョンがあります。"
  },
  {
    "start": 766457,
    "end": 770761,
    "text": "Y3 と Y2 のようなバージョンがあり、本当に混乱しています。"
  },
  {
    "start": 770873,
    "end": 773815,
    "text": "これは 120 ドルのマザーボードとしては良いものではありません。"
  },
  {
    "start": 773905,
    "end": 777499,
    "text": "もう一度ベンチマークを見ると、これは最下位にあります。"
  },
  {
    "start": 777587,
    "end": 781915,
    "text": "低価格の B650 マザーボードに関しては最悪中の最悪です。"
  },
  {
    "start": 782035,
    "end": 785267,
    "text": "実際には悪いので、この下に行を追加します。"
  },
  {
    "start": 785371,
    "end": 787499,
    "text": "皆さん、もう諦めてください。"
  },
  {
    "start": 787627,
    "end": 791243,
    "text": "Garbo 層に戻り、Tier リストを確認します。"
  },
  {
    "start": 791339,
    "end": 795835,
    "text": "ギガバイトの B650MCV2 が最下位になります。"
  },
  {
    "start": 795915,
    "end": 803517,
    "text": "さて、最後に、ASUS はこの価格帯の B650 マザーボードにある程度の自信を持っていただけますか?"
  },
  {
    "start": 803581,
    "end": 805973,
    "text": "ひどくないものを紹介してもらえますか？"
  },
  {
    "start": 806069,
    "end": 806813,
    "text": "ネタバレ注意。"
  },
  {
    "start": 806909,
    "end": 808557,
    "text": "実際、それはひどいことです。"
  },
  {
    "start": 808701,
    "end": 810065,
    "text": "F層の最下位。"
  },
  {
    "start": 810805,
    "end": 819789,
    "text": "Asus さん、私が予算と ryzen am 5 のビルドにプライム マザーボードを使用しないのには理由があります。"
  },
  {
    "start": 819837,
    "end": 821477,
    "text": "あるいは、それについては言うべきだと思います。"
  },
  {
    "start": 821581,
    "end": 825173,
    "text": "私の低価格 PC では、ASUS プライム マザーボードはほとんど見かけません。"
  },
  {
    "start": 825189,
    "end": 826237,
    "text": "それには理由があります。"
  },
  {
    "start": 826301,
    "end": 827799,
    "text": "彼らは常に VRM を怠っています。"
  },
  {
    "start": 827866,
    "end": 835635,
    "text": "ASUS Prime B650M の VRM を見ると、Web サイトにも Newegg にも、さらには ASUS の Web サイトにも掲載されていません。"
  },
  {
    "start": 835715,
    "end": 843371,
    "text": "私たちが取り上げるこれらの主要なマザーボードはすべて、6 コア CPU に適した 4 フェーズ電源設計を採用しています。"
  },
  {
    "start": 843483,
    "end": 850355,
    "text": "それ以上のものや、812 コアであろうと 16 コアであろうと、CPU にストレスを与えるものは、それほど良いものではないと思います。"
  },
  {
    "start": 850435,
    "end": 853335,
    "text": "たとえば、そのマザーボードに 130 ドルはどうでしょうか?"
  },
  {
    "start": 853416,
    "end": 861999,
    "text": "繰り返しになりますが、これから説明する 20 ドルまたは 5 ドルを追加で支払うだけで、より優れた V VRM を備えた大幅に優れたマザーボードを手に入れることができます。"
  },
  {
    "start": 862087,
    "end": 867871,
    "text": "これらの最上級のマザーボードは、VRMS が非常に精彩を欠いており、骨まで剥ぎ取られています。"
  },
  {
    "start": 867943,
    "end": 870943,
    "text": "残念ながら、ASUS はお金をかければかけるほど良くなります。"
  },
  {
    "start": 871039,
    "end": 874831,
    "text": "彼らのエントリーレベルのプライムマザーボードは、最も優れているわけではありません。"
  },
  {
    "start": 874903,
    "end": 882055,
    "text": "繰り返しになりますが、4 フェーズ電源フェーズ設計は、5 フェーズと 6 フェーズのマザーボードと比較しても、非常に残念です。"
  },
  {
    "start": 882135,
    "end": 887335,
    "text": "ただし、少なくともこのマザーボードでは BIOS を更新できるため、Garbo 層には入れられません。"
  },
  {
    "start": 887415,
    "end": 888849,
    "text": "これではそれはできません。"
  },
  {
    "start": 888967,
    "end": 890989,
    "text": "さて、ASRock、ボールはあなたのコートに戻りました。"
  },
  {
    "start": 891077,
    "end": 894597,
    "text": "低価格の B650 マザーボードについて少しでも理解できますか?"
  },
  {
    "start": 894661,
    "end": 896165,
    "text": "幸いなことに、それはできると思います。"
  },
  {
    "start": 896205,
    "end": 899797,
    "text": "こちらはASRock B650M HDV M2です。"
  },
  {
    "start": 899861,
    "end": 906565,
    "text": "それを簡単に説明し、このマザーボードを入手することが、先ほど説明した他のマザーボードと比べてどれだけ進歩するかを示しましょう。"
  },
  {
    "start": 906645,
    "end": 908558,
    "text": "こちらがHDV M2です。"
  },
  {
    "start": 908649,
    "end": 910833,
    "text": "小売価格は約135ドルです。"
  },
  {
    "start": 910924,
    "end": 912653,
    "text": "これをチェックしてください。"
  },
  {
    "start": 912744,
    "end": 916747,
    "text": "8 プラス 2 プラス 1 電源フェーズ設計。"
  },
  {
    "start": 916838,
    "end": 922521,
    "text": "私たちが取り上げた Gigabyte の B650MK とは異なり、ここにあるこの分厚いヒートシンクを見てください。"
  },
  {
    "start": 922593,
    "end": 923929,
    "text": "アスロックは宿題をした。"
  },
  {
    "start": 923977,
    "end": 926129,
    "text": "そこには分厚いヒートシンクが付いています。"
  },
  {
    "start": 926177,
    "end": 927338,
    "text": "VRM の真上にあります。"
  },
  {
    "start": 927422,
    "end": 934045,
    "text": "さらに良いのは、一番上の M2 SSD スロットが PC Edgen 5.0 をサポートしていることです。"
  },
  {
    "start": 934129,
    "end": 938049,
    "text": "これは、1 35 ドルのマザーボードとしては非常に優れています。"
  },
  {
    "start": 938097,
    "end": 943299,
    "text": "このマザーボードから得られる唯一の点は、オンボード WiFi がないことです。"
  },
  {
    "start": 943390,
    "end": 946565,
    "text": "このM2 WiFiスロットがあります。"
  },
  {
    "start": 946665,
    "end": 954405,
    "text": "それらはマザーボードの左下にあり、私は過去に M2 Wi Fi カードを挿入してこのマザーボードに WiFi を接続するために利用しました。"
  },
  {
    "start": 954485,
    "end": 956965,
    "text": "それは最も美しい解決策ではありませんが、それは存在します。"
  },
  {
    "start": 957045,
    "end": 964741,
    "text": "この 135 ドルのマザーボードは、すべてを考慮しても、特にパフォーマンスを見るとかなりまともです。"
  },
  {
    "start": 964853,
    "end": 973869,
    "text": "これは、100% のワークロード下でマルチコア 12 または 16 コア CPU を簡単に処理できる、数少ない非常に低価格の B650 マザーボードの 1 つです。"
  },
  {
    "start": 973947,
    "end": 976881,
    "text": "最高にクールではありませんが、間違いなく合格します。"
  },
  {
    "start": 976993,
    "end": 982129,
    "text": "そのため、このマザーボードを C 層に配置しています。"
  },
  {
    "start": 982297,
    "end": 983697,
    "text": "信じてください、C層は良好です。"
  },
  {
    "start": 983761,
    "end": 987937,
    "text": "先ほども言いましたが、この Tier リストの C Tier 以上のものはすべて、ゲームに最適です。"
  },
  {
    "start": 988001,
    "end": 990777,
    "text": "この Tier リストでまだ取り上げていない部分を見てください。"
  },
  {
    "start": 990881,
    "end": 993361,
    "text": "信じてください、まだ取り上げていない優れたマザーボードがいくつかあります。"
  },
  {
    "start": 993433,
    "end": 1000437,
    "text": "ギガバイトの DS3H のように、何らかの理由でこのマザーボードはゆっくりと廃止されていくようです。"
  },
  {
    "start": 1000561,
    "end": 1006165,
    "text": "このマザーボードが B650M D S3H を発売したとき、約 140 ドルでした。"
  },
  {
    "start": 1006245,
    "end": 1013629,
    "text": "実際、Gigabyte の非常に優れたマザーボードでした。VRM をチェックしてみると、6、21 が搭載されており、それほど悪くありません。"
  },
  {
    "start": 1013717,
    "end": 1015701,
    "text": "これらの VRM ヒートシンクをチェックしてください。"
  },
  {
    "start": 1015773,
    "end": 1017765,
    "text": "それは間違いなく物事を涼しく保ちました。"
  },
  {
    "start": 1017805,
    "end": 1021053,
    "text": "M2 SSD の分厚いヒートシンクを見てください。"
  },
  {
    "start": 1021149,
    "end": 1023965,
    "text": "これは、最初に発売されたときはまったく悪いマザーボードではありませんでした。"
  },
  {
    "start": 1024005,
    "end": 1026197,
    "text": "今は240ドルくらいです。"
  },
  {
    "start": 1026341,
    "end": 1030021,
    "text": "今Amazonで調べたら200ドルくらいです。"
  },
  {
    "start": 1030093,
    "end": 1033821,
    "text": "ギガバイトはこのマザーボードの製造を中止したような気がしますが、これは偽物です。"
  },
  {
    "start": 1033893,
    "end": 1044133,
    "text": "これは、最も手頃な価格の B650 マザーボードの 1 つであり、ゲームやマルチプロセスのマルチコア ワークロードに対しても、より高いコア数の CPU を十分に搭載できます。"
  },
  {
    "start": 1044189,
    "end": 1045205,
    "text": "それが言いたかったことです。"
  },
  {
    "start": 1045285,
    "end": 1049733,
    "text": "はい、敬意を表して、それが本来あるべき場所に置かなければなりません。"
  },
  {
    "start": 1049829,
    "end": 1054653,
    "text": "新品が 140 ドルで見つかるなら、私はそれを買うでしょう。"
  },
  {
    "start": 1054709,
    "end": 1060865,
    "text": "245ドルという非常に高額な価格では買えませんが、C層になるでしょう。"
  },
  {
    "start": 1061345,
    "end": 1063937,
    "text": "うーん、いいえ、6 フェーズです。"
  },
  {
    "start": 1064001,
    "end": 1066281,
    "text": "おそらくASRockの上に置く必要があります。"
  },
  {
    "start": 1066313,
    "end": 1067585,
    "text": "そうですね、そのほうが少し良く聞こえますね。"
  },
  {
    "start": 1067665,
    "end": 1068169,
    "text": "うーん。"
  },
  {
    "start": 1068257,
    "end": 1072081,
    "text": "ギガバイト B650M ゲームと Wi-Fi が追加されました。"
  },
  {
    "start": 1072153,
    "end": 1073969,
    "text": "さて、このマザーボードを購入しました。"
  },
  {
    "start": 1074057,
    "end": 1076529,
    "text": "うーん、あまり知らなかったので調べてみました。"
  },
  {
    "start": 1076577,
    "end": 1087723,
    "text": "ボックス自体を見ると、5 プラス 2 プラス 2 フェーズ設計で、非常に安価な B650M D3PH HP AX と同じです。"
  },
  {
    "start": 1087819,
    "end": 1089931,
    "text": "これは F 層であり、コストが高くなります。"
  },
  {
    "start": 1090003,
    "end": 1091019,
    "text": "見た目も涼しくなりましたか？"
  },
  {
    "start": 1091107,
    "end": 1091491,
    "text": "はい。"
  },
  {
    "start": 1091563,
    "end": 1093579,
    "text": "PC 構築ガイドに使用するつもりですか?"
  },
  {
    "start": 1093667,
    "end": 1097203,
    "text": "残念ながら、そうです、私はこのマザーボードを購入するまでこのことについて知りませんでした。"
  },
  {
    "start": 1097259,
    "end": 1103691,
    "text": "このマザーボードは実際には B650M D3HP AX よりもそれほど優れているわけではありません。"
  },
  {
    "start": 1103763,
    "end": 1106291,
    "text": "綺麗な白いペンキが塗ってあるだけです。"
  },
  {
    "start": 1106363,
    "end": 1113815,
    "text": "D3HP と H の間くらいになると思います。"
  },
  {
    "start": 1114975,
    "end": 1124807,
    "text": "これと同じ電源フェーズ設計があり、そのパフォーマンスもかなり精彩がなく、12 コアを超えるマルチコア数の CPU を投入するとスロットルが発生します。"
  },
  {
    "start": 1124911,
    "end": 1127167,
    "text": "先ほども言いましたが、ASUS。"
  },
  {
    "start": 1127271,
    "end": 1132431,
    "text": "繰り返しになりますが、これはASUS Prime B650M A2.2です。"
  },
  {
    "start": 1132543,
    "end": 1135455,
    "text": "さて、彼らは何かを見直すことを考えましたか？"
  },
  {
    "start": 1135535,
    "end": 1137554,
    "text": "VRMの改善を考えたのでしょうか？"
  },
  {
    "start": 1137634,
    "end": 1142031,
    "text": "いいえ、VRM は依然として 4 フェーズ電源設計です。"
  },
  {
    "start": 1142103,
    "end": 1142949,
    "text": "まだダメだ。"
  },
  {
    "start": 1142997,
    "end": 1148813,
    "text": "ストレスの多いワークロード下では 8 コア CPU と同様に、それでもそれほど優れたものではありません。"
  },
  {
    "start": 1148869,
    "end": 1149237,
    "text": "その。"
  },
  {
    "start": 1149301,
    "end": 1154565,
    "text": "B650M A に加えて、この Tier リスト全体の中で最も貧弱な VRM が搭載されています。"
  },
  {
    "start": 1154605,
    "end": 1162701,
    "text": "これは技術的には 2 番目のバージョンなので、少なくともこれらは 5 相電源設計になっているため、これらよりも上に置く必要がありますが、それよりも高くはありません。"
  },
  {
    "start": 1162773,
    "end": 1163773,
    "text": "これには4つあります。"
  },
  {
    "start": 1163869,
    "end": 1165765,
    "text": "それはASUSにとってひどいことです。"
  },
  {
    "start": 1165885,
    "end": 1171359,
    "text": "繰り返しになりますが、これらのプライム シリーズ マザーボードのスペック シートには電力フェーズ設計が記載されていません。"
  },
  {
    "start": 1171447,
    "end": 1175103,
    "text": "なぜなら、もしそうしたとしても、紙の上では悪い価値に見えるだけだからです。"
  },
  {
    "start": 1175199,
    "end": 1177719,
    "text": "ベンチマークを見てみると、残念ながらそうなっているからです。"
  },
  {
    "start": 1177847,
    "end": 1180631,
    "text": "さて、でもネガティブな気分はやめましょう。"
  },
  {
    "start": 1180703,
    "end": 1182519,
    "text": "もう少しポジティブなことについて話しましょう。"
  },
  {
    "start": 1182607,
    "end": 1188860,
    "text": "MSI Pro B650M は気にしないでください。それは MSI Pro B650S Wi-Fi のタイプミスのはずです。"
  },
  {
    "start": 1188940,
    "end": 1191258,
    "text": "ATXサイズのマザーボードです。"
  },
  {
    "start": 1191338,
    "end": 1198381,
    "text": "私はこれを、Ryzen 5 7500F を搭載した 1,000 ドルのゲーミング PC 構築ガイドに使用しています。"
  },
  {
    "start": 1198453,
    "end": 1200613,
    "text": "この種のマザーボードにはこれで十分です。"
  },
  {
    "start": 1200669,
    "end": 1203221,
    "text": "間違いなくそのような6コアCPUを処理します。"
  },
  {
    "start": 1203293,
    "end": 1214225,
    "text": "このマザーボードを調べてみると、このマザーボードは、140 ドルで 12 プラス 2 パワー フェイス デザインを特徴とする、この階層リストの最初のものです。"
  },
  {
    "start": 1214845,
    "end": 1215525,
    "text": "悪くないよ。"
  },
  {
    "start": 1215605,
    "end": 1216805,
    "text": "Wi-Fiが付いています。"
  },
  {
    "start": 1216845,
    "end": 1220437,
    "text": "VRM は冷却に関してもほぼ十分であると考えられます。"
  },
  {
    "start": 1220501,
    "end": 1221085,
    "text": "VRMではありません。"
  },
  {
    "start": 1221125,
    "end": 1226381,
    "text": "ヒートシンクは VRM を冷却するのにほぼ十分であるように見えますが、これは良いことです。"
  },
  {
    "start": 1226453,
    "end": 1229885,
    "text": "このビデオでは最初の ATX サイズのマザーボードです。"
  },
  {
    "start": 1230005,
    "end": 1231181,
    "text": "かなりまともです。"
  },
  {
    "start": 1231293,
    "end": 1234717,
    "text": "12 プラス 2 電源フェーズの設計はそれほど悪くありません。"
  },
  {
    "start": 1234781,
    "end": 1237325,
    "text": "Wi-Fi 6eもあるので良いです。"
  },
  {
    "start": 1237405,
    "end": 1240615,
    "text": "おそらくこれには pchn 5.0 が欠けていると思います。"
  },
  {
    "start": 1240708,
    "end": 1246117,
    "text": "pchn 5.0 M2 スロットもありませんが、140 ドルです。"
  },
  {
    "start": 1246181,
    "end": 1247205,
    "text": "本当に文句は言えません。"
  },
  {
    "start": 1247285,
    "end": 1250145,
    "text": "これをB層に投げます。"
  },
  {
    "start": 1250565,
    "end": 1252225,
    "text": "まともなマザーボードです。"
  },
  {
    "start": 1253315,
    "end": 1259015,
    "text": "これは、12 フェーズ VRM 設計を備えた、この階層リスト全体の中で最も安価なマザーボードです。"
  },
  {
    "start": 1259110,
    "end": 1259965,
    "text": "ブラボーMSI。"
  },
  {
    "start": 1260060,
    "end": 1264483,
    "text": "MSI Pro B650M Wi Fi はどうでしょうか。"
  },
  {
    "start": 1264579,
    "end": 1269971,
    "text": "以前にこのマザーボードをいじったことがあると思いますが、これもかなりまともです。"
  },
  {
    "start": 1270083,
    "end": 1271747,
    "text": "もう一度、VRMS を確認してみましょう。"
  },
  {
    "start": 1271811,
    "end": 1274453,
    "text": "約150ドルという価格で何が得られるでしょうか？"
  },
  {
    "start": 1274532,
    "end": 1281469,
    "text": "ここでは、55アンペアのVコアを備えた8フェーズVRMがCPUに与えられていると書かれています。"
  },
  {
    "start": 1281557,
    "end": 1284437,
    "text": "これはマイクロ ATX マザーボードにとってはそれほど悪くありません。"
  },
  {
    "start": 1284541,
    "end": 1286557,
    "text": "それは完全に実現可能だと思います。"
  },
  {
    "start": 1286701,
    "end": 1295005,
    "text": "これはおそらく、B650M HDV の後ろか前の間のどこかに行くことになるでしょう。"
  },
  {
    "start": 1295085,
    "end": 1304245,
    "text": "ただし、諦めなければならないとしたら、B650M a Wi Fi には Wi Fi が付属していますが、HDV M2 には付属していません。"
  },
  {
    "start": 1304325,
    "end": 1310733,
    "text": "ゲーム用の CPU を搭載した場合、これら 2 つのマザーボードのパフォーマンスは、たとえあったとしてもそれほど大きくないと思います。"
  },
  {
    "start": 1310789,
    "end": 1314317,
    "text": "これらは 2 つのかなりまともな B650 マザーボード オプションです。"
  },
  {
    "start": 1314381,
    "end": 1331021,
    "text": "繰り返しになりますが、B650M HDB M2 に M2 Wi Fi カードを投入すると、マザーボードの価格が 150 ドルを超えることになり、B650M Wi Fi よりも高価になってしまいます。それが私がそう思う理由です。 Wi-Fiカードがあるという理由だけでそれを優先します。"
  },
  {
    "start": 1331053,
    "end": 1334886,
    "text": "どちらも、手頃な価格の AM5 ゲーミング PC にとって優れた選択肢です。"
  },
  {
    "start": 1334987,
    "end": 1340611,
    "text": "ASRock B650M Pro RS Wi Fi と同様に、このマザーボードを見てみましょう。"
  },
  {
    "start": 1340693,
    "end": 1342305,
    "text": "これも150ドルです。"
  },
  {
    "start": 1342390,
    "end": 1347453,
    "text": "これには、8 プラス 2 プラス 1 の電力フェーズ設計もあります。"
  },
  {
    "start": 1347538,
    "end": 1350456,
    "text": "今のところ、55アンペアを消費するとは思いません。"
  },
  {
    "start": 1350541,
    "end": 1354103,
    "text": "おそらく 50 アンペアを消費しますが、実際にはその違いに気づくことはありません。"
  },
  {
    "start": 1354159,
    "end": 1361863,
    "text": "もう一度言いますが、この種の層の ASROCK マザーボードであるため、ここにあるスペックシートを見ると気づくでしょう。"
  },
  {
    "start": 1361919,
    "end": 1367137,
    "text": "一番上の M2 スロットは PCI Gen 5.0 M2 スロットです。"
  },
  {
    "start": 1367231,
    "end": 1367821,
    "text": "かなりきれいです。"
  },
  {
    "start": 1367893,
    "end": 1379533,
    "text": "つまり、はい、それはやりすぎですが、2026 年などの将来の PCI Gen 5.0 SSD を PC に搭載したい場合、このマザーボードは、それをサポートできる CPU と同様にそれらの速度をサポートできます。"
  },
  {
    "start": 1379629,
    "end": 1381573,
    "text": "また、この背面 IO を覗いてください。"
  },
  {
    "start": 1381669,
    "end": 1386013,
    "text": "先ほど調べた MSI マザーボードを確認してみると、IO シールドがありません。"
  },
  {
    "start": 1386069,
    "end": 1387685,
    "text": "つまり、1 つあるので、それを着用するだけです。"
  },
  {
    "start": 1387725,
    "end": 1391989,
    "text": "asrock はここに独自のものを持っていて、それは白なので、とてもクールです。"
  },
  {
    "start": 1392077,
    "end": 1399681,
    "text": "また、MSI マザーボードの背面には USB Type C がありませんが、ここには Type C ポートがあることにも注目してください。"
  },
  {
    "start": 1399753,
    "end": 1401657,
    "text": "ASRock の非常に優れた製品です。"
  },
  {
    "start": 1401721,
    "end": 1406537,
    "text": "Wi FI も含めて、私は今これを C 層の一番上に置いています。"
  },
  {
    "start": 1406721,
    "end": 1413913,
    "text": "おそらく、8 フェーズ VRM 設計を備えた 150 ドルの B650M マザーボードの中で最高のものでしょう。"
  },
  {
    "start": 1414089,
    "end": 1415481,
    "text": "それはかなり良いですね。"
  },
  {
    "start": 1415553,
    "end": 1416913,
    "text": "何が本当に良いのか知っていますか？"
  },
  {
    "start": 1416969,
    "end": 1419209,
    "text": "ASRock B650 ライブ ミキサー。"
  },
  {
    "start": 1419297,
    "end": 1424903,
    "text": "さて、これは本当に奇抜に見えますが、スペックシートはかなり印象的です。"
  },
  {
    "start": 1424999,
    "end": 1426359,
    "text": "さて、これがライフミキサーです。"
  },
  {
    "start": 1426407,
    "end": 1426999,
    "text": "それを見てください。"
  },
  {
    "start": 1427047,
    "end": 1432855,
    "text": "Rock が知っているように、これがこの種のマザーボードの主なセールス ポイントの 1 つであるため、すでにタイトルにあります。"
  },
  {
    "start": 1432935,
    "end": 1439167,
    "text": "14+2+1のパワーフェイスデザインが秀逸です。"
  },
  {
    "start": 1439231,
    "end": 1443840,
    "text": "これは CPU の 60 アンペアレールにも当てはまると思います。"
  },
  {
    "start": 1443922,
    "end": 1447515,
    "text": "これは 150 ドルのマザーボードとしては非常に優れています。"
  },
  {
    "start": 1447596,
    "end": 1454951,
    "text": "これで終わりではありません。なぜなら、繰り返しになりますが、ASRock はどういうわけかこの分野ですべてのメーカーの中で最高の仕事をしているからです。"
  },
  {
    "start": 1455023,
    "end": 1455999,
    "text": "それをチェックしてください。"
  },
  {
    "start": 1456047,
    "end": 1459663,
    "text": "一番上の M2 スロットは PCHN 5.0 です。"
  },
  {
    "start": 1459759,
    "end": 1460679,
    "text": "それはかなり良いですね。"
  },
  {
    "start": 1460767,
    "end": 1469303,
    "text": "これは、先ほど検討した以前の MSI Pro B650s マザーボードよりも優れた電源位相レイアウトであり、コストが 10 ドル安くなります。"
  },
  {
    "start": 1469359,
    "end": 1479351,
    "text": "これでは、非常に分厚い VRM と SSD 用の超高速 M2PCHN 5.0 スロットの上に、より優れた電源フェーズ レイアウトが得られます。"
  },
  {
    "start": 1479423,
    "end": 1484599,
    "text": "全体として、150 ドルで本当に優れた万能マザーボードです。"
  },
  {
    "start": 1484687,
    "end": 1489111,
    "text": "これは、ビデオの最初の 1 層マザーボードになります。"
  },
  {
    "start": 1489223,
    "end": 1490135,
    "text": "はい、その通りです。"
  },
  {
    "start": 1490175,
    "end": 1490943,
    "text": "はい、階層です。"
  },
  {
    "start": 1490999,
    "end": 1501063,
    "text": "ASRock の魅力はそれだけではありません。これらの色が少し乱暴すぎると感じた場合は、同じ 150 ドルでより落ち着いた PG ライティングを入手できます。"
  },
  {
    "start": 1501199,
    "end": 1515567,
    "text": "ヒートシンクは Live ミキサーほどクールではありませんが、これはまったく同じ 14 2.1 電力フェーズ設計で、同じ超高速 M2 PCIe gen 5.0 SSD スロットで 60 アンペアを消費します。"
  },
  {
    "start": 1515671,
    "end": 1528175,
    "text": "このマザーボードを最も手頃な価格の B650 マザーボードにするために欠けている唯一の点は、おそらくある種のことですが、グラフィックス カード用にこの最上部の PCI Express スロットがあることです。"
  },
  {
    "start": 1528255,
    "end": 1529255,
    "text": "B5.0。"
  },
  {
    "start": 1529295,
    "end": 1535847,
    "text": "そうそう、ライブ ミキサーについても言及しておく必要があります。これには Wi-Fi が内蔵されていませんが、以前に説明した HDV に似ています。"
  },
  {
    "start": 1535911,
    "end": 1540051,
    "text": "小さなカードを入れるのに便利な小さな M2 Wi Fi スロットがあります。"
  },
  {
    "start": 1540123,
    "end": 1543275,
    "text": "はい、WI Fi を使用すると、約 170 ドルになります。"
  },
  {
    "start": 1543355,
    "end": 1547747,
    "text": "電源フェーズの設計は、この層のマザーボードにとって非常に優れています。"
  },
  {
    "start": 1547811,
    "end": 1555123,
    "text": "これより高価な他のマザーボードについても説明しますが、それらの電源位相はこのマザーボードほど良くありません。"
  },
  {
    "start": 1555179,
    "end": 1559395,
    "text": "WiFi はいつでも追加できますが、マザーボード上の VRM を変更することはできません。"
  },
  {
    "start": 1559475,
    "end": 1567315,
    "text": "このマザーボードは見た目がそれほど奇抜ではないので、おそらくもっと売れるでしょう。B650 ライブ ミックスのすぐ上に置きます。"
  },
  {
    "start": 1567355,
    "end": 1571035,
    "text": "机上では、私の Tier リストではこれらは両方とも同等です。"
  },
  {
    "start": 1571375,
    "end": 1572559,
    "text": "またエイスース。"
  },
  {
    "start": 1572647,
    "end": 1574623,
    "text": "さて、atx に移動します。"
  },
  {
    "start": 1574759,
    "end": 1575591,
    "text": "エイスース。"
  },
  {
    "start": 1575743,
    "end": 1577439,
    "text": "教えてください、実際に見てみましょう。"
  },
  {
    "start": 1577527,
    "end": 1578503,
    "text": "エイスースに教えてください。"
  },
  {
    "start": 1578639,
    "end": 1580735,
    "text": "フルサイズの ATX マザーボードをお持ちです。"
  },
  {
    "start": 1580815,
    "end": 1583343,
    "text": "VRM にはさらに強力なヒートシンクが搭載されています。"
  },
  {
    "start": 1583439,
    "end": 1588183,
    "text": "あの小さな小さな四相電源設計を少しでも変更しましたか?"
  },
  {
    "start": 1588319,
    "end": 1594583,
    "text": "少なくとも技術仕様に記載しましたか、それとも待って、単に Digiplus VRM と呼ぶだけですか?"
  },
  {
    "start": 1594679,
    "end": 1606033,
    "text": "皆様、Asus Prime B650 plus は、同じ非常に小型の共感型 4 フェーズ VRM 設計を採用していますが、価格は以前の 2 つのマザーボードよりもさらに高価です。"
  },
  {
    "start": 1606129,
    "end": 1606460,
    "text": "$150."
  },
  {
    "start": 1606533,
    "end": 1609036,
    "text": "14に比べると残念ですね。"
  },
  {
    "start": 1609109,
    "end": 1609404,
    "text": "2."
  },
  {
    "start": 1609477,
    "end": 1613777,
    "text": "これら 2 つの ASRock マザーボードにある 1 つのフェーズ。"
  },
  {
    "start": 1613881,
    "end": 1615233,
    "text": "違いは夜と昼です。"
  },
  {
    "start": 1615249,
    "end": 1622897,
    "text": "ストレスの多い CPU ベースのワークロードに 8 コアを超えるマルチコア数の CPU を投入すると、このマザーボードは破壊されてしまいます。"
  },
  {
    "start": 1622961,
    "end": 1626259,
    "text": "一方、このアッシュロックボードはそれに非常にうまく対処します。"
  },
  {
    "start": 1626377,
    "end": 1630639,
    "text": "これはお勧めできませんし、このマザーボードの価格がこれらの主要なマザーボードよりも高いのは痛手です。"
  },
  {
    "start": 1630687,
    "end": 1634087,
    "text": "残念ながらF層の最下位に落ちてしまいます。"
  },
  {
    "start": 1634191,
    "end": 1639792,
    "text": "それは、ASUS が主要なラインナップの一部として手頃な価格の B650 マザーボードを持っていないというだけです。"
  },
  {
    "start": 1639853,
    "end": 1642439,
    "text": "ボードに組み込まれている VRM は最高のものではありません。"
  },
  {
    "start": 1642567,
    "end": 1643639,
    "text": "うーん、しかし、msi。"
  },
  {
    "start": 1643687,
    "end": 1649175,
    "text": "アメリカに住んでいるなら、このマザーボード、MSI B650M ゲームと WiFi を見つけることはできません。"
  },
  {
    "start": 1649215,
    "end": 1658971,
    "text": "このマザーボード上の VRM は、この Tier リストで後ほど説明する Project Zero マザーボードと同じであるため、とにかくここに投入したかったのです。"
  },
  {
    "start": 1659043,
    "end": 1666771,
    "text": "これは今すぐ海外の視聴者から話題になると確信しているので、これをランキングするためです。もし米国で販売されたら、おそらく約 160 ドルになるでしょう。"
  },
  {
    "start": 1666828,
    "end": 1670494,
    "text": "8 フェーズよりも優れた 10 フェーズ VRM 設計を採用しています。"
  },
  {
    "start": 1670551,
    "end": 1673723,
    "text": "もちろん、ここでは 14 や 12 ほど良くはありません。"
  },
  {
    "start": 1673779,
    "end": 1679633,
    "text": "米国で約 160 ドルで販売される場合、おそらく C 層のどこかに置く必要があるでしょう。"
  },
  {
    "start": 1679739,
    "end": 1688021,
    "text": "これらよりも優れた VRM があり、価格が 10 ドル高いだけであれば、MSI の 3 つのマザーボードよりも上位にランクされると思います。"
  },
  {
    "start": 1688093,
    "end": 1690957,
    "text": "アメリカで販売されていればの話ですが、実際には販売されていないと思います。"
  },
  {
    "start": 1691021,
    "end": 1695848,
    "text": "B650M マザーボードとしては予算内での優れた選択肢となる可能性があるため、そうなってほしいと思います。"
  },
  {
    "start": 1695981,
    "end": 1699229,
    "text": "さて、MSI Pro B650M。"
  },
  {
    "start": 1699317,
    "end": 1702077,
    "text": "これらの名前は、この Tier リストが終わるまでに私を殺すことになるでしょう。"
  },
  {
    "start": 1702141,
    "end": 1705519,
    "text": "さて、P wifi、今度はこのマザーボードを見てみましょう。"
  },
  {
    "start": 1705567,
    "end": 1722245,
    "text": "幸いなことに、このマザーボードは、12 プラス 2 プラス 1 で非常に優れた 12 フェーズ電源設計を備えているため、非常に小型の B650M P と同じ哀れな電源フェーズ設計を共有していません。"
  },
  {
    "start": 1722331,
    "end": 1726544,
    "text": "CPU の最大 75 アンペアの描画が可能になりました。"
  },
  {
    "start": 1726630,
    "end": 1727834,
    "text": "それはかなり良いですね。"
  },
  {
    "start": 1727920,
    "end": 1730414,
    "text": "価格を調べてみましょう。"
  },
  {
    "start": 1730500,
    "end": 1730887,
    "text": "$180."
  },
  {
    "start": 1730991,
    "end": 1732095,
    "text": "それはあまりみすぼらしいものではありません。"
  },
  {
    "start": 1732175,
    "end": 1733103,
    "text": "それは承ります。"
  },
  {
    "start": 1733239,
    "end": 1734079,
    "text": "それは承ります。"
  },
  {
    "start": 1734167,
    "end": 1740239,
    "text": "これは、より多くのアンペアを消費できるため、MSI Pro B650M S WiFi よりも優れています。"
  },
  {
    "start": 1740327,
    "end": 1742847,
    "text": "先に置くしかないので。"
  },
  {
    "start": 1742951,
    "end": 1745795,
    "text": "そうですね、追加で 40 ドルかかります。"
  },
  {
    "start": 1746575,
    "end": 1749111,
    "text": "つまり、これは実際に行ったり来たりする可能性があります。"
  },
  {
    "start": 1749223,
    "end": 1753327,
    "text": "理論上は、40 ドル高いとはいえ、これを上位にランクする必要があります。"
  },
  {
    "start": 1753391,
    "end": 1758801,
    "text": "これら 2 つのランクのランキングが変わる可能性があるため、B 層の残りの層リストがどのように展開するかを見てみましょう。"
  },
  {
    "start": 1758903,
    "end": 1759293,
    "text": "うーん。"
  },
  {
    "start": 1759349,
    "end": 1760984,
    "text": "ギガバイトB650イーグルアックス。"
  },
  {
    "start": 1761057,
    "end": 1765445,
    "text": "これは、発売されたばかりの Gigabyte の新しい B650 マザーボードの 1 つです。"
  },
  {
    "start": 1765525,
    "end": 1775525,
    "text": "これも非常に優れていると思います。調べてみると、価格は 160 ドルで、12、2、2、電源フェーズ設計が付属しているからです。"
  },
  {
    "start": 1775645,
    "end": 1777181,
    "text": "見てみるとそれほどみすぼらしいものではありません。"
  },
  {
    "start": 1777213,
    "end": 1778829,
    "text": "非常に強力な VRM がいくつかあります。"
  },
  {
    "start": 1778906,
    "end": 1779595,
    "text": "VRMではありません。"
  },
  {
    "start": 1779672,
    "end": 1781549,
    "text": "VRM 上のヒートシンク。"
  },
  {
    "start": 1781677,
    "end": 1783013,
    "text": "今はギガバイトから。"
  },
  {
    "start": 1783069,
    "end": 1793601,
    "text": "最後に、ここでスペックシートを確認してみると、一番上の M2 スロットは M2 SSD 用の PC Edge N5 スロットであり、ASRock の取り組みと一致しています。"
  },
  {
    "start": 1793673,
    "end": 1795249,
    "text": "これも悪くありません。"
  },
  {
    "start": 1795337,
    "end": 1798297,
    "text": "ただし、1 つだけ、ノックしてみてもよいと思います。"
  },
  {
    "start": 1798361,
    "end": 1799089,
    "text": "さあ、見てみましょう。"
  },
  {
    "start": 1799137,
    "end": 1800057,
    "text": "本当ですか？"
  },
  {
    "start": 1800161,
    "end": 1800809,
    "text": "見てみましょう。"
  },
  {
    "start": 1800897,
    "end": 1801329,
    "text": "そうそう。"
  },
  {
    "start": 1801377,
    "end": 1805769,
    "text": "この Eagle AX の LAN ポートは 1 ギガビット/秒です。"
  },
  {
    "start": 1805897,
    "end": 1814280,
    "text": "参考として、先ほど調べた MSI ボードの速度を調べてみると、すべての B650 マザーボードと同様に、実際にその速度が測定されるはずです。"
  },
  {
    "start": 1814353,
    "end": 1817993,
    "text": "これの地上速度は 2.5 ギガビット/秒です。"
  },
  {
    "start": 1818129,
    "end": 1824765,
    "text": "おそらく、Eagle AX の欠点は、LAN ポートが情けないほど遅いことでしょう。"
  },
  {
    "start": 1824885,
    "end": 1827037,
    "text": "WI Fiを使用するだけであれば、特に問題はありません。"
  },
  {
    "start": 1827101,
    "end": 1831909,
    "text": "つまり、私たちは今、これらの B650 マザーボードをかき集めるために非常に苦労しているのです。"
  },
  {
    "start": 1831997,
    "end": 1835733,
    "text": "そのため、これを両方の下に置く必要があります。"
  },
  {
    "start": 1835829,
    "end": 1840225,
    "text": "繰り返しますが、これらのマザーボードはいずれもゲーム PC に適しています。"
  },
  {
    "start": 1840685,
    "end": 1843885,
    "text": "ASRock B650MPG リップタイド Wi-Fi。"
  },
  {
    "start": 1843925,
    "end": 1846289,
    "text": "これについてはスペックシートを必ずチェックする必要があります。"
  },
  {
    "start": 1846357,
    "end": 1849110,
    "text": "わかりました。12.2One 電源フェーズ設計を使用しています。"
  },
  {
    "start": 1849182,
    "end": 1857444,
    "text": "これにはオンボード WiFi が付属しているため、M2 WiFi カードを備えたこれら 2 つのマザーボードとほぼ同じコストになります。"
  },
  {
    "start": 1857516,
    "end": 1859256,
    "text": "こちらの方が小さいです。"
  },
  {
    "start": 1859328,
    "end": 1863849,
    "text": "VRMはそれほど良くありませんが、価格はかなり良いです。"
  },
  {
    "start": 1863977,
    "end": 1868289,
    "text": "繰り返しますが、この上部には M2 PCI Gen 5.0 スロットがあります。"
  },
  {
    "start": 1868337,
    "end": 1870425,
    "text": "ヒートシンクはかなり肉厚です。"
  },
  {
    "start": 1870545,
    "end": 1873577,
    "text": "これも ASRock のかなりしっかりしたマザーボードです。"
  },
  {
    "start": 1873641,
    "end": 1878309,
    "text": "彼らはおそらく、パフォーマンスに対する価値という点で、この Tier リストの中でこれまでのところ最高の成績を収めています。"
  },
  {
    "start": 1878457,
    "end": 1880741,
    "text": "約170ドルで。"
  },
  {
    "start": 1880853,
    "end": 1886733,
    "text": "そうですね、このような 12 フェーズ VRM 設計を採用しているため、これは B 層に入る予定です。"
  },
  {
    "start": 1886829,
    "end": 1895365,
    "text": "価格的には、あと 20 ドル出したら、M2 SSD 用の M2PCHN 5.0 スロットがある Eagle AX を買うと思います。"
  },
  {
    "start": 1895450,
    "end": 1901289,
    "text": "VRM 用のより強力なヒートシンクが付いていますが、これと比べてわずか 20 ドル高いです。"
  },
  {
    "start": 1901374,
    "end": 1908517,
    "text": "CPU の 75 アンペアの消費電力を備えたこの MSI Pro ボードは本当に素晴らしく、おそらくイーグル アックスよりも優れています。"
  },
  {
    "start": 1908661,
    "end": 1913501,
    "text": "それを念頭に置いて、170 の場合は、多かれ少なかれ次のようになります。"
  },
  {
    "start": 1913613,
    "end": 1915005,
    "text": "あとは価格に合わせるしかないでしょう。"
  },
  {
    "start": 1915045,
    "end": 1921557,
    "text": "Eagle AX は PG Riptide よりも 10 ドル安いですが、どちらもおそらくまったく同じになると思います。"
  },
  {
    "start": 1921621,
    "end": 1923821,
    "text": "こちらも 1 ギガバイトの LAN ポートを備えています。"
  },
  {
    "start": 1923933,
    "end": 1926237,
    "text": "今ではそれがそれほど大きな問題ではないと思いますが。"
  },
  {
    "start": 1926341,
    "end": 1928013,
    "text": "はい、わかりました、このままにしておきます。"
  },
  {
    "start": 1928149,
    "end": 1929357,
    "text": "このままにしておきます。"
  },
  {
    "start": 1929501,
    "end": 1935845,
    "text": "ああ、Gigabyte が好調だと思っていたところに、B650 Gaming X が登場しました。"
  },
  {
    "start": 1936735,
    "end": 1937607,
    "text": "これは。"
  },
  {
    "start": 1937751,
    "end": 1942991,
    "text": "ああ、私はこのマザーボードを誇りに思っているわけではありません。以前の PC 構築ガイドで使用したと思うからです。"
  },
  {
    "start": 1943023,
    "end": 1947126,
    "text": "先ほど説明した Eagle EX には 12 プラス 2 プラス 2 があります。"
  },
  {
    "start": 1947194,
    "end": 1951880,
    "text": "Gaming X AX は 170 ドルで 10 ドル多く提供されますか?"
  },
  {
    "start": 1951948,
    "end": 1954631,
    "text": "とても誇り高い 8 プラス 2 プラス 1。"
  },
  {
    "start": 1954703,
    "end": 1956435,
    "text": "君たちはもうおかしくなってしまったか？"
  },
  {
    "start": 1956775,
    "end": 1961431,
    "text": "夢中になるなら、いいねボタンのために夢中になりましょうと言いたいです。"
  },
  {
    "start": 1961503,
    "end": 1962501,
    "text": "叩き潰しましょう。"
  },
  {
    "start": 1962623,
    "end": 1977197,
    "text": "なぜなら、この階層リストのビデオに「いいね！」が増えれば増えるほど、YouTube のアルゴリズムでより多くの人がその動画を世に出すことになり、より多くの人が、購入すべき B650 マザーボードの正誤について知るだけでなく、私を助け、正当化することにもなるからです。とにかくこれらの B650 マザーボードをすべて調べました。"
  },
  {
    "start": 1977264,
    "end": 1980529,
    "text": "はい、8 プラス 2 プラス 1 で 170 ドルです。"
  },
  {
    "start": 1980577,
    "end": 1981441,
    "text": "それはかなり情けないことだ。"
  },
  {
    "start": 1981513,
    "end": 1989989,
    "text": "これのヒートシンクはかなり大きく、かなりの量の AI と接続性を備えていることはわかっていますが、8 段階のフェーズがあり、それほど素晴らしいものではありません。"
  },
  {
    "start": 1990097,
    "end": 1994149,
    "text": "はい、価格は170ドルで本当に悪いです。"
  },
  {
    "start": 1994197,
    "end": 1999821,
    "text": "この電源フェーズ設計により、はるかに優れた電源フェーズを備えたマザーボードをより安価に入手できると思います。"
  },
  {
    "start": 1999933,
    "end": 2006789,
    "text": "ゲーミング X AX は 6 コアや 8 コアの CPU には適していますが、より安価でより良いボードを手に入れることができるということです。"
  },
  {
    "start": 2006877,
    "end": 2007949,
    "text": "それだけにしておきます。"
  },
  {
    "start": 2008037,
    "end": 2011653,
    "text": "では、B650 ゲームと Wi Fi についてはどうでしょうか?"
  },
  {
    "start": 2011789,
    "end": 2013349,
    "text": "早速スペックページを見てみましょう。"
  },
  {
    "start": 2013397,
    "end": 2014525,
    "text": "リフレッシュする必要があります。"
  },
  {
    "start": 2014605,
    "end": 2020611,
    "text": "以前の PC 構築ガイドでこのマザーボードを使用しましたが、このマザーボードは高すぎると言いたいのです。"
  },
  {
    "start": 2020683,
    "end": 2022275,
    "text": "それは必ずしも悪いことではありません。"
  },
  {
    "start": 2022355,
    "end": 2023523,
    "text": "値段が高す​​ぎます。"
  },
  {
    "start": 2023579,
    "end": 2024051,
    "text": "見てみましょう。"
  },
  {
    "start": 2024123,
    "end": 2027395,
    "text": "12 プラス 2 プラス 1 電源フェーズ設計。"
  },
  {
    "start": 2027515,
    "end": 2028547,
    "text": "それはあまりみすぼらしいものではありません。"
  },
  {
    "start": 2028611,
    "end": 2030779,
    "text": "何アンペアまで引き込むことができますか?"
  },
  {
    "start": 2030867,
    "end": 2032675,
    "text": "おそらくそれは言っていないでしょう。"
  },
  {
    "start": 2032715,
    "end": 2034523,
    "text": "マザーボードの仕様ページを確認してみましょう。"
  },
  {
    "start": 2034619,
    "end": 2035947,
    "text": "わかりました、それは言いません。"
  },
  {
    "start": 2035971,
    "end": 2041075,
    "text": "Pro B650P WiFi ほど良くないのは間違いありません。"
  },
  {
    "start": 2041155,
    "end": 2041699,
    "text": "ここだよ。"
  },
  {
    "start": 2041747,
    "end": 2042867,
    "text": "このマザーボードはここにあります。"
  },
  {
    "start": 2042931,
    "end": 2048571,
    "text": "どちらかと言えば、より高価な MSI Pro B650M S Wi Fi かもしれません。"
  },
  {
    "start": 2048663,
    "end": 2050410,
    "text": "これは 140 ドルかかります。"
  },
  {
    "start": 2050502,
    "end": 2052295,
    "text": "これで170くらいです。"
  },
  {
    "start": 2052415,
    "end": 2054831,
    "text": "それはただ悪い価値提案だと思います。"
  },
  {
    "start": 2054903,
    "end": 2057031,
    "text": "170ドルならそうなると思います。"
  },
  {
    "start": 2057143,
    "end": 2060431,
    "text": "つまり、B 層ボードと一緒にここに属するはずです。"
  },
  {
    "start": 2060503,
    "end": 2065495,
    "text": "その価格で、これらのマザーボードの 1 つ、または階層リストですぐに説明する他のマザーボードのいくつかを入手できます。"
  },
  {
    "start": 2065575,
    "end": 2070167,
    "text": "このため、ペナルティを与えてここC層に置くかもしれないと思います。"
  },
  {
    "start": 2070231,
    "end": 2072143,
    "text": "おそらくaと言いたいです。"
  },
  {
    "start": 2072239,
    "end": 2073615,
    "text": "ええ、おそらくそこにあります。"
  },
  {
    "start": 2073695,
    "end": 2075479,
    "text": "ゲーミングマザーボードとしては悪くないです。"
  },
  {
    "start": 2075527,
    "end": 2077891,
    "text": "これらはより良い選択肢であるというだけです。"
  },
  {
    "start": 2078003,
    "end": 2080611,
    "text": "ギガバイトB650UDAC。"
  },
  {
    "start": 2080763,
    "end": 2081579,
    "text": "親切ですね。"
  },
  {
    "start": 2081627,
    "end": 2083299,
    "text": "もっとたくさんのボードを手に入れました。"
  },
  {
    "start": 2083387,
    "end": 2084315,
    "text": "ああ、そうだね。"
  },
  {
    "start": 2084395,
    "end": 2085523,
    "text": "私は今それを失いつつあります。"
  },
  {
    "start": 2085579,
    "end": 2088515,
    "text": "米国で170ドル。"
  },
  {
    "start": 2088635,
    "end": 2091211,
    "text": "これはビデオのマザーボードのようなものです。"
  },
  {
    "start": 2091283,
    "end": 2092763,
    "text": "ここで何が起こっているのでしょうか？"
  },
  {
    "start": 2092819,
    "end": 2095013,
    "text": "VRM には非常に小さなヒートシンクがあります。"
  },
  {
    "start": 2095084,
    "end": 2097876,
    "text": "この M2 SSD レイアウトはどうなっているのでしょうか?"
  },
  {
    "start": 2097948,
    "end": 2100740,
    "text": "フルサイズの PCI Express スロットのみがあります。"
  },
  {
    "start": 2100811,
    "end": 2103961,
    "text": "小さい x16 や x のようなものはありません。"
  },
  {
    "start": 2104033,
    "end": 2108615,
    "text": "ここの M2 SSD レイアウトで何が起こっているのでしょうか?"
  },
  {
    "start": 2108686,
    "end": 2112910,
    "text": "さて、これは 6 プラス 2 プラス 2 で 170 ドルです。"
  },
  {
    "start": 2112982,
    "end": 2113268,
    "text": "何？"
  },
  {
    "start": 2113340,
    "end": 2120785,
    "text": "これには、上部に PCIe Gen 5.0 M2 スロットが 1 つと、さらに 2 つの 4.0 スロットがあるようです。"
  },
  {
    "start": 2120857,
    "end": 2121859,
    "text": "それは素晴らしいですね。"
  },
  {
    "start": 2121931,
    "end": 2129717,
    "text": "このマザーボードには何も付属していないため、ここに搭載される PCIe Gen 5.0 M2 SSD には非常に大きな同期機能があることを祈るばかりです。"
  },
  {
    "start": 2129781,
    "end": 2133089,
    "text": "ただし、V spi Fi はあり、リア IO は問題ありません。"
  },
  {
    "start": 2133177,
    "end": 2141165,
    "text": "ただし、少なくともタイプ C はありますが、6 プラス 2 プラス 2 フェーズ設計で 170 ドルなので、金額的にはかなり見えにくいです。"
  },
  {
    "start": 2141705,
    "end": 2143241,
    "text": "さて、これをどこに置きますか？"
  },
  {
    "start": 2143313,
    "end": 2143897,
    "text": "そうです。"
  },
  {
    "start": 2144001,
    "end": 2147833,
    "text": "ああ、少なくともプライムマザーボードは安いです。"
  },
  {
    "start": 2147889,
    "end": 2155896,
    "text": "少なくともこれらは約 120,130 ドルで入手できるため、これをフルサイズの ATX ボードと小型のマイクロ ATX ボードの間に差し込む必要があります。"
  },
  {
    "start": 2156005,
    "end": 2160993,
    "text": "150 の B650 プラスは、電力位相に関して非常にひどい値です。"
  },
  {
    "start": 2161049,
    "end": 2163409,
    "text": "これも 6 プラス 2 プラス 2 です。"
  },
  {
    "start": 2163457,
    "end": 2168681,
    "text": "170 ドルもあれば、ここに示すように、C 層から A 層までのかなり優れたマザーボードを入手できます。"
  },
  {
    "start": 2168753,
    "end": 2169441,
    "text": "ああ、分かった。"
  },
  {
    "start": 2169473,
    "end": 2178097,
    "text": "Gigabyte は、B650 Gaming X AX V2 でオリジナルの B650 Gaming X AX からさらに改善されていますか?"
  },
  {
    "start": 2178201,
    "end": 2178601,
    "text": "見てみましょう。"
  },
  {
    "start": 2178633,
    "end": 2179937,
    "text": "先に進み、スペックシートを確認してみましょう。"
  },
  {
    "start": 2180001,
    "end": 2181666,
    "text": "バージョン 1 は 170 ドルです。"
  },
  {
    "start": 2181733,
    "end": 2183334,
    "text": "バージョン 2 についてはどうですか?"
  },
  {
    "start": 2183401,
    "end": 2184905,
    "text": "あと10ドルだけです。"
  },
  {
    "start": 2184985,
    "end": 2191525,
    "text": "見た目はまったく同じで、同じ古い 8 プラス 2 プラス 2 フェーズの設計が採用されています。"
  },
  {
    "start": 2191605,
    "end": 2193077,
    "text": "もう一度確認してみましょう。"
  },
  {
    "start": 2193181,
    "end": 2193669,
    "text": "どうでも。"
  },
  {
    "start": 2193717,
    "end": 2199861,
    "text": "オリジナルでは 8 +2 +1 が使用されますが、V2 では 8+2 +2 が使用されます。"
  },
  {
    "start": 2199933,
    "end": 2203181,
    "text": "それは小さな改善であり、少なくともその点では改善です。"
  },
  {
    "start": 2203253,
    "end": 2208541,
    "text": "180 ドル出せば、より優れた電源フェーズ設計を備えた、より優れたマザーボードが存在します。"
  },
  {
    "start": 2208613,
    "end": 2211828,
    "text": "この MSI Pro B650M P がその好例です。"
  },
  {
    "start": 2211922,
    "end": 2216585,
    "text": "これら 2 つの ASRock マザーボードは、はるかに優れた電源フェーズ設計を備えています。"
  },
  {
    "start": 2216665,
    "end": 2222577,
    "text": "このような製品でも最上部に PCIe 5.0 M2 スロットがあるとは思えませんが、これは素晴らしいことです。"
  },
  {
    "start": 2222641,
    "end": 2225545,
    "text": "繰り返しますが、これより優れたマザーボードはあります。"
  },
  {
    "start": 2225625,
    "end": 2227161,
    "text": "オリジナルよりも上位になります。"
  },
  {
    "start": 2227233,
    "end": 2231121,
    "text": "これを B650 Gaming X AX の上に置く必要があります。"
  },
  {
    "start": 2231233,
    "end": 2231849,
    "text": "ああ、分かった。"
  },
  {
    "start": 2231897,
    "end": 2233177,
    "text": "最後にエイスース。"
  },
  {
    "start": 2233281,
    "end": 2237193,
    "text": "TUF シリーズ ゲーミング マザーボードで何か改善することはできますか?"
  },
  {
    "start": 2237289,
    "end": 2239321,
    "text": "確かにこれらは本当にクールに見えます。"
  },
  {
    "start": 2239393,
    "end": 2240593,
    "text": "私は彼らの見た目が好きです。"
  },
  {
    "start": 2240649,
    "end": 2244253,
    "text": "ブラックフライデー、サイバーマンデー、またはAmazonプライムデーに関して言えば、これらです。"
  },
  {
    "start": 2244289,
    "end": 2245781,
    "text": "これらには割引が適用されます。"
  },
  {
    "start": 2245853,
    "end": 2247980,
    "text": "TUF Gaming B650E を見てみましょう。"
  },
  {
    "start": 2248063,
    "end": 2252985,
    "text": "B650E ボードではなく、B650E なので、非常に紛らわしいです。"
  },
  {
    "start": 2253069,
    "end": 2254237,
    "text": "180ドルで。"
  },
  {
    "start": 2254320,
    "end": 2257156,
    "text": "どのような電力位相設計が得られるでしょうか?"
  },
  {
    "start": 2257240,
    "end": 2258825,
    "text": "8プラス2？"
  },
  {
    "start": 2258908,
    "end": 2259242,
    "text": "うん。"
  },
  {
    "start": 2259325,
    "end": 2263413,
    "text": "少なくとも PCI Gen 5.0 M2 スロットはあります。"
  },
  {
    "start": 2263497,
    "end": 2265541,
    "text": "これはまだ 4.0 です。"
  },
  {
    "start": 2265573,
    "end": 2266861,
    "text": "まあ、気にしないでください。"
  },
  {
    "start": 2267053,
    "end": 2268285,
    "text": "いや、この板の。"
  },
  {
    "start": 2268405,
    "end": 2269157,
    "text": "なくなってしまった。"
  },
  {
    "start": 2269261,
    "end": 2270293,
    "text": "ああ。"
  },
  {
    "start": 2270469,
    "end": 2272685,
    "text": "これは必ずしもマザーボードが悪いわけではありません。"
  },
  {
    "start": 2272765,
    "end": 2274125,
    "text": "ただ値段が高す​​ぎます。"
  },
  {
    "start": 2274205,
    "end": 2275498,
    "text": "これは実際には約 150 ドルのはずです。"
  },
  {
    "start": 2275563,
    "end": 2284805,
    "text": "8 プラス 2 なので、このトリオが同じかそれ以下で手に入るのに、なぜこれを 180 円で手に入れることができるのでしょうか。"
  },
  {
    "start": 2284925,
    "end": 2287965,
    "text": "私の知る限り、これはおそらく C 層に入るでしょう。"
  },
  {
    "start": 2288005,
    "end": 2293277,
    "text": "なぜなら、ここにあるような、小型で安価な 8 相電源設計が採用されているからです。"
  },
  {
    "start": 2293381,
    "end": 2295309,
    "text": "これはタフなシリーズのボードです。"
  },
  {
    "start": 2295477,
    "end": 2297229,
    "text": "それはちょっと高すぎます。"
  },
  {
    "start": 2297277,
    "end": 2298613,
    "text": "これらはより良い値です。"
  },
  {
    "start": 2298709,
    "end": 2301725,
    "text": "C層の最下位に置くのは厳しすぎますか？"
  },
  {
    "start": 2301805,
    "end": 2303493,
    "text": "そこにいる価値があるような気がします。"
  },
  {
    "start": 2303549,
    "end": 2309805,
    "text": "というのも、これから取り上げる他の TUF ボードの一部は 12 フェーズ電源設計を採用しており、非常にお買い得だと思います。"
  },
  {
    "start": 2309885,
    "end": 2310621,
    "text": "見てみましょう。"
  },
  {
    "start": 2310693,
    "end": 2311549,
    "text": "間違っているかもしれません。"
  },
  {
    "start": 2311637,
    "end": 2311941,
    "text": "わかった。"
  },
  {
    "start": 2311973,
    "end": 2315453,
    "text": "MSI Mag B650M Mortar WiFi。"
  },
  {
    "start": 2315589,
    "end": 2318669,
    "text": "このマザーボードは価格の割に本当に興味深いです。"
  },
  {
    "start": 2318757,
    "end": 2321885,
    "text": "実際、これをどこにランク付けするかについては、少し悩みました。"
  },
  {
    "start": 2321925,
    "end": 2323085,
    "text": "ここがモルタルのWi-Fiです。"
  },
  {
    "start": 2323125,
    "end": 2324613,
    "text": "180ドルです。"
  },
  {
    "start": 2324709,
    "end": 2327789,
    "text": "繰り返しになりますが、参照ベンチマークは MSI のこのボードです。"
  },
  {
    "start": 2327837,
    "end": 2330449,
    "text": "この価格帯では B650M P です。"
  },
  {
    "start": 2330557,
    "end": 2337569,
    "text": "これも 12、2:1 電力フェーズ設計ですが、80 アンペアの電力を消費します。"
  },
  {
    "start": 2337657,
    "end": 2343417,
    "text": "これは実際には、ここで取り上げたばかりのこのボード、B650M P Wi Fi よりも少しだけ優れています。"
  },
  {
    "start": 2343481,
    "end": 2345801,
    "text": "これとあれのどちらが安いか見てみましょう。"
  },
  {
    "start": 2345873,
    "end": 2347377,
    "text": "ほぼ同じ価格です。"
  },
  {
    "start": 2347521,
    "end": 2347953,
    "text": "はぁ。"
  },
  {
    "start": 2348009,
    "end": 2353537,
    "text": "マイクロ ATX ボードは、フルサイズの ATX ボードよりもわずかに優れた VRM を備えています。"
  },
  {
    "start": 2353641,
    "end": 2354121,
    "text": "面白い。"
  },
  {
    "start": 2354193,
    "end": 2357319,
    "text": "残念ながら、M2 スロットはまだ 4.0 です。"
  },
  {
    "start": 2357400,
    "end": 2367967,
    "text": "これが 5.0 だったらよかったのですが、VRMS と REIO 接続でのヒートシンクのサイズを見ると、これはクールで静かなマザーボードになるでしょう。"
  },
  {
    "start": 2368071,
    "end": 2369167,
    "text": "これは良いことだと思います。"
  },
  {
    "start": 2369191,
    "end": 2372279,
    "text": "MSI のモルタル シリーズは歴史的に非常に優れています。"
  },
  {
    "start": 2372367,
    "end": 2377831,
    "text": "これは 180 ドルで入手できる最高のマイクロ ATX B650 マザーボードの 1 つです。"
  },
  {
    "start": 2377903,
    "end": 2380627,
    "text": "PG Riptide WiFi よりも優れているのでしょうか?"
  },
  {
    "start": 2380715,
    "end": 2386291,
    "text": "これの VRM は若干優れていると思いますが、追加料金はわずか 10 ドルほどです。"
  },
  {
    "start": 2386371,
    "end": 2390670,
    "text": "B650M PG Ript には M2PCHN 5.0 スロットがあります。"
  },
  {
    "start": 2390750,
    "end": 2398275,
    "text": "そうですね、Pgraphide は 60 アンペアの電流を引き込めると思いますが、モルタル Wi-Fi は 80 アンペアの電流を引き込むことができます。"
  },
  {
    "start": 2398355,
    "end": 2404955,
    "text": "それまでに、追加の 10 ドルをこれに費やして、おそらくここの一番上に置くと思います。"
  },
  {
    "start": 2405075,
    "end": 2407720,
    "text": "そうですね、約 180 ドルで最高の VRM が手に入るかもしれません。"
  },
  {
    "start": 2407784,
    "end": 2411853,
    "text": "ただし、150 用のホッグボードとしては、この 2 つが現時点で傑出しています。"
  },
  {
    "start": 2411917,
    "end": 2414747,
    "text": "だって、彼らは 14 プラス 2 プラス 1 を持っているからです。"
  },
  {
    "start": 2414811,
    "end": 2416109,
    "text": "それらは今の傑出したものです。"
  },
  {
    "start": 2416187,
    "end": 2416457,
    "text": "よし。"
  },
  {
    "start": 2416481,
    "end": 2420737,
    "text": "さて、ASUS、この Tier リストで自分自身を取り戻すチャンスをたくさん与えます。"
  },
  {
    "start": 2420841,
    "end": 2424437,
    "text": "asus TUF Gaming B650M plus Wi Fi でそれを実現できますか?"
  },
  {
    "start": 2424503,
    "end": 2425096,
    "text": "見てみましょう。"
  },
  {
    "start": 2425162,
    "end": 2427072,
    "text": "さて、これは約190ドルです。"
  },
  {
    "start": 2427138,
    "end": 2430695,
    "text": "これは最高ではありませんが、これには 12 プラス 2 があります。"
  },
  {
    "start": 2430761,
    "end": 2432671,
    "text": "それはASUSにとってそれほど悪いことではありません。"
  },
  {
    "start": 2432737,
    "end": 2433330,
    "text": "厳しい基準。"
  },
  {
    "start": 2433396,
    "end": 2438977,
    "text": "これは、わずか 10 ドル高いだけで 8 個しかなかった B650E よりも確実に進歩しています。"
  },
  {
    "start": 2439041,
    "end": 2440177,
    "text": "それはとても立派なことです。"
  },
  {
    "start": 2440281,
    "end": 2443619,
    "text": "これには、はい、5.0 M2 SSD スロットがあると思います。"
  },
  {
    "start": 2443691,
    "end": 2445771,
    "text": "まだ PCHN 5.0 スロットではありません。"
  },
  {
    "start": 2445843,
    "end": 2447565,
    "text": "私たちはまだそこまで到達していません。"
  },
  {
    "start": 2447636,
    "end": 2451997,
    "text": "190 ドルで、このマザーボードは高すぎると言えると思います。"
  },
  {
    "start": 2452061,
    "end": 2455533,
    "text": "そのため、B層の一番下に置くことにします。"
  },
  {
    "start": 2455589,
    "end": 2457613,
    "text": "最も高価な 12 フェーズです。"
  },
  {
    "start": 2457709,
    "end": 2458741,
    "text": "に加えて。"
  },
  {
    "start": 2458893,
    "end": 2461141,
    "text": "まあ、これもカバーできると思います。"
  },
  {
    "start": 2461213,
    "end": 2464421,
    "text": "マイクロATXモデルと同じVRMを搭載しています。"
  },
  {
    "start": 2464493,
    "end": 2466101,
    "text": "これはほぼ同じ費用がかかります。"
  },
  {
    "start": 2466173,
    "end": 2471781,
    "text": "まったく同じボードなので、これを B650M プラス Wi-Fi と一緒に投げるつもりです。"
  },
  {
    "start": 2471853,
    "end": 2472037,
    "text": "ただ。"
  },
  {
    "start": 2472061,
    "end": 2473515,
    "text": "こちらも約190ドル。"
  },
  {
    "start": 2473645,
    "end": 2474162,
    "text": "わかった。"
  },
  {
    "start": 2474292,
    "end": 2476751,
    "text": "ASRock B650E PG リップタイド。"
  },
  {
    "start": 2476881,
    "end": 2482261,
    "text": "これは、この Tier リストで取り上げた最初の B650E マザーボードです。"
  },
  {
    "start": 2482333,
    "end": 2488021,
    "text": "約 190 ドルの B650E Pgraphide Wi Fi で何が得られるでしょうか。"
  },
  {
    "start": 2488093,
    "end": 2491253,
    "text": "先ほど取り上げた TUF マザーボードと同じ価格です。"
  },
  {
    "start": 2491309,
    "end": 2495781,
    "text": "さて、ここでは 14 プラス 2 プラス 1 の電力フェーズ設計が得られます。"
  },
  {
    "start": 2495893,
    "end": 2500453,
    "text": "これは、ここで取り上げた 2 つの ASRock ボードと同じものだと思います。"
  },
  {
    "start": 2500509,
    "end": 2503675,
    "text": "今では機内 Wi-Fi が提供されています。これは素晴らしいことです。"
  },
  {
    "start": 2503795,
    "end": 2506995,
    "text": "VRM 用のはるかに分厚いヒートシンク。"
  },
  {
    "start": 2507115,
    "end": 2508731,
    "text": "ああ、でも見てください。"
  },
  {
    "start": 2508883,
    "end": 2509939,
    "text": "それを見てください。"
  },
  {
    "start": 2509987,
    "end": 2516259,
    "text": "これは、最上部の PCI Express スロットに PCIe Gen 5.0 を搭載した最初のマザーボードでもあります。"
  },
  {
    "start": 2516347,
    "end": 2521369,
    "text": "はい、SSD 用の PCIe gen 5.0 M2 スロットの上にあります。"
  },
  {
    "start": 2521444,
    "end": 2523610,
    "text": "これにはすべての基準があります。"
  },
  {
    "start": 2523684,
    "end": 2529619,
    "text": "グラフィックス カードの Express スロットと M2 スロットの両方に優れた VRMS PCIe gen 5.0 を搭載。"
  },
  {
    "start": 2529667,
    "end": 2531139,
    "text": "背面の接続にも注目してください。"
  },
  {
    "start": 2531187,
    "end": 2533275,
    "text": "つまり、ミントです。"
  },
  {
    "start": 2533355,
    "end": 2539987,
    "text": "GPU サグ ブラケットも付属していると思います。これは、非常に重いグラフィックス カードを使用している場合に非常に便利な便利なツールです。"
  },
  {
    "start": 2540051,
    "end": 2542987,
    "text": "はい、190 ドルで必要なものがすべて揃っています。"
  },
  {
    "start": 2543051,
    "end": 2544611,
    "text": "それは私から良い評価を得るでしょう。"
  },
  {
    "start": 2544643,
    "end": 2547419,
    "text": "これを段の一番上に投げます。"
  },
  {
    "start": 2547507,
    "end": 2549611,
    "text": "200ドル未満で必要なものがすべて揃っています。"
  },
  {
    "start": 2549704,
    "end": 2551000,
    "text": "頑張れアスロック。"
  },
  {
    "start": 2551093,
    "end": 2553778,
    "text": "ああ、でもMSIを値引きすることはできません。"
  },
  {
    "start": 2553871,
    "end": 2560221,
    "text": "これがMSI Mag B650 Tomahawk Wi Fiです。AMDファンならこのマザーボードをよく知っています。"
  },
  {
    "start": 2560293,
    "end": 2565653,
    "text": "これは、価格の VRM に関しては、歴史的に最高のパフォーマンスを発揮するマザーボードの 1 つです。"
  },
  {
    "start": 2565749,
    "end": 2571016,
    "text": "今回は、Tomahawk Hawk が B650 プラットフォームに何を提供するのかを確認してみましょう。"
  },
  {
    "start": 2571113,
    "end": 2583275,
    "text": "これは約 200 ドルで、私が最近の 1500 ドルの PC 構築ガイドで使用したマザーボードとまったく同じで、180 ドルの割引だった 7800x3D を利用しています。"
  },
  {
    "start": 2583405,
    "end": 2585487,
    "text": "値段が上がったので何が得られるでしょうか？"
  },
  {
    "start": 2585551,
    "end": 2590895,
    "text": "ここで確認すると、14 プラス 2 プラス 1 の電力フェーズ設計が与えられます。"
  },
  {
    "start": 2590974,
    "end": 2595159,
    "text": "CPUに最大80アンペアを供給できるのは本当に素晴らしいです。"
  },
  {
    "start": 2595287,
    "end": 2596791,
    "text": "またとても素敵です。"
  },
  {
    "start": 2596863,
    "end": 2603231,
    "text": "それは多かれ少なかれ、ここでの迫撃砲に似ていますが、約 20 ドル高い 14 フェーズ電源設計です。"
  },
  {
    "start": 2603303,
    "end": 2614749,
    "text": "ここで気づくことの 1 つは、残念なことに、このボードは、先ほど説明したものとは異なり、グラフィックス カードの最上位の PCI Express スロットとして PCIe gen 4.0 スロットのみをサポートしているということです。"
  },
  {
    "start": 2614797,
    "end": 2615237,
    "text": "それは。"
  },
  {
    "start": 2615301,
    "end": 2616589,
    "text": "つまり、さらに悪化する可能性があります。"
  },
  {
    "start": 2616677,
    "end": 2621069,
    "text": "正直に言って、MSI から入手できる VRM は本当に価値があります。"
  },
  {
    "start": 2621157,
    "end": 2625376,
    "text": "現時点では、PCHN 4.0 と 5.0 の間に大きな違いは見られません。"
  },
  {
    "start": 2625459,
    "end": 2638395,
    "text": "5.0 マザーボードにはそれが備わっているため、私からはより良い評価が得られますが、この MSI Tomahawk WiFi ボードは、たとえグラフィックス カード用の PC Edge Gen 4.0 Express スロットがあったとしても、ゲーム用に非常に優れたものになるでしょう。"
  },
  {
    "start": 2638472,
    "end": 2640003,
    "text": "200ドルでも。"
  },
  {
    "start": 2640059,
    "end": 2641635,
    "text": "それほど悪い値ではありません。"
  },
  {
    "start": 2641715,
    "end": 2651075,
    "text": "これを 8 層用の他のマザーボードと並べて配置しますが、やはり PC エンジン、5.0 ポート、エクスプレス スロットがないため、最下位になる予定です。"
  },
  {
    "start": 2651160,
    "end": 2653213,
    "text": "200ドルです。"
  },
  {
    "start": 2653299,
    "end": 2654069,
    "text": "よし。"
  },
  {
    "start": 2654154,
    "end": 2656251,
    "text": "ASRock B650 スチールレジェンド WiFi。"
  },
  {
    "start": 2656323,
    "end": 2659315,
    "text": "このマザーボードはアメリカには存在しません。"
  },
  {
    "start": 2659475,
    "end": 2660987,
    "text": "誰もが正当な理由でそれを購入しました。"
  },
  {
    "start": 2661051,
    "end": 2662059,
    "text": "その理由を見てみましょう。"
  },
  {
    "start": 2662147,
    "end": 2667443,
    "text": "つまり、真剣に、現在は入手できないように、誰もがそれを購入しました。"
  },
  {
    "start": 2667539,
    "end": 2668195,
    "text": "その理由を見てみましょう。"
  },
  {
    "start": 2668235,
    "end": 2670147,
    "text": "こちらはWI fiのB650スチールエッジです。"
  },
  {
    "start": 2670171,
    "end": 2680569,
    "text": "人々がこのマザーボードについて話題にするだろうから、このマザーボードが登場することはわかっていますが、CPU 用に最大 80 アンペアを供給できるこの 14 プラス 2 プラス 1 の電力フェーズを見てください。"
  },
  {
    "start": 2680645,
    "end": 2681332,
    "text": "非常に素晴らしい。"
  },
  {
    "start": 2681408,
    "end": 2684803,
    "text": "最上位グラフィックス カード用の PCIe Gen 5.0 Express スロット。"
  },
  {
    "start": 2684899,
    "end": 2686091,
    "text": "そこは素晴らしいです。"
  },
  {
    "start": 2686123,
    "end": 2689386,
    "text": "これは非常に高速な PCHN 5.0 M2 スロットです。"
  },
  {
    "start": 2689485,
    "end": 2690374,
    "text": "これも素晴らしい。"
  },
  {
    "start": 2690473,
    "end": 2692399,
    "text": "機内Wi-Fiが付いています。"
  },
  {
    "start": 2692487,
    "end": 2702903,
    "text": "このマザーボードが発売された当時、小売価格は 180 ～ 170 ドルだったと思います。実際には、ここにある PG Riptide よりももう少し価値があったでしょう。"
  },
  {
    "start": 2702959,
    "end": 2709719,
    "text": "入手可能性が限られていることは理解していますが、紙面と仕様書だけを見れば、これは私にとって良い評価を得ることができると思います。"
  },
  {
    "start": 2709767,
    "end": 2711703,
    "text": "これをS段階に入れてみます。"
  },
  {
    "start": 2711799,
    "end": 2720659,
    "text": "これには、白いマザーボードに必要なものがすべて揃っており、PG Riptide よりもリア IO の拡張性がさらに優れていると思います。"
  },
  {
    "start": 2720747,
    "end": 2721611,
    "text": "こちらがマザーボードです。"
  },
  {
    "start": 2721643,
    "end": 2725315,
    "text": "B650E スチールレジェンドを実際に手に入れることができます。"
  },
  {
    "start": 2725395,
    "end": 2734491,
    "text": "これは、先ほど取り上げたトマホーク マザーボードと同じ 200 ドルで手に入るので、ぜひ見てみましょう。"
  },
  {
    "start": 2734683,
    "end": 2745609,
    "text": "これは、16 プラス 2 プラス 1 電源フェーズ設計を入手でき、他に必要なものが 200 ドルですべて揃っています。"
  },
  {
    "start": 2745737,
    "end": 2748489,
    "text": "残念ながら、理論上はトマホークよりも優れています。"
  },
  {
    "start": 2748577,
    "end": 2751985,
    "text": "あるいは、このマザーボードがその称号に値するので幸運だと言えるかもしれません。"
  },
  {
    "start": 2752065,
    "end": 2757217,
    "text": "これは、S ティアの最上位にある B650 スチールのレジェンドと並ぶことになります。"
  },
  {
    "start": 2757281,
    "end": 2761745,
    "text": "Steel レジェンドが約 180 ドルで手に入るとしたら、それは非常に良い価値があります。"
  },
  {
    "start": 2761825,
    "end": 2763257,
    "text": "そんなことは起こらないと思います。"
  },
  {
    "start": 2763321,
    "end": 2766945,
    "text": "B650E スチールレジェンドは 200 ドルで入手できます。"
  },
  {
    "start": 2767025,
    "end": 2768905,
    "text": "まさに今、すべてが揃っています。"
  },
  {
    "start": 2768985,
    "end": 2774321,
    "text": "正直なところ、このマザーボード以外に費用をかける必要はありませんが、この階層リストには他にもかなりの数のマザーボードが含まれています。"
  },
  {
    "start": 2774423,
    "end": 2778341,
    "text": "200 ドルの場合、B650i Lightning WiFi ITX はどうでしょうか。"
  },
  {
    "start": 2778413,
    "end": 2784661,
    "text": "さて、ITX 仲間の皆さんのために、この小さなマザーボードを Tier リストにいくつか含めておこうと思いました。"
  },
  {
    "start": 2784733,
    "end": 2789089,
    "text": "約 200 ドルで、8 プラス 2 プラス 1 の電力フェーズ設計を備えています。"
  },
  {
    "start": 2789153,
    "end": 2795430,
    "text": "これには PCHN 4.0 スロットしかありませんが、M2 SSD 用の PCHN 5.0 スロットが含まれています。"
  },
  {
    "start": 2795493,
    "end": 2802237,
    "text": "ITX ボードが 200 ドルということは、机上ではこの Tier リストで下位にランクされることを意味しますが、それが悪いボードであるという意味ではありません。"
  },
  {
    "start": 2802301,
    "end": 2803445,
    "text": "ITXボードです。"
  },
  {
    "start": 2803525,
    "end": 2804763,
    "text": "もっと費用がかかりますよ。"
  },
  {
    "start": 2804869,
    "end": 2806783,
    "text": "おそらくこれを投げるでしょう。"
  },
  {
    "start": 2806879,
    "end": 2809815,
    "text": "2 つのゲーミング X ボードの前にこれを投げます。"
  },
  {
    "start": 2809855,
    "end": 2811519,
    "text": "つまり、彼らは彼らとほぼ並んでいます。"
  },
  {
    "start": 2811567,
    "end": 2817791,
    "text": "本質的に ITX ボードであるため、VRM の冷却に関してはこれらのボードほどのパフォーマンスは得られません。"
  },
  {
    "start": 2817863,
    "end": 2820279,
    "text": "それでも、マザーボード自体が悪いというわけではありません。"
  },
  {
    "start": 2820327,
    "end": 2826559,
    "text": "ITX システムを構築している人が、すぐに分厚い 16 コア CPU を投入するとは思いません。"
  },
  {
    "start": 2826607,
    "end": 2832039,
    "text": "おそらく 8 コアまたは 6 コアのことを考えているでしょうが、これはゲーム向けのこの種のマザーボードとしてはまったく問題ありません。"
  },
  {
    "start": 2832087,
    "end": 2836839,
    "text": "現在 200 ドルで、Gigabyte B650Aorus Elite AX が手に入ります。"
  },
  {
    "start": 2836927,
    "end": 2840463,
    "text": "仕様シートを確認する必要があるので、これを簡単に確認しましょう。"
  },
  {
    "start": 2840559,
    "end": 2847655,
    "text": "わかりました。CPU 用に描画できる最大 70 アンペアの 14 プラス 2 プラス 1 の電力フェーズ設計が与えられました。"
  },
  {
    "start": 2847775,
    "end": 2848735,
    "text": "あまりみすぼらしいものではありません。"
  },
  {
    "start": 2848815,
    "end": 2849767,
    "text": "ああ、でも見てみましょう。"
  },
  {
    "start": 2849831,
    "end": 2852927,
    "text": "最上位の PCI gen 4.0 スロットのみ。"
  },
  {
    "start": 2852991,
    "end": 2856559,
    "text": "今のところ、これはトマホークと競合することになります。"
  },
  {
    "start": 2856647,
    "end": 2858423,
    "text": "これらは正直言って髪を裂く可能性があります。"
  },
  {
    "start": 2858549,
    "end": 2859931,
    "text": "本当にできるのです。"
  },
  {
    "start": 2860123,
    "end": 2862435,
    "text": "これらは実際に行ったり来たりする可能性があります。"
  },
  {
    "start": 2862555,
    "end": 2873427,
    "text": "むしろ、このマザーボードが 180 ドルまで割引されると知っているという理由だけで、トマホークを少し高くする必要があります。これは、私が PC 構築ガイドで使用しているものと同じです。"
  },
  {
    "start": 2873493,
    "end": 2881635,
    "text": "一方、B650Aorus Elite AX は少し高価ですが、現在メーカー希望小売価格でトマホークと同じ価格で割引中です。"
  },
  {
    "start": 2881715,
    "end": 2883243,
    "text": "すべては価値に帰着します。"
  },
  {
    "start": 2883299,
    "end": 2885535,
    "text": "トマホークの価値はほんの少しだけ高くなります。"
  },
  {
    "start": 2885615,
    "end": 2888511,
    "text": "紙の上では、これらは両方ともかなりネックです。"
  },
  {
    "start": 2888543,
    "end": 2910327,
    "text": "さて、これらの B650M Aorus Elite AX ボード (ICE モデルを含む) は、この Tier リストの価格設定で非常に上位にランクされるはずなので、少し奇妙ですが、残念なことに、実際の販売価格を確認すると、現時点では黒バージョンは250ドル程度、右バージョンは200ドル程度で販売されています。"
  },
  {
    "start": 2910391,
    "end": 2912641,
    "text": "彼らは明らかに最高ではありません。"
  },
  {
    "start": 2912713,
    "end": 2915521,
    "text": "つまり、12 プラス 2 プラス 2 は本当に良いのです。"
  },
  {
    "start": 2915593,
    "end": 2918649,
    "text": "何らかの理由でこれらの価格は本当に高いです。"
  },
  {
    "start": 2918737,
    "end": 2919537,
    "text": "理解できません。"
  },
  {
    "start": 2919601,
    "end": 2920665,
    "text": "それは好きではありません。"
  },
  {
    "start": 2920785,
    "end": 2922657,
    "text": "これらは本当に価格を下げる必要があります。"
  },
  {
    "start": 2922721,
    "end": 2928729,
    "text": "ここでは Mordor WI Fi と並んで約 180 ドルで販売されるはずですが、実際はそうではありません。"
  },
  {
    "start": 2928817,
    "end": 2934633,
    "text": "価格が非常に高額なので、C層のどこかに行くことになるでしょう。"
  },
  {
    "start": 2934769,
    "end": 2935313,
    "text": "うーん。"
  },
  {
    "start": 2935409,
    "end": 2936327,
    "text": "私を嫌いにならないでください。"
  },
  {
    "start": 2936481,
    "end": 2939387,
    "text": "これは困難を乗り越えるだろう。"
  },
  {
    "start": 2939451,
    "end": 2942355,
    "text": "これらのボードの下には、価格に見合った価値があります。"
  },
  {
    "start": 2942435,
    "end": 2947299,
    "text": "Gigabyte の B650M Aorus Elite AX ボードは、価格を下げる必要があります。"
  },
  {
    "start": 2947347,
    "end": 2949923,
    "text": "彼らは迫撃砲がある場所にいる必要がある。"
  },
  {
    "start": 2950019,
    "end": 2950571,
    "text": "ああ、分かった。"
  },
  {
    "start": 2950603,
    "end": 2955614,
    "text": "MSI は Pro B650A WiFi でトマホーク WiFi から少しでも改善されましたか?"
  },
  {
    "start": 2955697,
    "end": 2959395,
    "text": "さて、これは現在約205ドルで小売されています。"
  },
  {
    "start": 2959555,
    "end": 2961675,
    "text": "私たちにも同じものが与えられています。"
  },
  {
    "start": 2961795,
    "end": 2965707,
    "text": "同じ14/2/1のパワーフェイス設計を与えられています。"
  },
  {
    "start": 2965811,
    "end": 2970373,
    "text": "全体として、これは Tomahawk とほぼ同じマザーボードだと思います。"
  },
  {
    "start": 2970429,
    "end": 2974373,
    "text": "白い VRM ヒートシンクがいくつかあるだけですが、5 ドル高くなります。"
  },
  {
    "start": 2974429,
    "end": 2975693,
    "text": "もう少し費用がかかります。"
  },
  {
    "start": 2975749,
    "end": 2978013,
    "text": "そのため、ランクは少し低くなります。"
  },
  {
    "start": 2978069,
    "end": 2979677,
    "text": "これをこの下に置きます。"
  },
  {
    "start": 2979741,
    "end": 2981429,
    "text": "ここにある 2 つのマザーボード。"
  },
  {
    "start": 2981517,
    "end": 2982293,
    "text": "はい、そうです。"
  },
  {
    "start": 2982349,
    "end": 2982941,
    "text": "それは正しい。"
  },
  {
    "start": 2983053,
    "end": 2986597,
    "text": "最後に、MSI B650M プロジェクト ゼロ。"
  },
  {
    "start": 2986701,
    "end": 2988501,
    "text": "これは興味深い板です。"
  },
  {
    "start": 2988573,
    "end": 2993473,
    "text": "このマザーボードの小売価格は約 210 ドルですが、VRM レイアウトをチェックしてください。"
  },
  {
    "start": 2993589,
    "end": 2994873,
    "text": "これは少し間抜けです。"
  },
  {
    "start": 2994929,
    "end": 2998634,
    "text": "10 プラス 2 プラス 1 の電力フェーズ設計が与えられています。"
  },
  {
    "start": 2998711,
    "end": 3004313,
    "text": "理想的には、この MSI B650M ゲームと同じものに Wi Fi を加えたものですが、これはアメリカには存在しません。"
  },
  {
    "start": 3004369,
    "end": 3006281,
    "text": "これは同じ VRM レイアウトになります。"
  },
  {
    "start": 3006353,
    "end": 3010505,
    "text": "価格は約 210 ドルで、機能はほぼ同じです。"
  },
  {
    "start": 3010545,
    "end": 3017577,
    "text": "グラフィックス カード用の PCHN 4.0 スロットと、M2 SSD 用の 5.0 スロットだと思います。"
  },
  {
    "start": 3017656,
    "end": 3018793,
    "text": "いいえ、4.0です。"
  },
  {
    "start": 3018849,
    "end": 3022513,
    "text": "ちょっと奇妙ですが、このマザーボードを使用すると非常にクールな外観が得られます。"
  },
  {
    "start": 3022569,
    "end": 3023525,
    "text": "それをあげます。"
  },
  {
    "start": 3023625,
    "end": 3026301,
    "text": "もちろん、プロジェクト ゼロを達成することもできます。"
  },
  {
    "start": 3026373,
    "end": 3029965,
    "text": "このマザーボードのすべての電源コネクタが背面のどこにあるかを確認してください。"
  },
  {
    "start": 3030045,
    "end": 3033861,
    "text": "客観的に見て、この価格は Tier リストであまり良くありません。"
  },
  {
    "start": 3033933,
    "end": 3037301,
    "text": "つまり、このマザーボードに決めた人はどちらでも構いません。"
  },
  {
    "start": 3037333,
    "end": 3042709,
    "text": "電源や IO ケーブルが見えない、Project Zero のようなレイアウトになります。"
  },
  {
    "start": 3042797,
    "end": 3049725,
    "text": "これはおそらくD層の最上位に行くだろうと言いたい。"
  },
  {
    "start": 3049805,
    "end": 3053811,
    "text": "なぜなら、これら 2 つのゲーミング X ボードや ASRock のボードよりも優れた VRM を備えているからです。"
  },
  {
    "start": 3053893,
    "end": 3057103,
    "text": "価格もそれほど派手ではありませんが、大げさでもありません。"
  },
  {
    "start": 3057159,
    "end": 3058751,
    "text": "繰り返しになりますが、これは Project Zero ボードです。"
  },
  {
    "start": 3058823,
    "end": 3060943,
    "text": "そのためには少し余裕を持たせなければなりません。"
  },
  {
    "start": 3061039,
    "end": 3062431,
    "text": "ああ、わかった、それでは行きましょう。"
  },
  {
    "start": 3062503,
    "end": 3066599,
    "text": "ギガバイト B650AORUS エリート AX ICE。"
  },
  {
    "start": 3066687,
    "end": 3068335,
    "text": "ああ、これはマザーボードがたくさんあります。"
  },
  {
    "start": 3068415,
    "end": 3070731,
    "text": "これは小売価格が約 210 ドルだと思います。"
  },
  {
    "start": 3070853,
    "end": 3073167,
    "text": "それを再確認しましょう。"
  },
  {
    "start": 3073289,
    "end": 3074447,
    "text": "はい、210ドル。"
  },
  {
    "start": 3074591,
    "end": 3080011,
    "text": "白いマザーボードの場合、12 +2 +2 電源フェーズ設計のものになります。"
  },
  {
    "start": 3080143,
    "end": 3080979,
    "text": "つまり。"
  },
  {
    "start": 3081147,
    "end": 3083187,
    "text": "つまり、それは間違いなくうまくいきます。"
  },
  {
    "start": 3083291,
    "end": 3087363,
    "text": "この価格帯でこれより優れた電源フェーズを備えたマザーボードは他にありません。"
  },
  {
    "start": 3087419,
    "end": 3096211,
    "text": "このマザーボードは白色ですが、グラフィックス カードのプライマリ Express スロットには PCHN 4.0、M2 SSD には 5.0 が搭載されています。"
  },
  {
    "start": 3096283,
    "end": 3098987,
    "text": "実際、これはここにあるこの種のボードと同じようなものです。"
  },
  {
    "start": 3099051,
    "end": 3102003,
    "text": "ちょっと値段が高くて、色は白です。"
  },
  {
    "start": 3102099,
    "end": 3108491,
    "text": "12 電力フェーズのマザーボードであるため、残念なことに、これはおそらく B 層の最下位に配置する必要があるでしょう。"
  },
  {
    "start": 3108643,
    "end": 3110187,
    "text": "繰り返しますが、マザーボードが悪いわけではありません。"
  },
  {
    "start": 3110251,
    "end": 3111571,
    "text": "ただ値段が高す​​ぎます。"
  },
  {
    "start": 3111643,
    "end": 3113867,
    "text": "やっぱり白いマザーボードですね。"
  },
  {
    "start": 3113971,
    "end": 3118859,
    "text": "白い PCB と白いヒートシンクは、すべてを黒く保つよりも少しコストがかかります。"
  },
  {
    "start": 3118947,
    "end": 3120643,
    "text": "でも、はい、ここはB層になります。"
  },
  {
    "start": 3120699,
    "end": 3122963,
    "text": "繰り返しますが、決して悪いマザーボードではありません。"
  },
  {
    "start": 3123059,
    "end": 3128236,
    "text": "2,000 ドルのゲーミング PC 構築ガイドで示したように、それでも非常に高性能です。"
  },
  {
    "start": 3128320,
    "end": 3128655,
    "text": "うーん。"
  },
  {
    "start": 3128739,
    "end": 3129915,
    "text": "230ドルで。"
  },
  {
    "start": 3129999,
    "end": 3134114,
    "text": "わずか約 20 ドル追加で、ギガバイト B650 Aero G が手に入ります。"
  },
  {
    "start": 3134198,
    "end": 3138515,
    "text": "私は実際にこのマザーボードを 2,500 ドルの PC 構築ガイドで使用しています。"
  },
  {
    "start": 3138595,
    "end": 3141067,
    "text": "私が少し気に入っている理由はここにあります。"
  },
  {
    "start": 3141131,
    "end": 3144763,
    "text": "さて、Gigabyte の Web サイトは現在、機能不全に陥っています。"
  },
  {
    "start": 3144859,
    "end": 3147691,
    "text": "VRM はリストされませんが、事前に確認しました。"
  },
  {
    "start": 3147763,
    "end": 3150383,
    "text": "Aero g には 16 が付属します。"
  },
  {
    "start": 3150535,
    "end": 3154731,
    "text": "2.1 電力フェーズ設計。この価格のマザーボードとしてはかなり優れています。"
  },
  {
    "start": 3154803,
    "end": 3162571,
    "text": "200 ドル以上で、B650E ボードで、グラフィックス カード用の PCIe gen 5.0 Express スロットが付属していればよかったのにと思います。"
  },
  {
    "start": 3162603,
    "end": 3164163,
    "text": "それが私の唯一の願いです。"
  },
  {
    "start": 3164219,
    "end": 3167981,
    "text": "それでも、このマザーボード上の VRM は、コストパフォーマンスに優れています。"
  },
  {
    "start": 3168053,
    "end": 3174141,
    "text": "このマザーボードにマルチコア 12 または 16 コア CPU を投入した場合、かなりうまく機能します。"
  },
  {
    "start": 3174213,
    "end": 3184013,
    "text": "B650E PG Riptide のバージョンは 5.0 で、VRM の性能はそれほど優れていませんが、それでも約 40 ドル安くてかなり立派なものであることがわかります。"
  },
  {
    "start": 3184069,
    "end": 3186853,
    "text": "これはこのあたりのどこかに行きます。"
  },
  {
    "start": 3186989,
    "end": 3195155,
    "text": "繰り返しますが、ハリスを分割していますが、このアスマークボードが150ドルだったので、おそらくエアロGをそこに置く必要があると思います。"
  },
  {
    "start": 3195185,
    "end": 3196599,
    "text": "バックは価値がありすぎます。"
  },
  {
    "start": 3196687,
    "end": 3198751,
    "text": "PG リップタイドにはすべてが備わっています。"
  },
  {
    "start": 3198783,
    "end": 3206079,
    "text": "ここで 230 ドルで 190 ドルの場合、B650E である必要があり、もしそうであれば、これは A 層の最上位になります。"
  },
  {
    "start": 3206167,
    "end": 3206863,
    "text": "そうではありません。"
  },
  {
    "start": 3206919,
    "end": 3211248,
    "text": "それならB650E Aorus Elite X AX ICEはどうでしょうか。"
  },
  {
    "start": 3211358,
    "end": 3215103,
    "text": "いや、それは×が多かったです。"
  },
  {
    "start": 3215213,
    "end": 3224863,
    "text": "さて、このマザーボードは B650E なので、この価格帯のマザーボードにまさに必要なものなので、ギガバイトのクレジットを付けておきます。"
  },
  {
    "start": 3224919,
    "end": 3231117,
    "text": "グラフィックス カードの最上部の Express スロットには PCHN 5.0 スロットがあります。"
  },
  {
    "start": 3231181,
    "end": 3234413,
    "text": "VRM用にかなり分厚いヒートシンクが付いています。"
  },
  {
    "start": 3234469,
    "end": 3235653,
    "text": "ということで、これまでのところは順調です。"
  },
  {
    "start": 3235709,
    "end": 3238341,
    "text": "白で230ドルです。"
  },
  {
    "start": 3238488,
    "end": 3243293,
    "text": "この 12 +2 +2VRM デザインを入手してください。"
  },
  {
    "start": 3243389,
    "end": 3248840,
    "text": "私たちはちょうど 16 プラス 2 プラス 1 を搭載した Aero G 用のマザーボードを検討していました。"
  },
  {
    "start": 3248891,
    "end": 3257305,
    "text": "これには 12 プラス 2 プラス 2 しかなく、技術的にはすべての B 層マザーボードとともにこの層に分類されますが、これは少し恥ずかしいことです。"
  },
  {
    "start": 3257385,
    "end": 3267505,
    "text": "230 ドルの場合、B650E ボードはわずか 20 ドル高いだけなので、これは Elite AX Ice よりも良い価値があるでしょう。"
  },
  {
    "start": 3267665,
    "end": 3268521,
    "text": "それ。"
  },
  {
    "start": 3268633,
    "end": 3270881,
    "text": "ああ、すぐそこに行きます。"
  },
  {
    "start": 3270953,
    "end": 3277117,
    "text": "230 ドルの価格を正当化するには、より強力な VRM 電源フェーズ設計が必要でした。"
  },
  {
    "start": 3277201,
    "end": 3280685,
    "text": "見た目は素晴らしいマザーボードですが、おそらくそれが私が考えることができる限りの高さです。"
  },
  {
    "start": 3280725,
    "end": 3286533,
    "text": "これらの頑丈なマザーボードであっても、これと同じ VRM フェーズ レイアウトを備えているため、技術的にはより優れた価値があると考えられます。"
  },
  {
    "start": 3286589,
    "end": 3288893,
    "text": "今はB650i Aorus Ultraです。"
  },
  {
    "start": 3288949,
    "end": 3289565,
    "text": "そうだったと思います。"
  },
  {
    "start": 3289605,
    "end": 3291109,
    "text": "はい、このマザーボードを入手しました。"
  },
  {
    "start": 3291157,
    "end": 3292525,
    "text": "それは私たちのテストベンチマザーボードです。"
  },
  {
    "start": 3292605,
    "end": 3293685,
    "text": "これは実際かなり良いです。"
  },
  {
    "start": 3293725,
    "end": 3296005,
    "text": "240ドルくらいだと思います。"
  },
  {
    "start": 3296045,
    "end": 3299461,
    "text": "この電源フェーズの設計も実際には非常に優れています。"
  },
  {
    "start": 3299533,
    "end": 3303453,
    "text": "ITX マザーボードの場合、これには 8 プラス 2 プラス 1 が含まれます。"
  },
  {
    "start": 3303549,
    "end": 3305023,
    "text": "わかりました、実際には大丈夫です。"
  },
  {
    "start": 3305149,
    "end": 3307083,
    "text": "他に何か目的はありますか？"
  },
  {
    "start": 3307179,
    "end": 3312283,
    "text": "さて、階層リストの奥深くまで入ってしまったので、なぜこのマザーボードを C 階層に入れたか忘れてしまいました。"
  },
  {
    "start": 3312339,
    "end": 3313635,
    "text": "私たちはそれで行きます。"
  },
  {
    "start": 3313675,
    "end": 3315891,
    "text": "そこに置きます。"
  },
  {
    "start": 3316043,
    "end": 3316771,
    "text": "すぐそこです。"
  },
  {
    "start": 3316883,
    "end": 3317275,
    "text": "よし。"
  },
  {
    "start": 3317315,
    "end": 3320244,
    "text": "MSI MPG、B650 エッジ Wi-Fi。"
  },
  {
    "start": 3320337,
    "end": 3320710,
    "text": "わかった。"
  },
  {
    "start": 3320803,
    "end": 3324555,
    "text": "Pro B658 Wi Fi はトマホークをあまり改善しませんでした。"
  },
  {
    "start": 3324635,
    "end": 3326804,
    "text": "エッジは約240ドルでやってくれますか？"
  },
  {
    "start": 3326911,
    "end": 3331617,
    "text": "注意すべき点は、これは B650E ではないということです。"
  },
  {
    "start": 3331724,
    "end": 3334675,
    "text": "普通のB650なんですが、ちょっと動揺してます。"
  },
  {
    "start": 3334755,
    "end": 3340331,
    "text": "これは同じ 14/2 +1 電力フェーズ設計です。"
  },
  {
    "start": 3340483,
    "end": 3345635,
    "text": "何らかの理由で価格が高いだけであれば、それは多かれ少なかれトマホークと同じです。"
  },
  {
    "start": 3345715,
    "end": 3350203,
    "text": "それでも、一番上の PCI Express スロットは 5.0 ではなく、4.0 です。"
  },
  {
    "start": 3350259,
    "end": 3350443,
    "text": "うん。"
  },
  {
    "start": 3350459,
    "end": 3350883,
    "text": "わからない。"
  },
  {
    "start": 3350939,
    "end": 3355971,
    "text": "Edge が Pro やトマホークをどのように改善しているのかわかりません。"
  },
  {
    "start": 3356043,
    "end": 3356989,
    "text": "240ドルです。"
  },
  {
    "start": 3357124,
    "end": 3359091,
    "text": "B650Eではありません。"
  },
  {
    "start": 3359163,
    "end": 3361053,
    "text": "ただ本当に値段が高す​​ぎるような気がします。"
  },
  {
    "start": 3361109,
    "end": 3361605,
    "text": "見てみましょう。"
  },
  {
    "start": 3361645,
    "end": 3363997,
    "text": "このマザーボードを罰してもよいと思います。"
  },
  {
    "start": 3364061,
    "end": 3368885,
    "text": "単純に高すぎるので、どこかのB層に置くかもしれません。"
  },
  {
    "start": 3368965,
    "end": 3370749,
    "text": "入れなきゃいけないと思うよ。"
  },
  {
    "start": 3370837,
    "end": 3374525,
    "text": "14 フェーズ電源設計なので、それでもかなり立派です。"
  },
  {
    "start": 3374605,
    "end": 3379613,
    "text": "その価値はそれほど大きくないので、そこに置く必要があると思います。"
  },
  {
    "start": 3379709,
    "end": 3383011,
    "text": "B650 マザーボードとして十分なパフォーマンスを発揮するだけの性能を備えています。"
  },
  {
    "start": 3383086,
    "end": 3386261,
    "text": "この価格帯ではB650eで十分です。"
  },
  {
    "start": 3386333,
    "end": 3391614,
    "text": "ついに ASRock からクレイジーな B650 マザーボードが提供されました。"
  },
  {
    "start": 3391718,
    "end": 3393741,
    "text": "B650E タイチ ライト。"
  },
  {
    "start": 3393813,
    "end": 3400781,
    "text": "このマザーボードのスプレッドシートをチェックするだけで済みます。その価格には驚かれると思います。"
  },
  {
    "start": 3400893,
    "end": 3403957,
    "text": "$240は現在入荷待ちです。"
  },
  {
    "start": 3404021,
    "end": 3405885,
    "text": "これが優れたマザーボードであることを人々が知っているからです。"
  },
  {
    "start": 3405965,
    "end": 3412600,
    "text": "最大 105 アンペアを引き出すことができる 2421 パワー フェイス デザインを採用している理由。"
  },
  {
    "start": 3412723,
    "end": 3416935,
    "text": "これは B650 マザーボードにとってはやりすぎです。"
  },
  {
    "start": 3417059,
    "end": 3423452,
    "text": "240 ドルだったので、B650E である必要があるため、Edge WI Fi にペナルティを課すつもりだと今考えました。"
  },
  {
    "start": 3423540,
    "end": 3431395,
    "text": "B650E Aorus Elite X 軸には価格の割に優れた VRM が搭載されていないため、ペナルティを課すつもりです。"
  },
  {
    "start": 3431483,
    "end": 3442329,
    "text": "さて、ここにB650E Taichi Liteがありますが、これはB650Eボードであることに加えて、その価格で見た中で最高のVRMを備えたマザーボードの両方を完全に台無しにします。"
  },
  {
    "start": 3442417,
    "end": 3446489,
    "text": "これは実際にはそれ自体で層を取得することになります。"
  },
  {
    "start": 3446577,
    "end": 3451425,
    "text": "SS レベルでこの価格でそれがどれほどモンスターであるかということです。"
  },
  {
    "start": 3451465,
    "end": 3457569,
    "text": "私たちは B650E Taichi Lite をまさにトップに据えています。"
  },
  {
    "start": 3457697,
    "end": 3462225,
    "text": "このマザーボード以上にお金をかける必要があるとは思えません。"
  },
  {
    "start": 3462265,
    "end": 3466555,
    "text": "B650 マザーボードを搭載した完全な AMD ゲーミング PC が必要な場合。"
  },
  {
    "start": 3466635,
    "end": 3471163,
    "text": "このマザーボードには、これまで述べてきたすべてに加えて、すべてが備わっています。"
  },
  {
    "start": 3471219,
    "end": 3476886,
    "text": "16 コア CPU を徹底的にオーバークロックしたい場合は、それができると思います。"
  },
  {
    "start": 3476966,
    "end": 3480763,
    "text": "105アンペアということは、ご存知のとおり、扱うには多くの電流です。"
  },
  {
    "start": 3480819,
    "end": 3482155,
    "text": "先ほども言ったように、人々はそれが良いことを知っています。"
  },
  {
    "start": 3482195,
    "end": 3483739,
    "text": "現在 Newegg でバックオーダー中です。"
  },
  {
    "start": 3483787,
    "end": 3485715,
    "text": "ああ、マザーボードが 4 枚残っています。"
  },
  {
    "start": 3485755,
    "end": 3486855,
    "text": "私たちはとても近いです。"
  },
  {
    "start": 3487275,
    "end": 3494200,
    "text": "Asus は、これがこの高価な価格帯の VC 650e ボードではないため、すでに問題があると感じています。"
  },
  {
    "start": 3494276,
    "end": 3496993,
    "text": "B650 ですが、それでも見ておかなければなりません。"
  },
  {
    "start": 3497049,
    "end": 3500257,
    "text": "わかりました、では 240 ドルですが、どこから来たのかわかりますか?"
  },
  {
    "start": 3500321,
    "end": 3505026,
    "text": "24 プラス 2 プラス 1 電源フェーズ設計のマザーボードから来ました。"
  },
  {
    "start": 3505093,
    "end": 3508793,
    "text": "ここでは 12 プラス 2 で 240 という素晴らしい結果が与えられています。"
  },
  {
    "start": 3508929,
    "end": 3521343,
    "text": "見た目がクールであることはわかっていますし、正直なところ、これはゲーム用のほとんどすべての AMD ゲーム CPU に適していますが、机上だけで、同じ価格で信じられないほどのマザーボードをカバーしただけです。"
  },
  {
    "start": 3521439,
    "end": 3525743,
    "text": "これよりも安価で、これよりも優れた VRM 電源フェーズを備えたマザーボードは他にもあります。"
  },
  {
    "start": 3525839,
    "end": 3527015,
    "text": "意味がありません。"
  },
  {
    "start": 3527135,
    "end": 3528415,
    "text": "これは行かなければなりません。"
  },
  {
    "start": 3528575,
    "end": 3530479,
    "text": "いやあ、これはいけるのか。"
  },
  {
    "start": 3530607,
    "end": 3534103,
    "text": "これはずっと下まで行くつもりです。"
  },
  {
    "start": 3534159,
    "end": 3536263,
    "text": "それでいいですか？"
  },
  {
    "start": 3536319,
    "end": 3540067,
    "text": "なぜなら、少なくともエッジWi-Fiは14フェーズの電源設計を持っていたからです。"
  },
  {
    "start": 3540148,
    "end": 3540885,
    "text": "少なくとも。"
  },
  {
    "start": 3540967,
    "end": 3546591,
    "text": "B650E Aorus Elite X AX には、少なくとも PCHN 5.0 スロットが搭載されていました。"
  },
  {
    "start": 3546663,
    "end": 3549021,
    "text": "これにはどちらも備わっておらず、両方をボルトで締めるよりもコストがかかります。"
  },
  {
    "start": 3549093,
    "end": 3550565,
    "text": "実際はこれと同じくらいの値段になります。"
  },
  {
    "start": 3550605,
    "end": 3551837,
    "text": "罰則を科すのでしょうか？"
  },
  {
    "start": 3551941,
    "end": 3553965,
    "text": "はい、ここに投げようと思います。"
  },
  {
    "start": 3554045,
    "end": 3557445,
    "text": "B650マザーボードとしては高すぎます。"
  },
  {
    "start": 3557525,
    "end": 3560445,
    "text": "価格に見合った実質的なものは何も提供していません。"
  },
  {
    "start": 3560525,
    "end": 3568373,
    "text": "つまり、ほとんどすべてのゲーム アプリケーションには問題ありませんが、客観的に見て、より安く、同じ価格でより優れたマザーボードがあります。"
  },
  {
    "start": 3568469,
    "end": 3569421,
    "text": "もうすぐそこです。"
  },
  {
    "start": 3569493,
    "end": 3573173,
    "text": "Asus Rog Strix B650E F."
  },
  {
    "start": 3573229,
    "end": 3576063,
    "text": "さて、この階層リストには限界があったと言うべきでしょう。"
  },
  {
    "start": 3576119,
    "end": 3583007,
    "text": "B650 マザーボードに 250 ドル以上を費やすつもりなら、その選択に文句を言う理由はありません。"
  },
  {
    "start": 3583071,
    "end": 3586927,
    "text": "これから説明するような B650E である限り、問題はありません。"
  },
  {
    "start": 3586991,
    "end": 3595509,
    "text": "ここでは B650E F が約 260 ドルか 250 ドルで、10 ドル割引のプロモーション クーポン (12 プラス 2)​​ が付いています。"
  },
  {
    "start": 3595592,
    "end": 3602537,
    "text": "少なくとも PC エンジン 5.0 です。なぜなら、B650E はやはり高すぎるからです。"
  },
  {
    "start": 3602671,
    "end": 3604381,
    "text": "このマザーボードには何も問題はありません。"
  },
  {
    "start": 3604453,
    "end": 3606221,
    "text": "それは単純に高すぎます。"
  },
  {
    "start": 3606293,
    "end": 3607493,
    "text": "はい、本当にカッコいいですね。"
  },
  {
    "start": 3607549,
    "end": 3610469,
    "text": "はい、これは Asus のボードですが、価格が高すぎます。"
  },
  {
    "start": 3610517,
    "end": 3616805,
    "text": "さて、少なくともそれはB650Eであり、それを少し補っていますが、それでも価格の点で最も素晴らしいとは言えません。"
  },
  {
    "start": 3616925,
    "end": 3621757,
    "text": "これはB層の最下位になると思います。"
  },
  {
    "start": 3621861,
    "end": 3626693,
    "text": "つまり、それは高すぎるし、12フェーズのデザインなのです。"
  },
  {
    "start": 3626789,
    "end": 3628993,
    "text": "つまり、ゲームには良いのですが、"
  },
  {
    "start": 3629029,
    "end": 3634073,
    "text": "私たちはちょうど 14 フェーズと 16 フェーズのマザーボードについて話しており、ここでは最上位にある 24 フェーズのマザーボードについても話しました。"
  },
  {
    "start": 3634129,
    "end": 3635353,
    "text": "これにはレベルがあります。"
  },
  {
    "start": 3635449,
    "end": 3639089,
    "text": "はい、では MSI MPG B650i エッジ、ということで。"
  },
  {
    "start": 3639177,
    "end": 3643345,
    "text": "msi 用の ITX ボードが必要だと思っていたので、これは同情的な選択でした。"
  },
  {
    "start": 3643425,
    "end": 3645321,
    "text": "私はこれで転がるつもりです。"
  },
  {
    "start": 3645513,
    "end": 3646513,
    "text": "これは大丈夫です。"
  },
  {
    "start": 3646609,
    "end": 3648801,
    "text": "正直に言うと、今はスペックシートを調べる気はありません。"
  },
  {
    "start": 3648833,
    "end": 3650177,
    "text": "いったいどこにランク付けしたのか見ていきたいと思います。"
  },
  {
    "start": 3650201,
    "end": 3651001,
    "text": "どこに置きましたか？"
  },
  {
    "start": 3651073,
    "end": 3659451,
    "text": "Edge WI FI の方が高価であるにもかかわらず、Edge Wi Fi よりも B650i Aorus Ultra の方がお買い得だというのがコンセンサスだと思います。"
  },
  {
    "start": 3659523,
    "end": 3661603,
    "text": "これはいけると思います。"
  },
  {
    "start": 3661699,
    "end": 3664935,
    "text": "ITX マザーボードの場合はここに当てはまる可能性があります。"
  },
  {
    "start": 3665515,
    "end": 3681163,
    "text": "そうですね、繰り返しになりますが、ITX マザーボードとしては、そのことについては少し同情する必要があります。これらの ITX ボードは、標準の Micro ATX または ATX マザーボードよりも製造コストが少し高くなりますが、Ultra は、米国のより優れた ITX マザーボードです。私が読んだもの、特に価格について。"
  },
  {
    "start": 3681259,
    "end": 3688295,
    "text": "これで、最終的に、この Tier リストの最後のマザーボード、NZXT N7B650E が残ります。"
  },
  {
    "start": 3688335,
    "end": 3693087,
    "text": "この階層リストに NZXT マザーボードを含めるとは思わなかったでしょうが、ここに含めておきます。"
  },
  {
    "start": 3693151,
    "end": 3697215,
    "text": "このマザーボードがどのようなものか見てみましょう。Newegg で今すぐ調べてみましょう。"
  },
  {
    "start": 3697295,
    "end": 3700071,
    "text": "一つだけNZXTの功績を認めなければなりません。"
  },
  {
    "start": 3700143,
    "end": 3702423,
    "text": "これは実際にはまともなマザーボードです。"
  },
  {
    "start": 3702479,
    "end": 3706951,
    "text": "これは B650E チップセットの一部であり、非常に優れています。"
  },
  {
    "start": 3707023,
    "end": 3712322,
    "text": "ここのスペックシートを見ると、これは A16 プラス 2 プラス 1 電源フェーズ設計になっています。"
  },
  {
    "start": 3712395,
    "end": 3719363,
    "text": "グラフィックス カード用の PCI Express スロットと M2 スロットの両方に非常に優れた PCIe Gen 5.0 が搭載されています。"
  },
  {
    "start": 3719459,
    "end": 3720019,
    "text": "悪くないよ。"
  },
  {
    "start": 3720107,
    "end": 3722155,
    "text": "繰り返しになりますが、NZXT ボードです。"
  },
  {
    "start": 3722235,
    "end": 3723659,
    "text": "はい、素晴らしいですね。"
  },
  {
    "start": 3723707,
    "end": 3730763,
    "text": "マザーボード上にあるこの非常にやりすぎな VRM ヒートシンク スラッシュ プレートは、熱対策に役立ちます。"
  },
  {
    "start": 3730859,
    "end": 3732099,
    "text": "これはそれほど粗末ではありません。"
  },
  {
    "start": 3732147,
    "end": 3738309,
    "text": "はい、290 ですが、270 の黒について先ほど見たように Newegg を確認すると、これで問題ありません。"
  },
  {
    "start": 3738467,
    "end": 3740737,
    "text": "素晴らしいことではありませんが、大丈夫です。"
  },
  {
    "start": 3740801,
    "end": 3743761,
    "text": "特に、先ほど紹介した他の ASUS ボードのいくつかと比較してください。"
  },
  {
    "start": 3743793,
    "end": 3747954,
    "text": "少なくとも、これはかなり優れた VRM を備えた B650E チップセットだからです。"
  },
  {
    "start": 3748042,
    "end": 3750513,
    "text": "16 +2 +1 はまだ非常に優れています。"
  },
  {
    "start": 3750569,
    "end": 3754165,
    "text": "これは段に入るし、入れようと思う。"
  },
  {
    "start": 3754625,
    "end": 3757913,
    "text": "さて、Aerog も同じ位相設計です。"
  },
  {
    "start": 3758049,
    "end": 3762273,
    "text": "唯一の違いは、B650e チップセットが PCHN 5.0 を搭載していることです。"
  },
  {
    "start": 3762329,
    "end": 3762545,
    "text": "ああ。"
  },
  {
    "start": 3762585,
    "end": 3766331,
    "text": "ニュージーランドの物価を考えると、行かなければならないと思います。"
  },
  {
    "start": 3766523,
    "end": 3768315,
    "text": "そこに投げるつもりです。"
  },
  {
    "start": 3768435,
    "end": 3770755,
    "text": "はい、そのままにしておきます。"
  },
  {
    "start": 3770835,
    "end": 3771739,
    "text": "そこにあります。"
  },
  {
    "start": 3771787,
    "end": 3772875,
    "text": "それが階層リストです。"
  },
  {
    "start": 3772915,
    "end": 3775107,
    "text": "私はこれらすべての選択肢にかなり慣れています。"
  },
  {
    "start": 3775171,
    "end": 3777787,
    "text": "つまり、これらのいくつかはあちこちを動き回る可能性があります。"
  },
  {
    "start": 3777851,
    "end": 3783035,
    "text": "おそらく、エアロ G とトマホークのように、どちらの割引が有利かによって順位が入れ替わる可能性もあります。"
  },
  {
    "start": 3783115,
    "end": 3786179,
    "text": "全体として、ASRock はうまくいったと思います。"
  },
  {
    "start": 3786252,
    "end": 3787835,
    "text": "B650チップセット用。"
  },
  {
    "start": 3787875,
    "end": 3798089,
    "text": "価格、パフォーマンスのチップ セット、PC Edge N 5.0 の可用性を最適に組み合わせたものと、価格に対して最高の VRM を提供しています。"
  },
  {
    "start": 3798217,
    "end": 3817113,
    "text": "それは ASRock のこれらのマザーボード、特に Tai Chi Lite は 240 で 24.2One の電源フェーズを提供し、B650E Steel Legend は 200 で 16.2One を提供し、PG Riptide は 14 プラス 2 プラス 1 で 190 を提供します。"
  },
  {
    "start": 3817209,
    "end": 3826233,
    "text": "それなら、それより安くても、PG Lightning と Live Mixer が 150 ドルです。ただし、これらには再び Wi Fi オファーが付属しません。つまり、14 プラス 2 プラス 1 です。"
  },
  {
    "start": 3826296,
    "end": 3831569,
    "text": "ASRock はそれを見事に成功させましたが、2 番目に来るのはおそらく MSI になると思います。"
  },
  {
    "start": 3831632,
    "end": 3835649,
    "text": "彼らは、200ドル以上を除いて、全体的に非常に優れたVRMを価格で提供しています。"
  },
  {
    "start": 3835712,
    "end": 3840681,
    "text": "200.00ドルを超えると、手頃な価格のB650Eマザーボードが提供されていないため、残念ながらほぼ横ばいになります。"
  },
  {
    "start": 3840766,
    "end": 3843222,
    "text": "はい、それだけです。"
  },
  {
    "start": 3843307,
    "end": 3850049,
    "text": "200 ドルを超えると MSI は横ばいになりますが、200 ドル未満では依然としてかなりまともですが、ASRock ほどの価値はありません。"
  },
  {
    "start": 3850097,
    "end": 3852497,
    "text": "3番目はギガバイトになると思います。"
  },
  {
    "start": 3852641,
    "end": 3857977,
    "text": "Eagle AX、Aorus Elite AX、Aero G など、良いオプションがあちこちにあります。"
  },
  {
    "start": 3858041,
    "end": 3862937,
    "text": "他のマザーボードの一部には価格の問題があり、残念ながらそれが彼らに損害を与えています。"
  },
  {
    "start": 3863041,
    "end": 3867329,
    "text": "ASUSはおそらく、低価格マザーボードにとって最悪のことをしたでしょう。"
  },
  {
    "start": 3867417,
    "end": 3874941,
    "text": "同社の VRM は非常に不十分で、特に価格の割に 4 相電源設計しか提供していないプライム シリーズはかなりひどいものです。"
  },
  {
    "start": 3875013,
    "end": 3878709,
    "text": "そして、ボードのハイエンドに行くほど、価格が高すぎるだけです。"
  },
  {
    "start": 3878757,
    "end": 3881429,
    "text": "必ずしも悪いわけではなく、ただ値段が高す​​ぎるだけです。"
  },
  {
    "start": 3881477,
    "end": 3883005,
    "text": "特にROGシリーズ。"
  },
  {
    "start": 3883085,
    "end": 3884501,
    "text": "彼らの厳しい人たちは大丈夫です。"
  },
  {
    "start": 3884613,
    "end": 3888893,
    "text": "ここにあるタフなボードが割引になったら、かなり良い買い物になるでしょう。"
  },
  {
    "start": 3888949,
    "end": 3893861,
    "text": "全体として、Asus はビッグ 4 の中で最悪のパフォーマンスを示していると思います。"
  },
  {
    "start": 3893893,
    "end": 3896357,
    "text": "このビデオを気に入っていただけたなら、最後までご覧いただけて嬉しいです。"
  },
  {
    "start": 3896421,
    "end": 3904703,
    "text": "「いいね！」をしてください。この種の Tier リストのビデオが気に入ったら、私は時々作成します。気に入ったら、購読したい場合は、おそらくさらにいくつか作成します。"
  },
  {
    "start": 3904759,
    "end": 3909455,
    "text": "以上、ご視聴いただき誠にありがとうございました。Skybolt チャンネルはサインアウトしました。"
  }
]