[
  {
    "start": 410,
    "end": 9070,
    "text": "私たちは、もしかしたら予想もしていなかったような言語モデルのつながりを目にすることになるかもしれないが、それはとても現実的なことなのだ。"
  },
  {
    "start": 9140,
    "end": 13546,
    "text": "まずは、スティーブン・パンタドシがいることが幸運だ。"
  },
  {
    "start": 13738,
    "end": 21258,
    "text": "彼はカリフォルニア大学バークレー校の心理学と神経科学の教授で、AIの友人でもある。"
  },
  {
    "start": 21354,
    "end": 35078,
    "text": "実際、私たちは一緒に助成金を受けており、AIに携わる私たちの多くは、心理学者から学び、彼らが私たちの仕事にどのようなインスピレーションを与えてくれるのかに興奮し、興味を持っている。"
  },
  {
    "start": 35164,
    "end": 44438,
    "text": "というのも、心理学者たちもまた、人間について何かを理解するための言語モデルに興奮しているからだ。"
  },
  {
    "start": 44534,
    "end": 49670,
    "text": "スティーブンは、彼がしてきた仕事について話してくれるだろう。"
  },
  {
    "start": 49750,
    "end": 55534,
    "text": "それで、スティーブン、ここで話す機会を与えてくれてありがとう。"
  },
  {
    "start": 55652,
    "end": 61466,
    "text": "大規模な言語モデルの時代における意味、あるいは大規模な言語モデルの時代における意味の発見について話すつもりだ。"
  },
  {
    "start": 61498,
    "end": 67780,
    "text": "この講演は、言語モデルや評価などに関する技術的な話ではない。"
  },
  {
    "start": 68310,
    "end": 101174,
    "text": "それは哲学に近いというか、認知科学や心理学における高度な理論に近いもので、意味や、言語や意味論において意味がどこから来るのかという人々の考え方の歴史や、大規模な言語モデルの文脈でそれらをどのように考えることができるのか、特に大規模な言語モデルに関する議論の文脈では、それらは単なる確率的なオウム返しであり、理解という形を持っていないのか、それとも理解する意味があるのか、というようなことです。"
  },
  {
    "start": 101222,
    "end": 110542,
    "text": "もし彼らが何らかの理解を持っているのであれば、その理解の形が人々が持つ理解の種類と少しでも関係があるのであれば。"
  },
  {
    "start": 110676,
    "end": 126040,
    "text": "まず、一般的な意味と参照についてお話しし、大規模な言語モデルにおける主張と、なぜ意味や本当の意味論がないと思われがちなのかについてお話しします。"
  },
  {
    "start": 126410,
    "end": 135190,
    "text": "それから、意味に関するいくつかの心理学理論と、概念的役割と呼ばれるものからどのように意味が生まれるかについてお話しします。"
  },
  {
    "start": 135690,
    "end": 151546,
    "text": "大規模言語モデルに戻って、大規模言語モデルや一般的な機械学習システムにおける概念役割の学習について少しお話しします。"
  },
  {
    "start": 151728,
    "end": 159966,
    "text": "2020年のベンダーとコーラーの論文だ。"
  },
  {
    "start": 160068,
    "end": 173086,
    "text": "エミリー・ベンダーは言語学者として訓練を受けたコンピューター科学者で、ワシントン大学に在籍している。"
  },
  {
    "start": 173278,
    "end": 189100,
    "text": "私が最初に興味を持ったのは、大規模な言語モデルの有意性についての主張と、テキストで訓練された統計モデルができることにはまったく意味がないという本質的な議論だったと思います。"
  },
  {
    "start": 189870,
    "end": 197034,
    "text": "ベンダーとコーラーは、彼らがタコテストと呼ぶ、この点を非常にうまく説明する方法を考え出した。"
  },
  {
    "start": 197232,
    "end": 199510,
    "text": "タコのテストは次のようなものだ。"
  },
  {
    "start": 199590,
    "end": 207770,
    "text": "つまり、彼らにとっての出発点は、意味とは、ある単語と言語の外部にある何かとの間の関連性なのだ。"
  },
  {
    "start": 207850,
    "end": 208142,
    "text": "いいかい？"
  },
  {
    "start": 208196,
    "end": 213760,
    "text": "本の意味は、物理的な物体、つまり世の中に出ている本である。"
  },
  {
    "start": 214130,
    "end": 214926,
    "text": "それはわかるだろう。"
  },
  {
    "start": 214948,
    "end": 215374,
    "text": "その通りだ。"
  },
  {
    "start": 215412,
    "end": 217806,
    "text": "それが物理的な物体にラベルを貼る方法だからだ。"
  },
  {
    "start": 217838,
    "end": 219282,
    "text": "単語を覚えるときにね。"
  },
  {
    "start": 219336,
    "end": 222814,
    "text": "私たちは、周りに本があれば本という言葉を耳にし、その連想から本を手にする。"
  },
  {
    "start": 222862,
    "end": 232760,
    "text": "つまり、現実世界の何かを外から参照するというのが、この言葉の根本的な意味なんだ。"
  },
  {
    "start": 233850,
    "end": 239974,
    "text": "ベンダーとコーラーは、よし、それを意味の定義として、タコを想像してみよう、と言う。"
  },
  {
    "start": 240022,
    "end": 250218,
    "text": "海中に住むタコが、2つの島の間の通信チャンネル、例えば電話線を盗聴したんだ。"
  },
  {
    "start": 250304,
    "end": 251326,
    "text": "タコはそこにいる。"
  },
  {
    "start": 251348,
    "end": 258190,
    "text": "この2つの島の間で起こるすべてのコミュニケーションを盗聴することで、膨大な量の言語的インプットを得ることができる。"
  },
  {
    "start": 259010,
    "end": 268418,
    "text": "とても賢いタコなら、その通信チャネルで起きていることの統計的特性をすべて学習できるかもしれないと想像できるだろう？"
  },
  {
    "start": 268504,
    "end": 272082,
    "text": "文章を予測するのが得意になるかもしれない。"
  },
  {
    "start": 272136,
    "end": 273918,
    "text": "もしかしたら、最適な予測ができるかもしれない。"
  },
  {
    "start": 274094,
    "end": 282850,
    "text": "彼らの主張はともかく、タコは物理的な参照にアクセスすることができないので、実際に意味を学ぶことはできないということだ。"
  },
  {
    "start": 283010,
    "end": 283720,
    "text": "そうだろう？"
  },
  {
    "start": 286490,
    "end": 286854,
    "text": "そうだね。"
  },
  {
    "start": 286892,
    "end": 291340,
    "text": "チャイニーズ・ルームとはちょっと違うのが面白い。"
  },
  {
    "start": 292030,
    "end": 295740,
    "text": "もしよければ、その質問は最後に回してもいいですか？"
  },
  {
    "start": 296270,
    "end": 300602,
    "text": "中国人の部屋で起きていることは、後で私が話すことでより理解できると思うからだ。"
  },
  {
    "start": 300656,
    "end": 300970,
    "text": "オーケー。"
  },
  {
    "start": 301040,
    "end": 303760,
    "text": "精神的には非常に似ていると言える。"
  },
  {
    "start": 304610,
    "end": 311434,
    "text": "このタコは物理的な参照にアクセスできないため、物理的なオブジェクトを含むタスクを解決することができなかった。"
  },
  {
    "start": 311482,
    "end": 311694,
    "text": "そうだね。"
  },
  {
    "start": 311732,
    "end": 322738,
    "text": "彼らにココナッツが何であるかを視覚的に認識させたとしたら、たとえココナッツという言葉が使われる場所の統計的性質をすべて知っていたとしても、物理的なものを解くことはできないだろう。"
  },
  {
    "start": 322824,
    "end": 326406,
    "text": "もちろん、これは大規模な言語モデルが置かれている状況だ。"
  },
  {
    "start": 326428,
    "end": 329014,
    "text": "少なくとも、テキストだけで訓練されたもの、ですね？"
  },
  {
    "start": 329052,
    "end": 330854,
    "text": "世界中のものにアクセスすることはできない。"
  },
  {
    "start": 330892,
    "end": 334760,
    "text": "テキストがあるだけだ。"
  },
  {
    "start": 335930,
    "end": 339480,
    "text": "したがって、このタコには言葉の意味がない。"
  },
  {
    "start": 340250,
    "end": 346726,
    "text": "このようなタコは大規模な言語モデルのようなもので、テキストと予測能力しかないため、意味を与えることはできない。"
  },
  {
    "start": 346838,
    "end": 347258,
    "text": "そうだね。"
  },
  {
    "start": 347344,
    "end": 351850,
    "text": "意味とは、予測能力とは根本的に異なるものなのだ。"
  },
  {
    "start": 353090,
    "end": 355374,
    "text": "もうひとつ例を挙げよう。"
  },
  {
    "start": 355412,
    "end": 360606,
    "text": "まあ、表面的にはある程度説得力のある議論だと思うよ。"
  },
  {
    "start": 360628,
    "end": 367982,
    "text": "このように意味を考えると、説得力がある。"
  },
  {
    "start": 368046,
    "end": 382920,
    "text": "数学者にとっては説得力に欠けるかもしれない。"
  },
  {
    "start": 383290,
    "end": 384854,
    "text": "心の中でそう思ってください。"
  },
  {
    "start": 385052,
    "end": 385830,
    "text": "ああ、素晴らしい。"
  },
  {
    "start": 385900,
    "end": 394940,
    "text": "というのも、数学者が公理について考えることは、これからお話しする別の意味のバージョンと大いに関係があるからです。"
  },
  {
    "start": 395790,
    "end": 399146,
    "text": "ヒルベルトが望んだように。"
  },
  {
    "start": 399168,
    "end": 409934,
    "text": "ヒルベルトの望みは、ユークリッド幾何学を公理の集合に変換し、すべての記号を任意のスクイグルに置き換えてもシステムが機能するようにすることだった。"
  },
  {
    "start": 410132,
    "end": 413870,
    "text": "それはヒルベルトが幾何学の公理化で行ったことである。"
  },
  {
    "start": 414210,
    "end": 424900,
    "text": "ええ、ほとんどの数学者は少し違った意味を持っていると思いますが、私が数分後に話すことと同じ意味です。"
  },
  {
    "start": 426490,
    "end": 432066,
    "text": "言語モデルにおける意味について、もうひとつだけ説明しよう。"
  },
  {
    "start": 432098,
    "end": 434630,
    "text": "ゲイリー・マーカスがラムダについて語っている。"
  },
  {
    "start": 434970,
    "end": 437602,
    "text": "実際のところ、システムが言うことは文字通りすべてでたらめだ。"
  },
  {
    "start": 437666,
    "end": 444380,
    "text": "ラムダの発言はでたらめであり、予測ワードツールを使った単なるゲームであり、本当の意味はないことに早く気づけば、私たちはより良い生活を送ることができる。"
  },
  {
    "start": 445310,
    "end": 448250,
    "text": "ラムダのようなソフトウェアは、広く世界とつながろうともしない。"
  },
  {
    "start": 448320,
    "end": 448506,
    "text": "そうだろう？"
  },
  {
    "start": 448528,
    "end": 450646,
    "text": "それが彼の考えるデタラメなのだ。"
  },
  {
    "start": 450758,
    "end": 453550,
    "text": "ただ、オートコンプリートのベストバージョンになろうとしているだけだ。"
  },
  {
    "start": 453620,
    "end": 460240,
    "text": "彼らは、文章を世界と関連づけるという意味での言語を理解しているのではなく、ただ言葉の並びを互いに関連づけるだけなのだ。"
  },
  {
    "start": 462370,
    "end": 468926,
    "text": "私がこのことに興味を持ったのは、この見解に説得力を感じたからでもある。"
  },
  {
    "start": 469118,
    "end": 471682,
    "text": "その一方で、ある種の深い間違いだとも思う。"
  },
  {
    "start": 471736,
    "end": 483670,
    "text": "それが深く間違っている点については、機械学習モデルだけでなく、人間の心における概念表現と意味についても言えることで、実に興味深い。"
  },
  {
    "start": 484010,
    "end": 500602,
    "text": "数年前、私はディープマインドの研究者であるフェリックス・ヒルとチームを組み、基本的に「意味とはこのような参照形式ではない」という議論を経て論文を書いた。"
  },
  {
    "start": 500656,
    "end": 512846,
    "text": "実際、意味が世界の物事との対応付けと同一視されるべきだという考え方は、言語学や哲学、認知科学の人々によってしばしば否定されてきた。"
  },
  {
    "start": 513028,
    "end": 524274,
    "text": "例えば、多くの概念や言葉には、外界との関連性がないものがたくさんあるよね？"
  },
  {
    "start": 524312,
    "end": 526082,
    "text": "機能語はその好例である。"
  },
  {
    "start": 526136,
    "end": 528790,
    "text": "twoとかisとかmanyとか。"
  },
  {
    "start": 528940,
    "end": 533670,
    "text": "その言葉が指し示す世界には、2つしかない。"
  },
  {
    "start": 533820,
    "end": 536760,
    "text": "また、世界に出ているわけでも、たくさんいるわけでもない。"
  },
  {
    "start": 537130,
    "end": 539190,
    "text": "これらは言語における機能語である。"
  },
  {
    "start": 539270,
    "end": 546922,
    "text": "彼らがやっていることは、数学の演算子とかがやっているようなことに似ているよね？"
  },
  {
    "start": 546976,
    "end": 549478,
    "text": "これらの言葉には内的な意味がある。"
  },
  {
    "start": 549654,
    "end": 559706,
    "text": "つまり、文の意味を表現するためには、言語表現の内部で文が構成されなければならない。"
  },
  {
    "start": 559738,
    "end": 559934,
    "text": "そうだろう？"
  },
  {
    "start": 559972,
    "end": 562400,
    "text": "彼らは世界の何かを指し示しているのではない。"
  },
  {
    "start": 563010,
    "end": 571554,
    "text": "このような機能的な言葉でなくとも、意味は世の中にあるものだという一種の見方では、意味を理解するのが非常に難しい言葉は他にもある。"
  },
  {
    "start": 571592,
    "end": 574718,
    "text": "正義のような非常に抽象的な言葉を思い浮かべることができる。"
  },
  {
    "start": 574894,
    "end": 576754,
    "text": "そこに正義はないだろう。"
  },
  {
    "start": 576792,
    "end": 579730,
    "text": "それは私たちが持っている、あるいはウィットのようなものだ。"
  },
  {
    "start": 579890,
    "end": 582418,
    "text": "あるいは、ドラゴンのように存在しないものを考えることもできる。"
  },
  {
    "start": 582514,
    "end": 583014,
    "text": "そうだろう？"
  },
  {
    "start": 583132,
    "end": 586630,
    "text": "ドラゴンのような外的なものはこの世に存在しない。"
  },
  {
    "start": 586970,
    "end": 591930,
    "text": "私たちが持っている言葉や概念には、世界とはまったく関係のないものだってあるでしょ？"
  },
  {
    "start": 592000,
    "end": 596650,
    "text": "架空の自転車について考えるなら、それは定義上、架空のものだ。"
  },
  {
    "start": 597150,
    "end": 598442,
    "text": "外にはないんだ。"
  },
  {
    "start": 598576,
    "end": 600394,
    "text": "それとも永久機関？"
  },
  {
    "start": 600432,
    "end": 611418,
    "text": "私たちは永久機関という概念を持ち、それについて考え、推論することはできるが、普通の概念でさえ、世の中に存在しないことは確かだ。"
  },
  {
    "start": 611594,
    "end": 617282,
    "text": "私たちは、そのコンセプトの参照になりうるすべての可能性を検討したわけでもないでしょう？"
  },
  {
    "start": 617336,
    "end": 625700,
    "text": "私がナスで作った靴を履いて店内に入れば、それを見て、誰もが靴だと納得するだろう？"
  },
  {
    "start": 626230,
    "end": 630406,
    "text": "茄子で作られた靴を見たことがなくても、それが靴であることに同意するだろう。"
  },
  {
    "start": 630508,
    "end": 630822,
    "text": "そうだろう？"
  },
  {
    "start": 630876,
    "end": 637094,
    "text": "世の中に靴だと誰もが認めるものがある。"
  },
  {
    "start": 637132,
    "end": 641338,
    "text": "ということは、靴かどうかを決めるのは、世の中にあるものではあり得なかったということだよね？"
  },
  {
    "start": 641424,
    "end": 646202,
    "text": "靴を靴たらしめているのは、もっと抽象的な概念に違いないだろう？"
  },
  {
    "start": 646256,
    "end": 650540,
    "text": "関数や原点といったものが、どのように使われるかを考えることができる。"
  },
  {
    "start": 651070,
    "end": 657242,
    "text": "物体のこうした他の種類の性質は、概念の分類にとってはるかに重要であるようだ。"
  },
  {
    "start": 657306,
    "end": 667874,
    "text": "植物の靴はまだ靴とみなされるかもしれないが、アイスクリームの靴はおそらくそうだろう。"
  },
  {
    "start": 667992,
    "end": 670002,
    "text": "誰も靴だと気づかないだろう？"
  },
  {
    "start": 670136,
    "end": 671886,
    "text": "それなら、アイスクリームの靴のことは考えない。"
  },
  {
    "start": 671918,
    "end": 679766,
    "text": "靴として思いつくものが小さな器に入っているようなもので、すでに遠すぎるものについては考えない。"
  },
  {
    "start": 679788,
    "end": 684246,
    "text": "一番近い現実の物体までは、まだ少し距離があるようだ。"
  },
  {
    "start": 684428,
    "end": 685160,
    "text": "そうだね。"
  },
  {
    "start": 687290,
    "end": 692666,
    "text": "これらはすべて、実物が無関係だと言っているわけではない。"
  },
  {
    "start": 692768,
    "end": 701530,
    "text": "私は、アイスクリームよりもナスの方が靴としてはるかに妥当であることに同意する。"
  },
  {
    "start": 701870,
    "end": 705478,
    "text": "私が言いたいのは、物理的なことが決定的なことではないということだ。"
  },
  {
    "start": 705504,
    "end": 709294,
    "text": "靴かそうでないかを判断するのは、対象物の中にある何かではないでしょう？"
  },
  {
    "start": 709412,
    "end": 713460,
    "text": "どのように使われるのかとか、どのように作られるのかとか、そういう抽象的なものだ。"
  },
  {
    "start": 715190,
    "end": 732870,
    "text": "実は、この論文の中で郵便切手の概念について少し触れているのだが、これはおそらく人々が直感的に思いつくような例であり、これまで見てきた郵便切手とは根本的に異なる郵便切手を簡単に思いつくことができる。"
  },
  {
    "start": 732940,
    "end": 737490,
    "text": "例えば、ガラス製のもの、あるいはRFIDタグのようなものが考えられるだろう。"
  },
  {
    "start": 737650,
    "end": 744730,
    "text": "郵便切手と呼ぶべきものには、おそらく誰もが同意するような物理的な化身があるはずだ。"
  },
  {
    "start": 745230,
    "end": 754574,
    "text": "郵便切手というのは、政府が手紙を配達するために、お金を払って手紙に貼るものだ。"
  },
  {
    "start": 754612,
    "end": 764978,
    "text": "この言葉が意味するものは、支払いとか手紙とか配達とか、そういった他の多くの用語と本質的に結びついている。"
  },
  {
    "start": 765144,
    "end": 767662,
    "text": "実際、これらの用語が意味を変えるのであれば。"
  },
  {
    "start": 767806,
    "end": 780422,
    "text": "例えば、人々が新しい支払い方法を開発し、ブロックチェーンか何かで支払うようになれば、少なくとも原理的には、切手がその方法で支払えることが自動的にわかるでしょう？"
  },
  {
    "start": 780476,
    "end": 788060,
    "text": "単にその言葉が他のものと結びついているというだけでなく、その意味が他のものと本質的に結びついているということなのだ。"
  },
  {
    "start": 789790,
    "end": 802486,
    "text": "それは、なぜ世の中にあるものを参照することが、意味について考える良い方法ではないのかということについての、ひとつの考え方だ。"
  },
  {
    "start": 802678,
    "end": 805198,
    "text": "一つの選択肢を教えよう。"
  },
  {
    "start": 805364,
    "end": 813598,
    "text": "実はその前に、他の選択肢をいくつか挙げておこう。"
  },
  {
    "start": 813684,
    "end": 817586,
    "text": "今話したのは、このようなワールド・マッピングの見方なんだよね？"
  },
  {
    "start": 817608,
    "end": 831974,
    "text": "ある言葉があり、その意味は物理的な物体や物である。概念や意味に対する他の種類の見方を考えることができる。ある種の特徴、宇宙的な見方、サポートベクターマシンとかがあるかもしれないね？"
  },
  {
    "start": 832012,
    "end": 833958,
    "text": "抽象的な特徴空間がある。"
  },
  {
    "start": 834044,
    "end": 846086,
    "text": "コンセプトとは、この空間における区切り線とか、領域とか、そういうもので、狭い範囲での用途では問題ないと思う。"
  },
  {
    "start": 846118,
    "end": 859546,
    "text": "次にお話しするのは、例えば人間の認知のケースですが、人が概念やその関係について考える方法は、より複雑であるという意味で、この図式にはうまく当てはまりません。"
  },
  {
    "start": 859658,
    "end": 863374,
    "text": "人々はこのようなヒエラルキーやネットワーク観を持っているかもしれないね。"
  },
  {
    "start": 863412,
    "end": 865586,
    "text": "時々、人々はこう考える。"
  },
  {
    "start": 865608,
    "end": 871410,
    "text": "真ん中にあるコンセプトブックと他のコンセプトブックをつなぐ線があるはずだろう？"
  },
  {
    "start": 871480,
    "end": 889270,
    "text": "例えば、意味論的な組織の古い理論や、非常に古いAIのようなアプローチは、概念の階層や、時には概念のネットワークを構築し、それらの関係性の中で意味を定義しようとするものです。"
  },
  {
    "start": 889350,
    "end": 903918,
    "text": "私は、このビューと特徴ビューとワールドマップビューの両方が、ある種の有用な特性や、概念に関する有用な洞察を持っていると思う。"
  },
  {
    "start": 904004,
    "end": 915586,
    "text": "このような別の概念の見方を紹介するために、最近のニュースから人々の直感を得ようと思う。"
  },
  {
    "start": 915688,
    "end": 919938,
    "text": "さて、ここでアメリカ対トランプの最近のニュースを少し。"
  },
  {
    "start": 920104,
    "end": 923940,
    "text": "これは直近の起訴ではなく、1つか2つ前の起訴だと思う。"
  },
  {
    "start": 924790,
    "end": 932838,
    "text": "目を通せば、ペンスとトランプ、そして選挙を操作するための努力などについてすべて読むことができる。"
  },
  {
    "start": 933004,
    "end": 936358,
    "text": "パラグラフのひとつ、90 C.を少しパラフレーズしてみよう。"
  },
  {
    "start": 936444,
    "end": 943542,
    "text": "ペンス副大統領（右）は、副大統領は選挙人票を拒否できると主張するトランプ陣営の訴訟に反対した。"
  },
  {
    "start": 943606,
    "end": 947830,
    "text": "ペンスは、選挙人票を拒否することができると主張されたくなかったのだ。"
  },
  {
    "start": 947990,
    "end": 952410,
    "text": "彼はトランプに対し、憲法上の権限はなく、その行動は不適切だと述べた。"
  },
  {
    "start": 952490,
    "end": 955438,
    "text": "これは当時のペンスのメモによるものだ。"
  },
  {
    "start": 955524,
    "end": 960330,
    "text": "ペンスのメモによれば、トランプは、君もそうだろう、と答えた。"
  },
  {
    "start": 960490,
    "end": 964690,
    "text": "その状況について、そしてこの状況について知っていることすべてについて考えてみてくれ。"
  },
  {
    "start": 964760,
    "end": 968820,
    "text": "なぜトランプはこんなことを言ったのか？"
  },
  {
    "start": 971430,
    "end": 988966,
    "text": "トランプが何を達成しようとしていたのか、トランプはどんな性格なのか、トランプはペンスに何をしようとしていたのか。"
  },
  {
    "start": 988998,
    "end": 992806,
    "text": "彼を操って何らかの行動を起こさせようとしているのだろうか？"
  },
  {
    "start": 992918,
    "end": 997606,
    "text": "その行動が選挙に与える影響とは？"
  },
  {
    "start": 997798,
    "end": 1006526,
    "text": "誰だって、これらを推論し、何が起こっているのかについて、ある種もっともらしい因果関係のストーリーを考え出すことは完璧にできるだろう？"
  },
  {
    "start": 1006548,
    "end": 1012574,
    "text": "このような出来事について、私たちは自分たちなりの内面的な説明を考え出すことができるような気がする。"
  },
  {
    "start": 1012772,
    "end": 1028706,
    "text": "実際、内的な説明、相互に関連する概念や意味を考え出すこのプロセスは、発達心理学の人たちが人間の認知の理論として非常に興味を持ち、興奮してきたものだ。"
  },
  {
    "start": 1028818,
    "end": 1036630,
    "text": "基本的な観察によれば、人は非常に豊かな相互関係を持った概念体系を形成している。"
  },
  {
    "start": 1036700,
    "end": 1044790,
    "text": "そのような質問に答えるために必要な、相互に関連したものすべてが、まったく普通に感じられる。"
  },
  {
    "start": 1044950,
    "end": 1047126,
    "text": "人々はこれを直感的理論と呼ぶことがある。"
  },
  {
    "start": 1047238,
    "end": 1058042,
    "text": "あなたは、トランプがどのように行動しているか、あるいは政治システムがどのように機能するか、あるいはペンスが何をしているか、あるいは何を達成しようとしているかについて、直感的な理論を持っている。"
  },
  {
    "start": 1058186,
    "end": 1062160,
    "text": "こういうことはよく科学の理論に例えられるよね？"
  },
  {
    "start": 1065170,
    "end": 1070722,
    "text": "トランプがなぜこのようなことをするのかというあなたの理論は、ちょっとした科学的理論に似ていると考えることができるだろう？"
  },
  {
    "start": 1070776,
    "end": 1074014,
    "text": "いくつかのピースがあり、ピース同士の関係もある。"
  },
  {
    "start": 1074062,
    "end": 1075490,
    "text": "ダイナミクスがある。"
  },
  {
    "start": 1075910,
    "end": 1084550,
    "text": "あなたが遭遇した他の種類のシステムについて推論するのと同じように、これらすべてを見て、因果関係を推論することができるかもしれない。"
  },
  {
    "start": 1084970,
    "end": 1102618,
    "text": "人は、そして特に子どもは、このような行動をとるという考えは、認知発達の分野で非常に有名なもので、ここバークレー校の発達心理学者であるアリソン・ゴスニックが最も顕著に提唱したものである。"
  },
  {
    "start": 1102794,
    "end": 1111210,
    "text": "この領域で、子供たち（子供と同じようなもの）を相手にした実験がどのように行われるか、簡単な例を挙げてみよう。"
  },
  {
    "start": 1111290,
    "end": 1116606,
    "text": "ラゾットとゲルマンの実験である。"
  },
  {
    "start": 1116798,
    "end": 1130854,
    "text": "子供たちは2匹のキツネを見せられ、それが同じ絵であることに気づくかもしれない。"
  },
  {
    "start": 1130892,
    "end": 1133558,
    "text": "トランプはなぜあんなことを言ったのか？"
  },
  {
    "start": 1133724,
    "end": 1136790,
    "text": "片方は動物で、片方はおもちゃだと言われるかもしれない。"
  },
  {
    "start": 1137710,
    "end": 1143500,
    "text": "どっちが動物でどっちがオモチャか判断するためにはどうしたらいいんだ？"
  },
  {
    "start": 1146590,
    "end": 1153758,
    "text": "この実験では、子供たちは内臓をチェックするとか、そういうことをするべきだと言うだろう？"
  },
  {
    "start": 1153844,
    "end": 1158846,
    "text": "開いて、彼らの行動を見たり、見たりするんだろう？"
  },
  {
    "start": 1159028,
    "end": 1166480,
    "text": "もし動物のように振る舞うのであれば、それを使ってどれが動物でどれがおもちゃか、あるいは両親を調べることができるだろう？"
  },
  {
    "start": 1167670,
    "end": 1171698,
    "text": "動物には動物の親がいて、おもちゃにはいないでしょう？"
  },
  {
    "start": 1171864,
    "end": 1175458,
    "text": "重要なのは、彼らは単に、ええ、あなたはこれらについてすべてをチェックすることができます、と言わないことだ。"
  },
  {
    "start": 1175544,
    "end": 1178066,
    "text": "例えば、年齢が関係ないことは知っているよね？"
  },
  {
    "start": 1178088,
    "end": 1180374,
    "text": "彼らはそれを教えてくれない。"
  },
  {
    "start": 1180572,
    "end": 1183858,
    "text": "年齢が上がれば、どれが動物でどれがおもちゃかわかるだろう。"
  },
  {
    "start": 1183954,
    "end": 1190134,
    "text": "概念的な表現という点では、このことが何を意味するのか、立ち止まって考えてみる価値はあるだろう？"
  },
  {
    "start": 1190332,
    "end": 1197194,
    "text": "何が動物を動物たらしめているのか、何が玩具たらしめているのか、切手の例と同じように考えてみればいい。"
  },
  {
    "start": 1197312,
    "end": 1205742,
    "text": "親とは何かとか、内臓はどうなっているのかとか、行動はどうなのかとか、そういう他のことと本質的につながっているんだ。"
  },
  {
    "start": 1205876,
    "end": 1207806,
    "text": "そのコンセプトは本質的にリンクしている。"
  },
  {
    "start": 1207828,
    "end": 1213360,
    "text": "未就学児の子供たちは、幼い頃からそのことを知っている。"
  },
  {
    "start": 1214530,
    "end": 1218260,
    "text": "一人は犬、一人は狼、あなたならどうする？"
  },
  {
    "start": 1219430,
    "end": 1221154,
    "text": "子供たちは基本的に同じことを言う。"
  },
  {
    "start": 1221192,
    "end": 1223374,
    "text": "内部をチェックすることもできるし、挙動を見ることもできる。"
  },
  {
    "start": 1223422,
    "end": 1227986,
    "text": "彼らの親を調べて、犬の親がいるか、狼の親がいるかを確認することができる。"
  },
  {
    "start": 1228168,
    "end": 1230102,
    "text": "この中には、ちょっと面白いものもあるよね？"
  },
  {
    "start": 1230156,
    "end": 1237714,
    "text": "少なくとも私は、犬と狼を見分けるために内側をどう見ればいいのか、誰も知らないと思うからだ。"
  },
  {
    "start": 1237762,
    "end": 1238360,
    "text": "そうだね。"
  },
  {
    "start": 1239450,
    "end": 1244618,
    "text": "もしかしたら、DNAを調べればわかるかもしれない。"
  },
  {
    "start": 1244784,
    "end": 1252422,
    "text": "このカテゴリーに属するということは、その概念に属するという他の側面に依存する何かがあるのだ。"
  },
  {
    "start": 1252486,
    "end": 1252810,
    "text": "そうだね。"
  },
  {
    "start": 1252880,
    "end": 1255150,
    "text": "まあ、私にはもっと単純に読めるけどね。"
  },
  {
    "start": 1255490,
    "end": 1259086,
    "text": "基本的に彼らが言っているのは、ルーク、これはすべて視覚的なものなんだ。"
  },
  {
    "start": 1259188,
    "end": 1261386,
    "text": "ただ、それを言語に投影しようとしているだけだ。"
  },
  {
    "start": 1261418,
    "end": 1267538,
    "text": "子供たちが言いたいのは、見ればわかる、遊べばわかるということだろう。"
  },
  {
    "start": 1267544,
    "end": 1268002,
    "text": "そうだね。"
  },
  {
    "start": 1268136,
    "end": 1270530,
    "text": "ビジョンと交流だ。"
  },
  {
    "start": 1270950,
    "end": 1271650,
    "text": "そうだね。"
  },
  {
    "start": 1271800,
    "end": 1272930,
    "text": "年齢はどちらでもない。"
  },
  {
    "start": 1273430,
    "end": 1273986,
    "text": "そうだね。"
  },
  {
    "start": 1274088,
    "end": 1277122,
    "text": "その通りだと思う。"
  },
  {
    "start": 1277256,
    "end": 1278914,
    "text": "これらはすべて視覚的な合図である。"
  },
  {
    "start": 1278962,
    "end": 1283734,
    "text": "非視覚的な手がかりに注目した実験を私は知らないが、そう思う。"
  },
  {
    "start": 1283772,
    "end": 1284982,
    "text": "ああ、それは興味深いね。"
  },
  {
    "start": 1285036,
    "end": 1289830,
    "text": "もうひとつ例を挙げよう。"
  },
  {
    "start": 1289980,
    "end": 1290342,
    "text": "そうだね。"
  },
  {
    "start": 1290396,
    "end": 1296518,
    "text": "一人はアマンダで、一人はメリッサだと言えば、テストはすべて却下される。"
  },
  {
    "start": 1296614,
    "end": 1297018,
    "text": "そうだね。"
  },
  {
    "start": 1297104,
    "end": 1300250,
    "text": "どっちがアマンダかなんて、内部は教えてくれないよ。"
  },
  {
    "start": 1300590,
    "end": 1302414,
    "text": "行動も、両親も、年齢も。"
  },
  {
    "start": 1302452,
    "end": 1304238,
    "text": "これらのことは起こらない。"
  },
  {
    "start": 1304324,
    "end": 1314878,
    "text": "つまり、人々は、子供でさえも、概念が他の概念とどのように関係するかについて、かなり洗練された理論を持っているということだ。"
  },
  {
    "start": 1315044,
    "end": 1320674,
    "text": "実際、このような状況では、視覚的にわかるものは何もないらしい。"
  },
  {
    "start": 1320712,
    "end": 1320914,
    "text": "そうだね。"
  },
  {
    "start": 1320952,
    "end": 1322638,
    "text": "これは視覚的な識別課題ではない。"
  },
  {
    "start": 1322654,
    "end": 1329400,
    "text": "それは本当に、他の種類の概念的な特徴や物事に目を向けるよう求める、一種の概念的なものだ。"
  },
  {
    "start": 1330970,
    "end": 1344940,
    "text": "このような直感的な理論を持っている人たちは、その理論において言葉やシンボル、概念が果たす役割から意味が生まれるということを、かなり多くの人たちが主張していますよね。"
  },
  {
    "start": 1345470,
    "end": 1362750,
    "text": "アニマルの意味は、アニマルをテストする方法、アニマルの特徴、そしてアニマルと単純な意味的関連ではなく、直感的な理論という意味で深く結びついている他のすべてのものと、実に本質的に関係しているのだ。"
  },
  {
    "start": 1363190,
    "end": 1386774,
    "text": "例えば、起訴とは何かを定義しようとした場合、他の法律用語や、すでにある他の社会的構成要素や概念を参照しない方法で定義するのは非常に難しいのです。"
  },
  {
    "start": 1386892,
    "end": 1391126,
    "text": "これは、他の概念や用語のシステムと本質的に関連しているんだ。"
  },
  {
    "start": 1391308,
    "end": 1393546,
    "text": "コード・チェンジも、音楽で言えばこんな感じだよね？"
  },
  {
    "start": 1393568,
    "end": 1398954,
    "text": "コードや音符、五度圏とか、そういう話をしなければならない。"
  },
  {
    "start": 1399072,
    "end": 1400694,
    "text": "これらのことは本質的に関連しているんだ。"
  },
  {
    "start": 1400742,
    "end": 1403162,
    "text": "物理学における力とはこういうものだと思う。"
  },
  {
    "start": 1403296,
    "end": 1409534,
    "text": "実験や他の概念や物事と切り離して語るのはとても難しい。"
  },
  {
    "start": 1409572,
    "end": 1412702,
    "text": "ボビンはミシンで何をするんだ？"
  },
  {
    "start": 1412756,
    "end": 1416046,
    "text": "例えば、糸について話さなければならないし、縫製のプロセスについて話さなければならない。"
  },
  {
    "start": 1416078,
    "end": 1419860,
    "text": "ただ、これらのことの意味は、すべてが本質的に結びついている。"
  },
  {
    "start": 1421110,
    "end": 1425246,
    "text": "この考え方は、意味とは、参照とは関係ない。"
  },
  {
    "start": 1425278,
    "end": 1428790,
    "text": "概念役割理論とは、何かが果たす役割のことだ。"
  },
  {
    "start": 1429450,
    "end": 1433110,
    "text": "言葉や概念の意味は、それが果たす役割によって決まる。"
  },
  {
    "start": 1434250,
    "end": 1446870,
    "text": "これは、私の好きな論文のタイトルのひとつを書いた心の哲学者、ネッド・ブロックによって、おそらく最も顕著に主張されている。"
  },
  {
    "start": 1447030,
    "end": 1456346,
    "text": "心理学の意味論の広告で、基本的に心理学には意味論と意味理論が必要だという内容だ。"
  },
  {
    "start": 1456458,
    "end": 1459854,
    "text": "コンセプチュアルな役割という考え方は、それを可能にするものだ。"
  },
  {
    "start": 1459892,
    "end": 1462254,
    "text": "意味がどこから来るのかを説明することができる。"
  },
  {
    "start": 1462292,
    "end": 1474158,
    "text": "意味というものが、自分の表象やカテゴリーといったものにどのように依存するかという問題に取り組むことができる。"
  },
  {
    "start": 1474334,
    "end": 1478894,
    "text": "最も説得力があるのは、脳みそに意味を見出す方法を説明できることだろうね。"
  },
  {
    "start": 1478952,
    "end": 1488826,
    "text": "脳を開いてニューロンから記録を始めたとしても、そこに外界への参照があるということが何を意味するのか、実に不明だ。"
  },
  {
    "start": 1489008,
    "end": 1500990,
    "text": "もしかしたら、信号や表現のシステムを解釈できるような方法で、活動のパターンを理解できるかもしれない。"
  },
  {
    "start": 1502050,
    "end": 1508080,
    "text": "もうひとつ、物事をより明確にするかもしれない例を挙げよう。"
  },
  {
    "start": 1508610,
    "end": 1515418,
    "text": "この概念役割セマンティクスの考え方は、例えばコンピューターにおいて意味がどのように機能するかということでもあると思う。"
  },
  {
    "start": 1515604,
    "end": 1520974,
    "text": "また、私は数学で考えているので、数学に関する質問を先延ばしにしていた。"
  },
  {
    "start": 1521022,
    "end": 1522370,
    "text": "というようなことが考えられる。"
  },
  {
    "start": 1522440,
    "end": 1529246,
    "text": "これは浮動小数点表現であり、この表現におけるビットは何を意味するのか、何をするのかを問う。"
  },
  {
    "start": 1529368,
    "end": 1531174,
    "text": "特に、最初のビットは何を意味するのか？"
  },
  {
    "start": 1531212,
    "end": 1532182,
    "text": "サインビット。"
  },
  {
    "start": 1532316,
    "end": 1532614,
    "text": "そうだね。"
  },
  {
    "start": 1532652,
    "end": 1540950,
    "text": "なぜなら、浮動小数点数には何十種類もの規約があり、符号ビットはさまざまな場所に置かれてきたからだ。"
  },
  {
    "start": 1542510,
    "end": 1549866,
    "text": "符号ビットを意味するのは、それが浮動小数点数でできる他のすべての演算とどのように相互作用するかということである。"
  },
  {
    "start": 1549968,
    "end": 1550570,
    "text": "そうだね。"
  },
  {
    "start": 1550720,
    "end": 1555706,
    "text": "シンボルの意味、そして時にはシンボル同士の相互作用、言い換えればシンボルの概念的な役割から生まれることもある。"
  },
  {
    "start": 1555738,
    "end": 1557838,
    "text": "特に、否定は何をするのか？"
  },
  {
    "start": 1557924,
    "end": 1558318,
    "text": "そうだね。"
  },
  {
    "start": 1558404,
    "end": 1560494,
    "text": "否定演算子があれば、OKだ。"
  },
  {
    "start": 1560532,
    "end": 1561582,
    "text": "符号のビットが反転する。"
  },
  {
    "start": 1561636,
    "end": 1561902,
    "text": "素晴らしい。"
  },
  {
    "start": 1561956,
    "end": 1562560,
    "text": "オーケー。"
  },
  {
    "start": 1564210,
    "end": 1566066,
    "text": "そこに意味がある。"
  },
  {
    "start": 1566088,
    "end": 1566274,
    "text": "そうだね。"
  },
  {
    "start": 1566312,
    "end": 1567186,
    "text": "あるいは、足し算は何をするのか？"
  },
  {
    "start": 1567208,
    "end": 1573554,
    "text": "足し算は正弦ビットや掛け算、四捨五入などに関して正しいことをするのか？"
  },
  {
    "start": 1573672,
    "end": 1574050,
    "text": "そうだね。"
  },
  {
    "start": 1574120,
    "end": 1582630,
    "text": "これが浮動小数点表現であり、最初のビットが正弦を表すのは、表現そのものに内在するものではない。"
  },
  {
    "start": 1582700,
    "end": 1586440,
    "text": "それは、システムの他のすべての構成要素とどのように相互作用するかということだ。"
  },
  {
    "start": 1586890,
    "end": 1587494,
    "text": "そうだね。"
  },
  {
    "start": 1587612,
    "end": 1596140,
    "text": "このような意味論的な考え方と、階層的なアプローチ、つまり数字で概念を表すような考え方との違いを説明していただけますか？"
  },
  {
    "start": 1596910,
    "end": 1604402,
    "text": "ああ、確かに人々が持つ概念には上下関係があると思う。"
  },
  {
    "start": 1604486,
    "end": 1604686,
    "text": "そうだね。"
  },
  {
    "start": 1604708,
    "end": 1609118,
    "text": "犬は動物の一種であり、動物は生き物の一種である。"
  },
  {
    "start": 1609284,
    "end": 1615866,
    "text": "そのような図式に欠けているのは、私たちの表現が実際には計算オブジェクトのようなものだということだと思う。"
  },
  {
    "start": 1615898,
    "end": 1616798,
    "text": "何かをするようにね。"
  },
  {
    "start": 1616884,
    "end": 1617098,
    "text": "そうだね。"
  },
  {
    "start": 1617124,
    "end": 1622914,
    "text": "それらは互いに影響し合い、ある種の推論問題を解くことを可能にしてくれる。"
  },
  {
    "start": 1623112,
    "end": 1625658,
    "text": "あなたのコンセプトでできることのすべて。"
  },
  {
    "start": 1625694,
    "end": 1627286,
    "text": "トランプの例のようにね。"
  },
  {
    "start": 1627388,
    "end": 1628040,
    "text": "そうだろう？"
  },
  {
    "start": 1628970,
    "end": 1629334,
    "text": "そうだね。"
  },
  {
    "start": 1629372,
    "end": 1631778,
    "text": "上下関係がないという主張ではない。"
  },
  {
    "start": 1631874,
    "end": 1632182,
    "text": "そうだね。"
  },
  {
    "start": 1632236,
    "end": 1638366,
    "text": "興味深い、重要なことは、ある種の内部的な、概念間の相互作用から生まれるということだ。"
  },
  {
    "start": 1638418,
    "end": 1645690,
    "text": "記号のビットが興味深い、あるいは重要であるのは、否定や乗算といったものとの相互作用に由来する。"
  },
  {
    "start": 1648110,
    "end": 1656170,
    "text": "あなたの言っていることはまったく正しいが、私が問題だと思うのは、これを意味論の排他的な理論として買うことだ。"
  },
  {
    "start": 1656330,
    "end": 1660654,
    "text": "あなたがそれに対して正論を述べたようにね。"
  },
  {
    "start": 1660692,
    "end": 1662298,
    "text": "意味とは単なる参照である。"
  },
  {
    "start": 1662474,
    "end": 1663006,
    "text": "いいかい？"
  },
  {
    "start": 1663108,
    "end": 1675054,
    "text": "あなたはその説を否定したと思うが、今度は別の説を唱えようとしている。"
  },
  {
    "start": 1675102,
    "end": 1680274,
    "text": "子供たちの成長を見てみると、具体性判断に関する研究がある。"
  },
  {
    "start": 1680402,
    "end": 1690086,
    "text": "2歳児の語彙には、ミルクや哺乳瓶、ジャンプやお座りなど、具体的な単語がたくさんある。"
  },
  {
    "start": 1690118,
    "end": 1702058,
    "text": "視覚的な意味で具体的であり、運動プログラム的な意味で具体的である。"
  },
  {
    "start": 1702224,
    "end": 1705278,
    "text": "その方が、このコンセプチュアルなロード・ストーリーにぴったりだ。"
  },
  {
    "start": 1705364,
    "end": 1714980,
    "text": "一方、2歳の子供の語彙力は、感覚運動経験に根ざしたものである。"
  },
  {
    "start": 1715510,
    "end": 1717506,
    "text": "これは私にとって問題ではない。"
  },
  {
    "start": 1717528,
    "end": 1722158,
    "text": "なぜ私たちは、意味について一つの排他的な理論を持つ必要があるのか？"
  },
  {
    "start": 1722334,
    "end": 1725442,
    "text": "その中には意味の側面もある。"
  },
  {
    "start": 1725506,
    "end": 1727270,
    "text": "そうだね。"
  },
  {
    "start": 1727340,
    "end": 1735574,
    "text": "物理的な参照は、ある意味、何かが持ちうる概念的な役割のひとつと考えることができると思う。"
  },
  {
    "start": 1735612,
    "end": 1736200,
    "text": "そうだね。"
  },
  {
    "start": 1737130,
    "end": 1738214,
    "text": "それは重要なことだ。"
  },
  {
    "start": 1738332,
    "end": 1743642,
    "text": "その種の言葉について、子供たちが初期の段階でどの程度抽象的な意味を持っているのか、私たちはよく分かっていない。"
  },
  {
    "start": 1743696,
    "end": 1743866,
    "text": "そうだね。"
  },
  {
    "start": 1743888,
    "end": 1748490,
    "text": "というのも、少し抽象的でなければならないからだ。"
  },
  {
    "start": 1748560,
    "end": 1748794,
    "text": "そうだね。"
  },
  {
    "start": 1748832,
    "end": 1753342,
    "text": "あなたが見てきたボトルの例から離れて、抽象化されたものがある。"
  },
  {
    "start": 1753396,
    "end": 1760560,
    "text": "私もそう思う。序盤はとても具体的で、後になるにつれて抽象的でなくなっていくように感じる。"
  },
  {
    "start": 1763090,
    "end": 1775446,
    "text": "ただ、この理論が言っていることが正しい考え方であることを理解しようとしているんだ。意味は基本的に、あるものに対するある同型のようなものだと言っているわけだからね。"
  },
  {
    "start": 1775548,
    "end": 1778070,
    "text": "直感的か形式的な理論か。"
  },
  {
    "start": 1779530,
    "end": 1780280,
    "text": "もちろんだ。"
  },
  {
    "start": 1780970,
    "end": 1786690,
    "text": "では、その後に続く質問は、どの同型が有効であるかをどうやって知るのか、というようなものだろう。"
  },
  {
    "start": 1786770,
    "end": 1793820,
    "text": "というのも、もし私が任意の対応マッピングを持つことができれば、どんなものでも他の何にでも対応させることができるからだ。"
  },
  {
    "start": 1794830,
    "end": 1796218,
    "text": "ここでは何が許されるのか？"
  },
  {
    "start": 1796384,
    "end": 1799382,
    "text": "ええ、だから、誰もそこまで正式なことはしていないと思います。"
  },
  {
    "start": 1799446,
    "end": 1818340,
    "text": "パットナムのような人々は、物理システムにおける計算の理解についてこのような議論をしてきた。基本的には、脳や彼の例で言えば壁のような物理システムは非常に複雑であり、その状態とある種の任意の計算システムの状態を行き来するマッピングを思いつくことができる、と言っている。"
  },
  {
    "start": 1818950,
    "end": 1822226,
    "text": "それはおそらく、もっと長い話になるだろう。"
  },
  {
    "start": 1822248,
    "end": 1825138,
    "text": "ただ、それについては簡単には答えられないと思う。"
  },
  {
    "start": 1825224,
    "end": 1825860,
    "text": "そうだね。"
  },
  {
    "start": 1826470,
    "end": 1837190,
    "text": "そのような意味で形式化されたものではなく、どのような理論を探すべきかという点で、より高いレベルのものだと考えている。"
  },
  {
    "start": 1837260,
    "end": 1837638,
    "text": "そうだね。"
  },
  {
    "start": 1837724,
    "end": 1841670,
    "text": "となると、それを正確にするためにやるべきことはたくさんある。"
  },
  {
    "start": 1842650,
    "end": 1848758,
    "text": "クラインは実際に、1950年代の哲学のようなこの種の理論を動機づけるために、そのような例を用いている。"
  },
  {
    "start": 1848934,
    "end": 1850122,
    "text": "すみません、どの例ですか？"
  },
  {
    "start": 1850256,
    "end": 1851946,
    "text": "クワインはこの例を使っている。"
  },
  {
    "start": 1852048,
    "end": 1853626,
    "text": "彼はガバガイの例を使っている。"
  },
  {
    "start": 1853658,
    "end": 1870526,
    "text": "何かが飛び出してくるのを見て、ガバガイがウサギを意味するのでもなく、走りを意味するのでもなく、全体を意味するのでもなく、他の何かを意味するのでもないと、どうしてわかるんだ？"
  },
  {
    "start": 1870628,
    "end": 1872610,
    "text": "広範な記述。"
  },
  {
    "start": 1873270,
    "end": 1875326,
    "text": "以前から運用されていたのだろうか？"
  },
  {
    "start": 1875448,
    "end": 1876920,
    "text": "それについてコメントをいただけますか？"
  },
  {
    "start": 1877370,
    "end": 1878390,
    "text": "私はそうは思わない。"
  },
  {
    "start": 1878460,
    "end": 1889942,
    "text": "ああ、直観的な理論を学ぶ例もいくつかあるが、それらは基本的にこのような性格を持っている。"
  },
  {
    "start": 1890006,
    "end": 1896730,
    "text": "データを取得し、正しい関係に従う構造を考え出そうとする。"
  },
  {
    "start": 1896880,
    "end": 1897580,
    "text": "そうだね。"
  },
  {
    "start": 1899150,
    "end": 1903440,
    "text": "ええ、それについては少し話しますが、それについてはまだあまり研究が進んでいません。"
  },
  {
    "start": 1905570,
    "end": 1913710,
    "text": "この理論は、同じシンボルや言葉が異なる種類の理論や設定の中にある場合、どのように対処するのですか？"
  },
  {
    "start": 1914470,
    "end": 1920894,
    "text": "シンボル自体に意味がないということなのか、それとも異なる文脈の中でどのように意味が共有されているのか。"
  },
  {
    "start": 1921022,
    "end": 1928150,
    "text": "うん、だからそれは興味深い質問で、みんなあまり解決していないと思う。"
  },
  {
    "start": 1928220,
    "end": 1935730,
    "text": "あなたの父親に対するシンボルは、さまざまな役割を担っているかもしれない。"
  },
  {
    "start": 1935810,
    "end": 1936054,
    "text": "そうだろう？"
  },
  {
    "start": 1936092,
    "end": 1942250,
    "text": "父親がどんな仕事をしているか、家族関係や趣味を知っているからだ。"
  },
  {
    "start": 1943790,
    "end": 1949754,
    "text": "そのすべてをどのように理解すればいいのか、形式化された良い説明はないと思う。"
  },
  {
    "start": 1949872,
    "end": 1953710,
    "text": "概念的な役割を形式化するような素晴らしい理論はない。"
  },
  {
    "start": 1954610,
    "end": 1961130,
    "text": "言語モデルがこのようなことをするのは、少なくともごく小さなバージョンではあり得ると私が考える理由をいくつか挙げてみよう。"
  },
  {
    "start": 1961290,
    "end": 1967330,
    "text": "豊かで人間らしい概念的な役割という点では、解決するのが難しい重要な問題のひとつだと思う。"
  },
  {
    "start": 1968950,
    "end": 1969746,
    "text": "他にもありますか？"
  },
  {
    "start": 1969768,
    "end": 1992620,
    "text": "ええ、例えば、私たちが今使っているような人々の思考の腫瘍学は、人間の心の存在論のサブセットであり、おそらく将来発明される可能性のあるすべての概念などのサブセットでもある、と言いたかったのです。"
  },
  {
    "start": 1993150,
    "end": 1995594,
    "text": "申し訳ない、最初の部分を見逃していた。"
  },
  {
    "start": 1995632,
    "end": 1996282,
    "text": "質問は何だったのか？"
  },
  {
    "start": 1996336,
    "end": 1996602,
    "text": "パート？"
  },
  {
    "start": 1996656,
    "end": 2019470,
    "text": "あなたが今使っている既存の存在論は、人間の心の存在論の一部であり、私たちがまだ十分に探求していないものだと思いますか？"
  },
  {
    "start": 2019550,
    "end": 2021806,
    "text": "存在論というのは、これらの理論のことですか？"
  },
  {
    "start": 2021998,
    "end": 2024850,
    "text": "例えば、コンセプトとか？"
  },
  {
    "start": 2028090,
    "end": 2030390,
    "text": "どれが正解というわけではないと思う。"
  },
  {
    "start": 2030540,
    "end": 2030854,
    "text": "そうだね。"
  },
  {
    "start": 2030892,
    "end": 2039306,
    "text": "こういったことを解明するのは実はとても難しいんだけど、何か有益な方向性を指し示しているような気がするんだ。"
  },
  {
    "start": 2039408,
    "end": 2042060,
    "text": "質問の答えになっているかどうかわからない。"
  },
  {
    "start": 2045470,
    "end": 2046538,
    "text": "なぜそれが重要なのか？"
  },
  {
    "start": 2046624,
    "end": 2077160,
    "text": "というのも、ある意味を定義しさえすれば、言葉を使って表現しようが、Iを使って表現しようが、精神表現のようなどのシンボルを使おうが、表現しようが使おうが、その形があなたのものである限り、問題にはならないからだ。"
  },
  {
    "start": 2081050,
    "end": 2082440,
    "text": "念のため。"
  },
  {
    "start": 2082890,
    "end": 2085510,
    "text": "まだどこまでやるんだ？"
  },
  {
    "start": 2085660,
    "end": 2087078,
    "text": "まだ少し先がある。"
  },
  {
    "start": 2087164,
    "end": 2087474,
    "text": "オーケー。"
  },
  {
    "start": 2087532,
    "end": 2091370,
    "text": "この件は、後にしたほうがいいかもしれない。"
  },
  {
    "start": 2091440,
    "end": 2094774,
    "text": "もっと深い議論になりそうだからだ。"
  },
  {
    "start": 2094822,
    "end": 2095226,
    "text": "そうだね。"
  },
  {
    "start": 2095328,
    "end": 2096540,
    "text": "オーケー、素晴らしい。"
  },
  {
    "start": 2098430,
    "end": 2098842,
    "text": "オーケー。"
  },
  {
    "start": 2098896,
    "end": 2104954,
    "text": "こういった意味の説明について話したよね。"
  },
  {
    "start": 2105152,
    "end": 2108190,
    "text": "特に、概念的な役割としての意味である。"
  },
  {
    "start": 2108610,
    "end": 2115890,
    "text": "概念的な役割の学習と、それがもっともらしく、あるいは役に立つと考える理由について少し話をしよう。"
  },
  {
    "start": 2117510,
    "end": 2128870,
    "text": "少なくとも私には、大規模な言語モデルは、概念的な役割の一部を学習する必要があることは間違いないと思える。"
  },
  {
    "start": 2128940,
    "end": 2135298,
    "text": "首尾一貫した文章を書いたり、翻訳をしたり、定義を示したり、詳しく説明したりする。"
  },
  {
    "start": 2135394,
    "end": 2139814,
    "text": "これらのことはすべて、記号を他の記号と適切な関係に置く必要がある。"
  },
  {
    "start": 2139942,
    "end": 2140522,
    "text": "そうだね。"
  },
  {
    "start": 2140656,
    "end": 2147990,
    "text": "ということは、これらのことをうまくこなすには、本質的に、概念的な役割の小さな構成要素をいくつか持たなければならないということだ。"
  },
  {
    "start": 2148070,
    "end": 2148700,
    "text": "そうだろう？"
  },
  {
    "start": 2151390,
    "end": 2156126,
    "text": "これを考える一つの方法は、人間の意味や人間の概念的な役割がテキストを生み出したということだ。"
  },
  {
    "start": 2156228,
    "end": 2156494,
    "text": "そうだろう？"
  },
  {
    "start": 2156532,
    "end": 2165742,
    "text": "賢い推論モデルであれば、それを逆手にとって、私が見たものを生み出した概念的な役割は何であった可能性が高いかを見つけ出すことができるかもしれない。"
  },
  {
    "start": 2165876,
    "end": 2167326,
    "text": "私はこの香りの言葉が好きだ。"
  },
  {
    "start": 2167358,
    "end": 2167506,
    "text": "そうだろう？"
  },
  {
    "start": 2167528,
    "end": 2170254,
    "text": "文の構造は、思考の構造のイメージとして機能する。"
  },
  {
    "start": 2170302,
    "end": 2170562,
    "text": "そうだね。"
  },
  {
    "start": 2170616,
    "end": 2176670,
    "text": "私たちの思考や意味、概念的な役割の投影が、文章になる。"
  },
  {
    "start": 2176750,
    "end": 2177380,
    "text": "そうだね。"
  },
  {
    "start": 2184470,
    "end": 2184798,
    "text": "その"
  },
  {
    "start": 2184824,
    "end": 2185302,
    "text": "どの例だ。"
  },
  {
    "start": 2185356,
    "end": 2188620,
    "text": "すみません、リゼットとギルマンの2つの箱の例をもう一度説明するつもりですか？"
  },
  {
    "start": 2192030,
    "end": 2193738,
    "text": "いや、戻るつもりはなかった。"
  },
  {
    "start": 2193824,
    "end": 2194122,
    "text": "そうだね。"
  },
  {
    "start": 2194176,
    "end": 2197930,
    "text": "大規模な言語モデルの研究については、また後で話そう。"
  },
  {
    "start": 2199390,
    "end": 2200140,
    "text": "オーケー。"
  },
  {
    "start": 2201710,
    "end": 2203722,
    "text": "多くの人が、これは不可能だと直感している。"
  },
  {
    "start": 2203776,
    "end": 2210430,
    "text": "これはベンダーとマーカスの直感のようなもので、私たちの思考はこのような貧弱な音の連続に投影されるのだと思う。"
  },
  {
    "start": 2210500,
    "end": 2210734,
    "text": "そうだね。"
  },
  {
    "start": 2210772,
    "end": 2215362,
    "text": "そこに豊かな概念的役割のようなものを発見できるわけがないだろう？"
  },
  {
    "start": 2215496,
    "end": 2222290,
    "text": "言語という投影があるだけで、どうして豊かで興味深いコンセプトの役割をサポートすることができるだろうか？"
  },
  {
    "start": 2224470,
    "end": 2236870,
    "text": "数学的に正確な実装とかではないのですが、有用なアナロジーのひとつだと思います。"
  },
  {
    "start": 2237020,
    "end": 2250886,
    "text": "時系列からの幾何学と呼ばれる論文があるが、これは基本的に、力学系の投影を取り、その投影から力学の構造を捉えるものを復元できる場合があることを示している。"
  },
  {
    "start": 2251078,
    "end": 2255414,
    "text": "特にこの論文では、ロスラー・アトラクタというものを取り上げている。"
  },
  {
    "start": 2255542,
    "end": 2260826,
    "text": "これは3次元の微分方程式系である。"
  },
  {
    "start": 2261018,
    "end": 2268820,
    "text": "そこでできることは、そのダイナミクスを一次元的に投影して、そこで起こっていることのXロケーションだけを見ることだ。"
  },
  {
    "start": 2269270,
    "end": 2285106,
    "text": "巧妙なトリックを使えば、基本的に1次元を3次元に変換し、何段階か時間を逆行させることで、実際に1次元の投影からこの構造を復元することができる。"
  },
  {
    "start": 2285298,
    "end": 2286040,
    "text": "オーケー。"
  },
  {
    "start": 2286650,
    "end": 2293466,
    "text": "トールキンの埋め込み定理とか、そういう一般的な定理もある。"
  },
  {
    "start": 2293568,
    "end": 2301242,
    "text": "ここで言いたいのは、ある種の思考の投影から、何が可能かについて強い直感を持つべきではないということだ。"
  },
  {
    "start": 2301306,
    "end": 2301582,
    "text": "そうだろう？"
  },
  {
    "start": 2301636,
    "end": 2316580,
    "text": "というのも、学習モデルによって、あるシステムの単純な測定値から、そのシステムの構造の興味深い部分を再構築できることがよくあるからだ。"
  },
  {
    "start": 2316950,
    "end": 2341286,
    "text": "水滴が落ちるまでの時間を測定し、心理学の手法とよく似た手法を使って、潜在変数や潜在構造について解明する。"
  },
  {
    "start": 2341318,
    "end": 2352702,
    "text": "80年代にロジャー・シェパードが行った研究があるが、それは基本的に行動判断を行い、その背後にある根本的な構造を推測しようとするものだった。"
  },
  {
    "start": 2352756,
    "end": 2362202,
    "text": "例えば、このマトリクスは異なる色、つまり異なる波長の光であり、そして判断のタスクではそれらの混同が生じる。"
  },
  {
    "start": 2362266,
    "end": 2364034,
    "text": "これらはどのくらい似ているのだろうか？"
  },
  {
    "start": 2364072,
    "end": 2366180,
    "text": "あるいは、ある色と別の色がどれだけ混同しやすいか？"
  },
  {
    "start": 2367190,
    "end": 2376882,
    "text": "シェパードは多次元スケーリングを使って、このようなデータからこのような表現をしていた。"
  },
  {
    "start": 2376946,
    "end": 2377174,
    "text": "そうだね。"
  },
  {
    "start": 2377212,
    "end": 2393260,
    "text": "基本的には、その距離が混同行列の距離と一致するように点を並べることで、そのデータを生成した根本的な、この場合は心理的な構造について何かを復元することができる。"
  },
  {
    "start": 2395710,
    "end": 2406554,
    "text": "同じようなことは、理論や直感的な理論を実際に形式化したものを学ぶ際にも行われてきた。"
  },
  {
    "start": 2406602,
    "end": 2410090,
    "text": "トモール・ウルマンとノア・グッドマンによるこの論文はとても気に入っている。"
  },
  {
    "start": 2410170,
    "end": 2413886,
    "text": "次に話すジョシュは、磁気の理論を学んでいる。"
  },
  {
    "start": 2413998,
    "end": 2437074,
    "text": "つまり、基本的には、どの物体が他の物体と相互作用するのかを観察し、2つの異なる種類の磁性を持つ物体が存在し、その2つの異なる種類の物体は互いに作用し合うが、磁性を持たない物体とは作用しないという事実について、ある種の高度な理論を習得するための学習を行うのだ。"
  },
  {
    "start": 2437122,
    "end": 2437334,
    "text": "そうだろう？"
  },
  {
    "start": 2437372,
    "end": 2446170,
    "text": "これは、非常に単純で、相互作用に関する貧弱なデータから得られる、小さな小さな直感的理論のようなものだ。"
  },
  {
    "start": 2447230,
    "end": 2455254,
    "text": "だから、llmsが単にテキストに基づいているというだけでは、それがどのような理論を誘発するかについて何かを結論づけるには不十分だと思う。"
  },
  {
    "start": 2455302,
    "end": 2455478,
    "text": "そうだね。"
  },
  {
    "start": 2455504,
    "end": 2460494,
    "text": "あるいは、そのテキストからどのような内部構造や概念的な役割を誘発するのか。"
  },
  {
    "start": 2460692,
    "end": 2469790,
    "text": "そして実際、少なくともある種の単純な領域では、彼らが誘導していることがかなりもっともらしく見えるという証拠もある。"
  },
  {
    "start": 2469870,
    "end": 2481842,
    "text": "グランドとその同僚たちによるこの論文は、基本的に単語の埋め込みベクトルを調べ、それを例えば直感的な次元に投影したものだ。"
  },
  {
    "start": 2481906,
    "end": 2483960,
    "text": "ここにはたくさんの言葉がある。"
  },
  {
    "start": 2484330,
    "end": 2488630,
    "text": "大小を結ぶこの線に投影するのだ。"
  },
  {
    "start": 2488780,
    "end": 2489094,
    "text": "いいかい？"
  },
  {
    "start": 2489132,
    "end": 2494570,
    "text": "すべての高次元単語ベクトルは、大小線に投影される。"
  },
  {
    "start": 2494640,
    "end": 2499740,
    "text": "我々はこれを、異なる物体の大きさと小ささを測る方法と考える。"
  },
  {
    "start": 2500290,
    "end": 2513470,
    "text": "では、テキスト予測のみで訓練されたモデルにおいて、その投影は、根底にある概念空間について人間らしい何かを回復するのだろうか？"
  },
  {
    "start": 2513890,
    "end": 2515250,
    "text": "その通りだ。"
  },
  {
    "start": 2515320,
    "end": 2520926,
    "text": "ここに、X軸を意味的投影とした6つのプロットがある。"
  },
  {
    "start": 2521038,
    "end": 2528740,
    "text": "Y軸は、その物体がどれだけ小さいか大きいかを示す人間の評価である。"
  },
  {
    "start": 2529050,
    "end": 2532610,
    "text": "相関関係は完璧ではないが、ゴミでもないことがわかるだろう。"
  },
  {
    "start": 2532690,
    "end": 2532982,
    "text": "そうだね。"
  },
  {
    "start": 2533036,
    "end": 2547418,
    "text": "ウェットかドライか、大きいか小さいか、あるいは危険か安全か、このようなモデルには非常に強力だと思う。"
  },
  {
    "start": 2547504,
    "end": 2547802,
    "text": "そうだろう？"
  },
  {
    "start": 2547856,
    "end": 2556730,
    "text": "つまり、テキストを予測するだけで、単語ベクトル表現に潜在する意味構造のこの種の側面を回復したのだ。"
  },
  {
    "start": 2556810,
    "end": 2560394,
    "text": "ああ、でもこれはおそらくngramsに残っているんだ。"
  },
  {
    "start": 2560442,
    "end": 2562410,
    "text": "ビグラムでは、実際、その情報がある。"
  },
  {
    "start": 2562500,
    "end": 2563042,
    "text": "そうだね。"
  },
  {
    "start": 2563176,
    "end": 2565460,
    "text": "現実世界とは何の関係もない。"
  },
  {
    "start": 2566070,
    "end": 2568260,
    "text": "まあ、それは現実の世界と関係がある。"
  },
  {
    "start": 2571590,
    "end": 2576942,
    "text": "大小は言語的な構成要素であり、あなたはそれを言語でテストしているに過ぎない。"
  },
  {
    "start": 2577086,
    "end": 2577766,
    "text": "ああ、なるほど。"
  },
  {
    "start": 2577788,
    "end": 2582006,
    "text": "小虎対大虎とか言っているのが原因だと思っているのか。"
  },
  {
    "start": 2582188,
    "end": 2586310,
    "text": "子犬は小さく、虎は常に大きい。"
  },
  {
    "start": 2586380,
    "end": 2586662,
    "text": "そうだね。"
  },
  {
    "start": 2586716,
    "end": 2589558,
    "text": "Nグラムではそうかもしれない。"
  },
  {
    "start": 2589574,
    "end": 2589946,
    "text": "よく分からない。"
  },
  {
    "start": 2589968,
    "end": 2592220,
    "text": "そんなことは見ていないと思う。"
  },
  {
    "start": 2596030,
    "end": 2598218,
    "text": "でも、それが議論の妨げになるとは思わない。"
  },
  {
    "start": 2598304,
    "end": 2598602,
    "text": "そうだろう？"
  },
  {
    "start": 2598656,
    "end": 2605134,
    "text": "というのも、Ngramの統計でさえ、単語の関係についての統計だからだ。"
  },
  {
    "start": 2605252,
    "end": 2605966,
    "text": "そうだね。"
  },
  {
    "start": 2606148,
    "end": 2613540,
    "text": "このようなことをするのに高級な言語モデルなどは必要ないということかもしれないが、これが機能するのに実世界は必要ない。"
  },
  {
    "start": 2614950,
    "end": 2620462,
    "text": "さて、現実の世界では、スモールパピーとラージパピーという言葉をよく耳にする。"
  },
  {
    "start": 2620526,
    "end": 2620850,
    "text": "そうだろう？"
  },
  {
    "start": 2620920,
    "end": 2630100,
    "text": "そして、そのシステムが導き出すコンフィギュレーションもまた、現実世界の特性を反映したものなのだ。"
  },
  {
    "start": 2632410,
    "end": 2633366,
    "text": "彼らを押し返すことはできるか？"
  },
  {
    "start": 2633388,
    "end": 2634022,
    "text": "それもそうだ。"
  },
  {
    "start": 2634156,
    "end": 2640370,
    "text": "エイリアスが言っていることは正しいような気がする。これは大規模な言語モデルよりも、Nグラムにずっと近い。"
  },
  {
    "start": 2640450,
    "end": 2647174,
    "text": "私たちが見ている特性は、実際のエンベッディングのようなトリックとは比べものにならないほど荒々しい。"
  },
  {
    "start": 2647222,
    "end": 2649898,
    "text": "ああ、大規模な言語モデルはこれよりずっと賢いということか？"
  },
  {
    "start": 2650064,
    "end": 2652634,
    "text": "ある意味、どう比較できるのかさえわからない。"
  },
  {
    "start": 2652672,
    "end": 2652826,
    "text": "そうだね。"
  },
  {
    "start": 2652848,
    "end": 2658954,
    "text": "例えば、これは単なるPCAから飛び出してきたものであるのに対し、私たちは大規模な言語からこのような荒々しい創発的行動が生まれるのを見ている。"
  },
  {
    "start": 2659002,
    "end": 2662634,
    "text": "ああ、これでは野生の創発的行動を説明できないと思う。"
  },
  {
    "start": 2662682,
    "end": 2673662,
    "text": "これは、テキスト予測の訓練をするときに、テキスト統計に反映される世界の真の特性のいくつかと一致するように自分自身を構成するということを言いたかっただけだと思う。"
  },
  {
    "start": 2673806,
    "end": 2674740,
    "text": "それだけだ。"
  },
  {
    "start": 2677210,
    "end": 2678966,
    "text": "時間がないので省略する。"
  },
  {
    "start": 2678988,
    "end": 2691500,
    "text": "トランスフォーマーを研究している他の論文や、認知科学における概念に関する古典的な研究、古典的な効果の種類とトランスフォーマーがどう関係しているかを研究している論文もありますが、それは省略します。"
  },
  {
    "start": 2692590,
    "end": 2696134,
    "text": "このような楽しい実験を通して、ごく簡単に説明しようかな。"
  },
  {
    "start": 2696182,
    "end": 2707370,
    "text": "これは私の研究室のマーク・ゴレンスタインで、言語的経験から概念を学習することに興味を持っている。"
  },
  {
    "start": 2707530,
    "end": 2716326,
    "text": "彼は、空白のある自然言語の文章を人々に与えるという、ちょっとクールな実験をしているんだ。"
  },
  {
    "start": 2716378,
    "end": 2718014,
    "text": "ここに一節がある。"
  },
  {
    "start": 2718062,
    "end": 2724830,
    "text": "空白の神話は非常に強力で、その言葉そのものが、シュトゥルーデルの空白や、居心地の良い神々のカフェでの空白を思い起こさせる。"
  },
  {
    "start": 2724990,
    "end": 2730738,
    "text": "参加者の仕事は、ダックスという言葉をどこに置くかを学ぶことだ。"
  },
  {
    "start": 2730914,
    "end": 2734040,
    "text": "ダックスとは、彼らがこれまで出会ったことのない斬新な言葉である。"
  },
  {
    "start": 2735130,
    "end": 2744410,
    "text": "それを理解し、ダックスが舞台裏で密かにどこに行くべきかを見極めるには、これを読んで文脈などを理解しなければならない。"
  },
  {
    "start": 2745390,
    "end": 2753454,
    "text": "この例は、人々がおそらく知らないような、本当に珍しい単語の大きなテキスト・コーパスから選ばれたものだ。"
  },
  {
    "start": 2753652,
    "end": 2756830,
    "text": "ここでのレアワードはサッカー不法行為である。"
  },
  {
    "start": 2757330,
    "end": 2769810,
    "text": "ということは、この言葉は、サッカーの不法行為が実際に起こった場所と同じように、実際の人々から生み出されたものであり、おそらくサクラトートの根本的な意味や事柄を反映しているということだ。"
  },
  {
    "start": 2770310,
    "end": 2772830,
    "text": "その言葉が正しいかどうかも分からない。"
  },
  {
    "start": 2772990,
    "end": 2776834,
    "text": "このような人たちの例がたくさんあれば、ダックスの居場所もわかるだろう。"
  },
  {
    "start": 2776872,
    "end": 2783394,
    "text": "実際にサクロトートが出現した場所を選んだかどうかで、正解かどうかのフィードバックがもらえる。"
  },
  {
    "start": 2783522,
    "end": 2795050,
    "text": "では、この単語がどこに入るのか、予測タスクのようなものをやってもらいますが、実際には単語は見えません。"
  },
  {
    "start": 2795120,
    "end": 2800494,
    "text": "彼らはダックスの人たちがかなりまともになるのを見ている。"
  },
  {
    "start": 2800532,
    "end": 2804880,
    "text": "言葉によっては80％くらいまで。"
  },
  {
    "start": 2806850,
    "end": 2811710,
    "text": "これらは、未知のコンテクストを生成した単語の例である。"
  },
  {
    "start": 2812450,
    "end": 2814254,
    "text": "その後、私たちは彼らにたくさんの質問をした。"
  },
  {
    "start": 2814292,
    "end": 2816106,
    "text": "私たちは彼らに読解力を求めた。"
  },
  {
    "start": 2816218,
    "end": 2818430,
    "text": "彼らにダックスについての質問をした。"
  },
  {
    "start": 2818510,
    "end": 2818706,
    "text": "そうだね。"
  },
  {
    "start": 2818728,
    "end": 2820098,
    "text": "ダックスは人工物ですか？"
  },
  {
    "start": 2820184,
    "end": 2822094,
    "text": "生物学者は通常ダックスを研究するのですか？"
  },
  {
    "start": 2822142,
    "end": 2823870,
    "text": "ペインティングでダックスを使う人はいますか？"
  },
  {
    "start": 2824030,
    "end": 2828370,
    "text": "ただ、基本的な機能、コンセプトYのような質問を集めただけだ。"
  },
  {
    "start": 2828520,
    "end": 2830590,
    "text": "彼らに画像認識タスクを与える。"
  },
  {
    "start": 2830670,
    "end": 2831300,
    "text": "そうだね。"
  },
  {
    "start": 2831610,
    "end": 2836882,
    "text": "サッカーのトート、本物と代替品を選ぶ。"
  },
  {
    "start": 2837026,
    "end": 2839302,
    "text": "また、明確な定義を求めることもある。"
  },
  {
    "start": 2839366,
    "end": 2839594,
    "text": "そうだね。"
  },
  {
    "start": 2839632,
    "end": 2841510,
    "text": "これらの文脈は定義ではない。"
  },
  {
    "start": 2841590,
    "end": 2843770,
    "text": "サクロターとはこういうものだ、とは言っていない。"
  },
  {
    "start": 2843840,
    "end": 2847020,
    "text": "それは自然主義的な物の使い方だ。"
  },
  {
    "start": 2847550,
    "end": 2856186,
    "text": "私たちが実際に発見したのは、20回ほどのトライアルの範囲内である。"
  },
  {
    "start": 2856368,
    "end": 2859018,
    "text": "申し訳ないが、すべて20回のトライの後だ。"
  },
  {
    "start": 2859114,
    "end": 2864770,
    "text": "このようなコンセプトの特徴を判断するのは、実はとても得意なのだ。"
  },
  {
    "start": 2865110,
    "end": 2870146,
    "text": "私たちが質問するほとんどの種類の特徴的な質問において、ほぼ天井知らずだ。"
  },
  {
    "start": 2870328,
    "end": 2877218,
    "text": "ここに各単語を一列に並べ、X軸に特徴を示す。"
  },
  {
    "start": 2877394,
    "end": 2880006,
    "text": "ほとんどすべてが赤い。"
  },
  {
    "start": 2880028,
    "end": 2884598,
    "text": "また、どの写真が対象物かを選ぶのもうまい。"
  },
  {
    "start": 2884684,
    "end": 2884886,
    "text": "そうだね。"
  },
  {
    "start": 2884908,
    "end": 2893786,
    "text": "彼らは写真に遭遇したことがまったくないのに、8割かそこらはこういうものを選び出すのがうまいし、こういう用語の定義を与えるのもうまい。"
  },
  {
    "start": 2893888,
    "end": 2897002,
    "text": "じゃあ、辞書かウィッチナリーか何かをここに置いておこう。"
  },
  {
    "start": 2897056,
    "end": 2898358,
    "text": "サッカーの不法行為の定義"
  },
  {
    "start": 2898374,
    "end": 2906106,
    "text": "これはオーストリア発祥のチョコレートケーキで、1832年にフランツ・サッカーがウィーンの王子のために考案したと言われている。"
  },
  {
    "start": 2906298,
    "end": 2913242,
    "text": "そのうちの20人は、これらの文脈から、ウィーンで元々よく作られていたケーキに似たチョコレート・デザートであることを知るだろう。"
  },
  {
    "start": 2913306,
    "end": 2919890,
    "text": "オーストリアでデザートに注文できるチョコレートケーキの一種で、ウィーンなどの濃厚なチョコレートケーキのようなものだと思う。"
  },
  {
    "start": 2920040,
    "end": 2939100,
    "text": "しかし、それを味わうことは決してできない。"
  },
  {
    "start": 2940030,
    "end": 2941180,
    "text": "食べたことある？"
  },
  {
    "start": 2942670,
    "end": 2944140,
    "text": "聞いたことがなかった。"
  },
  {
    "start": 2944830,
    "end": 2946794,
    "text": "オーケー、ではここで終わりにしよう。"
  },
  {
    "start": 2946832,
    "end": 2957230,
    "text": "私は、このような概念的な役割や理論は、少なくとも現在の大規模言語モデルの長所でもあり短所でもあると考えている。"
  },
  {
    "start": 2957810,
    "end": 2963546,
    "text": "ひとつは、大規模な言語モデルは、浅いながらも幅広い理論を学習するのが得意なように見えるということですね。"
  },
  {
    "start": 2963588,
    "end": 2966014,
    "text": "靴はナスで作れるのか？"
  },
  {
    "start": 2966062,
    "end": 2968142,
    "text": "あるいは、もし靴がナスでできていたらどうなるだろうか？"
  },
  {
    "start": 2968206,
    "end": 2968578,
    "text": "そうだね。"
  },
  {
    "start": 2968664,
    "end": 2975622,
    "text": "そのようなことをすることで、どのような悪影響があるのかを知っているはずだ。"
  },
  {
    "start": 2975676,
    "end": 2975942,
    "text": "そうだろう？"
  },
  {
    "start": 2975996,
    "end": 2995674,
    "text": "あるいは、基本的な質問に答えるような場合、そのような状況に関係するオブジェクト間の関係について、1つか2つのリンクを通して推論することに頼るかもしれない。"
  },
  {
    "start": 2995792,
    "end": 3005742,
    "text": "驚くのは、これらのモデルが膨大な数の単語でトレーニングできることだろう。"
  },
  {
    "start": 3005796,
    "end": 3016770,
    "text": "というわけで、表面的には、膨大な数の単語の概念的な役割について少し知っているだけで、言語生成の面で説得力があるように見えるという点では、かなりのところまでいけるようだ。"
  },
  {
    "start": 3017350,
    "end": 3023426,
    "text": "このような概念的な役割や理論も弱点であり、強固で精密な理論はあまり得意ではないようですね？"
  },
  {
    "start": 3023448,
    "end": 3039498,
    "text": "数学のような概念的な役割について考えるなら、例えば自然数をどう定義するかとか、積分をどう定義するかとか、それらはすべて象徴的な種類の理論であり、正確で、任意の長さの推論の連鎖をサポートするものですよね？"
  },
  {
    "start": 3039584,
    "end": 3043706,
    "text": "それが、これらのシステムが本当に苦手としていることのようだ。"
  },
  {
    "start": 3043808,
    "end": 3053194,
    "text": "おそらくそれは、推論やより豊かな理論の基礎となるような重要なものが欠けているからだろう。"
  },
  {
    "start": 3053322,
    "end": 3057040,
    "text": "次はジョシュがこのことについて話すと思う。"
  },
  {
    "start": 3057890,
    "end": 3078054,
    "text": "認知心理学で概念や概念表現について研究している人たちにとって、概念や意味に対するより広い見方ができるようになったことは、本当に喜ばしいことだと思います。"
  },
  {
    "start": 3078092,
    "end": 3097226,
    "text": "特に、フォーダーやポリューションのような人々による、構成性や体系性、生産性についての議論は、人々が思考の特徴として指摘し、象徴的思考の特徴であると主張してきたこれらの種類のものすべてが、そうでないことが判明した。"
  },
  {
    "start": 3097248,
    "end": 3097578,
    "text": "そうだね。"
  },
  {
    "start": 3097664,
    "end": 3101066,
    "text": "ベクターにそれらをさせることができることがわかった。"
  },
  {
    "start": 3101248,
    "end": 3111454,
    "text": "ベクターがなぜそのようなことができるかというと、おそらくこれらのモデルが行っているのは、概念的な役割をエンコードするベクターをトレーニングすることなのだ、と私は主張したい。"
  },
  {
    "start": 3111492,
    "end": 3117918,
    "text": "彼らが学んでいるのは、概念的役割の重要な部分を捉えた意味の表象のようなものだ。"
  },
  {
    "start": 3118014,
    "end": 3123886,
    "text": "これは、例えば計算論的神経科学の分野では長い間求められてきたことだ。"
  },
  {
    "start": 3123998,
    "end": 3136338,
    "text": "ベクトルシンボリックアーキテクチャのように、任意の記号体系や任意の数学体系をベクトルにエンコードする非常にエキサイティングな方法がある。"
  },
  {
    "start": 3136514,
    "end": 3142890,
    "text": "この2つが結びつけば、とてもエキサイティングなことになると思う。"
  },
  {
    "start": 3144190,
    "end": 3150942,
    "text": "大規模な言語モデルは、本質的にベクトルベースの概念的役割に基づく意味の理論を指し示していますね？"
  },
  {
    "start": 3150996,
    "end": 3164526,
    "text": "おそらく、認知科学や認知発達学の人たちが人間の概念体系から引き出そうとしてきた、意味のさまざまな特徴の多くを捉えることができるだろう？"
  },
  {
    "start": 3164548,
    "end": 3181080,
    "text": "例えば、私たちの意味には勾配があるとか、階層があるとか、私たちは定義のようなものを知っていて、関係や類似性について推論することができるとか、そういったことはすべて、少なくとも原理的には、ベクトルにコード化できるように思える。"
  },
  {
    "start": 3181770,
    "end": 3184534,
    "text": "それは省略する。"
  },
  {
    "start": 3184572,
    "end": 3185782,
    "text": "これで終わりにしよう。"
  },
  {
    "start": 3185916,
    "end": 3191580,
    "text": "お誘いいただいたことに改めてお礼を申し上げるとともに、この作品に携わっている共同執筆者の皆さんにも感謝している。"
  },
  {
    "start": 3195630,
    "end": 3217010,
    "text": "ベクトル表現と大規模な言語モデルが、人間の認知と言語、言語の本質について何を教えてくれるのか、あなたは示唆しているように私には思えました。"
  },
  {
    "start": 3217750,
    "end": 3223940,
    "text": "投影測定をして、それについて何か言ってくれるように頼めるかな？"
  },
  {
    "start": 3225370,
    "end": 3231650,
    "text": "ベクターが本当にもっともらしいことを教えてくれていると思う。"
  },
  {
    "start": 3231730,
    "end": 3235218,
    "text": "ベクターがどのような意味を持つのかを教えてくれるようなものだ。"
  },
  {
    "start": 3235314,
    "end": 3235718,
    "text": "そうだね。"
  },
  {
    "start": 3235804,
    "end": 3241690,
    "text": "それが意味として妥当だと思うのは、概念的な役割をエンコードしているという点だ。"
  },
  {
    "start": 3242510,
    "end": 3243562,
    "text": "それが私の言いたいことだ。"
  },
  {
    "start": 3243616,
    "end": 3248906,
    "text": "それまでは、最近のディープラーニングのようなものまでは、それが本当に不明瞭だったと思うんだ。"
  },
  {
    "start": 3248928,
    "end": 3256090,
    "text": "概念の基礎は定義なのか、それとも何となく似ているのか、人々は何十年も議論してきた。"
  },
  {
    "start": 3256170,
    "end": 3261280,
    "text": "それとも、ある単語を知っているだけで、それに関連する特徴や何かをたくさん知っているということなのか？"
  },
  {
    "start": 3261970,
    "end": 3271010,
    "text": "例えば、大きな言語モデルから定義を抽出することができるというのが、主な洞察のひとつだと思います。"
  },
  {
    "start": 3271080,
    "end": 3278600,
    "text": "私たちが行った人体実験のようなものもいくつか与えたが、そこからチョコレートの不法行為のような定義を導き出すのはかなりうまい。"
  },
  {
    "start": 3278970,
    "end": 3283250,
    "text": "これは、定義がベクターにエンコードできることを示している。"
  },
  {
    "start": 3283330,
    "end": 3283622,
    "text": "そうだね。"
  },
  {
    "start": 3283676,
    "end": 3284760,
    "text": "それは素晴らしいことだ。"
  },
  {
    "start": 3285530,
    "end": 3291574,
    "text": "つまり、概念を定義する部分として定義を考える必要はないということだ。"
  },
  {
    "start": 3291622,
    "end": 3291786,
    "text": "そうだね。"
  },
  {
    "start": 3291808,
    "end": 3298326,
    "text": "もっと抽象的な高次元の空間か何かが意味を定義している。"
  },
  {
    "start": 3298358,
    "end": 3306122,
    "text": "その意味を定義する意味は、あなたがその概念を自然に使用するタスクにおけるベクトル間の関係という点である。"
  },
  {
    "start": 3306186,
    "end": 3312870,
    "text": "脳はたくさんのニューロンを発火させながら情報をコード化しているのだから、これは驚くべきことではない。"
  },
  {
    "start": 3312970,
    "end": 3314610,
    "text": "驚くことではない。"
  },
  {
    "start": 3315670,
    "end": 3318500,
    "text": "どうしてそんなことが可能なのか、いつも不明だった。"
  },
  {
    "start": 3320870,
    "end": 3321860,
    "text": "ああ、その通りだ。"
  },
  {
    "start": 3324230,
    "end": 3328770,
    "text": "こういったことをサポートできる継続的なシステムが必要だということは、誰もがなんとなくわかっていた。"
  },
  {
    "start": 3328840,
    "end": 3335110,
    "text": "言語における不連続性や数学における不連続性を見てみると、それがどこから来るのかが常に不明確だった。"
  },
  {
    "start": 3335180,
    "end": 3339080,
    "text": "だから、ベクター・シンボリック・アーキテクチャーのようなものも、とてもエキサイティングだと思うんだ。"
  },
  {
    "start": 3339530,
    "end": 3345850,
    "text": "人間が意味を補うとき、彼らは現実世界から得た多くの文脈を使っている。"
  },
  {
    "start": 3346000,
    "end": 3351850,
    "text": "タコが意味を埋めようとするとき、彼らには使える文脈がはるかに少ない。"
  },
  {
    "start": 3352000,
    "end": 3357278,
    "text": "LLMが意味を補うとき、彼らには何の文脈もない。"
  },
  {
    "start": 3357364,
    "end": 3360030,
    "text": "その違いについて何か考えていることはないかと思ったんだ。"
  },
  {
    "start": 3361730,
    "end": 3367746,
    "text": "その人体実験ではいったい何が起きているのか、それを考えるのは本当に興味深い。"
  },
  {
    "start": 3367768,
    "end": 3372578,
    "text": "ケーキに出会ったり、高級なペストリーに出会ったりとかね。"
  },
  {
    "start": 3372664,
    "end": 3377550,
    "text": "それらの意味についてあなたが知っていることの一部は、根拠のある部分である。"
  },
  {
    "start": 3377630,
    "end": 3377874,
    "text": "そうだね。"
  },
  {
    "start": 3377912,
    "end": 3383238,
    "text": "ケーキがどんなものか知っているからこそ、写真やいろいろなものがわかる。"
  },
  {
    "start": 3383404,
    "end": 3389778,
    "text": "地に足がついたものを移し替えるということがどういうことなのか、私にははっきりしないので、いつも少し考えあぐねている。"
  },
  {
    "start": 3389874,
    "end": 3394410,
    "text": "それが少しでも伝わるためには、少し抽象的でなければならないような気がする。"
  },
  {
    "start": 3395790,
    "end": 3409150,
    "text": "そして、人々がその問題をどのように解決しているのか、あるいは、それが概念的な役割に依存しているのか、地に足の着いた経験に依存しているのかなどについて、理論もなければ証拠もない。"
  },
  {
    "start": 3409300,
    "end": 3410894,
    "text": "では、もうひとつ質問させてください。"
  },
  {
    "start": 3410932,
    "end": 3414820,
    "text": "その間に、次の登壇者にセッティングを始めてもらおうかな。"
  },
  {
    "start": 3418150,
    "end": 3418514,
    "text": "そうだね。"
  },
  {
    "start": 3418552,
    "end": 3420642,
    "text": "スティーブ、素晴らしい話をありがとう。"
  },
  {
    "start": 3420776,
    "end": 3431742,
    "text": "というのも、このような概念埋め込み実験では、LLMに背が高いかどうかを聞けばいいように思えるからだ。"
  },
  {
    "start": 3431816,
    "end": 3436354,
    "text": "このプロジェクションがこのタスクをこなせるということを知るために、本当にこのプロジェクションをする必要はなかった。"
  },
  {
    "start": 3436402,
    "end": 3443980,
    "text": "出力ではなくエンベディングを見ているということは、何か特別なことなのでしょうか？"
  },
  {
    "start": 3444670,
    "end": 3446058,
    "text": "いい質問だね。"
  },
  {
    "start": 3446144,
    "end": 3448700,
    "text": "たぶんできると思うよ。"
  },
  {
    "start": 3449890,
    "end": 3454080,
    "text": "ただ頼んだ場合と頼まなかった場合の結果がどうなるかは分からない。"
  },
  {
    "start": 3456050,
    "end": 3457440,
    "text": "ああ、よくわからない。"
  },
  {
    "start": 3460050,
    "end": 3467780,
    "text": "ただ聞くだけでは成功しないのであれば、潜在的な表現がまだその情報を持っているのか、持っていないのかを知るのは興味深いことだ。"
  },
  {
    "start": 3469430,
    "end": 3475540,
    "text": "そのような疑問に対して、どのようにこれらのモデルを質問することができるのか、その全容を私は知らない。"
  },
  {
    "start": 3477210,
    "end": 3479720,
    "text": "よし、感謝しよう。"
  },
  {
    "start": 3483930,
    "end": 3491094,
    "text": "この講演の後のリフレッシュメントで、彼ともっと話す時間は十分にある。"
  },
  {
    "start": 3491132,
    "end": 3491874,
    "text": "誰が知っている？"
  },
  {
    "start": 3491922,
    "end": 3495622,
    "text": "もしかしたら、そこでザカールの拷問があるかもしれない。"
  },
  {
    "start": 3495676,
    "end": 3498120,
    "text": "もしウィーンにいるなら、絶対に試してみるべきだ。"
  },
  {
    "start": 3498570,
    "end": 3503582,
    "text": "というわけで、残念ながら、次のスピーカーはここに来ることができなかった。"
  },
  {
    "start": 3503636,
    "end": 3510814,
    "text": "ジョシュ・テネンバウムはこのセッションの潜在変数である。"
  },
  {
    "start": 3510852,
    "end": 3514860,
    "text": "スティーブンはジョシュの教え子だった。"
  }
]